Workbook

Sheet Léeme
A1: Anexo A — Cálculos del trabajo integrador (Analítica para Negocios, PP7, UNRC)
A3: Observatorio de la Economía del Cuidado — CDMX. Programa evaluado: Red de Cuidado a Domicilio «Manos que Cuidan» (escenario simulado).
A5: Hojas:
A6: Supuestos — todos los supuestos con su fuente. Cambia las celdas azules; las amarillas son las variables por escenario.
A7: Flujo Pesimista / Realista / Optimista — flujo mensual de 60 meses e indicadores (VAN, TIR, payback, punto de equilibrio, capital).
A8: Escenarios — tabla comparativa y valor esperado del VAN.
A9: Pronóstico oferta — serie semestral del DENUE 2016-2026, backtesting e intervalos del pronóstico.
A10: Modelo ENUT — coeficientes, calculadora por AGEB y métricas de validación del modelo de horas de cuidado.
A11: Riesgos — matriz de riesgos con mitigación.
A13: Colores: azul = dato o supuesto editable · negro = fórmula · verde = vínculo a otra hoja · relleno amarillo = supuesto clave.
A14: Unidades: pesos constantes de 2026; tasas reales. Negativos entre paréntesis.
A16: Se genera con notebooks/anexo_excel.py desde el notebook 03; las reglas son las de backend/observatorio/factibilidad.py.
... A24: Supuesto clave

Sheet Supuestos
A1: Supuestos del modelo financiero — Red de Cuidado a Domicilio «Manos que Cuidan» (escenario simulado)
A2: Pesos constantes de 2026. Celdas en azul: supuestos que se pueden cambiar. Relleno amarillo: variables clave por escenario.
A4: Variable que cambia por escenario | B4: Unidad | C4: Pesimista | D4: Realista | E4: Optimista | F4: Fuente o justificación
A5: Adopción en estado estable | B5: % de hogares con necesidad de cuidado | C5: 0.01 | D5: 0.02 | E5: 0.032 | F5: Anclada en la ENASIC 2022 (nacional): 3.2 % de las cuidadoras buscó un servicio formal en el último año; es el techo del escenario optimista.
A6: Horas contratadas por familia | B6: horas por semana | C6: 6 | D6: 8 | E6: 10 | F6: ENUT 2024: las mujeres de la CDMX que cuidan dedican 12.2 h a la semana; el servicio cubre la mitad o algo más.
A7: Subsidio público por hora | B7: pesos por hora | C7: 20 | D7: 40 | E7: 40 | F7: Supuesto de convenio con el Sistema Público de Cuidados de la CDMX (ley promulgada el 2 de julio de 2026). Sin convenio no hay subsidio.
A8: Meses para llegar al estado estable | B8: meses | C8: 24 | D8: 18 | E8: 12
A9: Probabilidad asignada | B9: % | C9: 0.3 | D9: 0.5 | E9: 0.2 | F9: Subjetiva y cargada hacia abajo: no hay historia del servicio y el subsidio depende de un convenio que no existe.
A10: Suma de probabilidades (debe ser 100 %) | C10: =SUM(C9:E9) -> 1
A12: Parámetro común | B12: Unidad | C12: Valor | F12: Fuente o justificación
A13: Hogares con necesidad de cuidado en la zona | B13: hogares | C13: 9415 | F13: Censo 2020 (25 AGEB de Iztapalapa sin respaldo) y ENUT 2024 (1.206 personas con necesidad de cuidado por hogar con necesidad).
A14: Copago de la familia | B14: $ por hora | C14: 60 | F14: Tarifa social, por debajo del mercado (≈ $142/h de una cuidadora de tiempo completo a $25,000 al mes en la CDMX).
A15: Pago bruto a la cuidadora | B15: $ por hora | C15: 55 | F15: 1.28 veces el salario mínimo profesional de las trabajadoras del hogar 2026 ($342.47 diarios, $42.81 por hora en jornada de 8 h).
A16: Prestaciones y seguridad social sobre el pago | B16: % | C16: 0.3 | F16: Seguridad social obligatoria del trabajo del hogar, aguinaldo y vacaciones.
A17: Seguro por hora, insumos y traslados | B17: $ por hora | C17: 3
A18: Jornada de una cuidadora de la red | B18: horas por semana | C18: 30
A19: Rotación mensual de cuidadoras | B19: % | C19: 0.03
A20: Capacitación y verificación por cuidadora nueva | B20: $ | C20: 3500
A21: Familias por trabajadora social | B21: familias | C21: 80
A22: Familias del piloto | B22: familias | C22: 15 | F22: Incidente crítico del PP: piloto de 2 colonias, 15 familias y 6 cuidadoras.
A23: Cuidadoras del piloto | B23: cuidadoras | C23: 6
A24: Duración del piloto | B24: meses | C24: 6
A25: Coordinadora del programa (con 35 % de carga social) | B25: $ al mes | C25: 29700
A26: Trabajadora social (con 35 % de carga social) | B26: $ al mes | C26: 24300
A27: Plataforma: hospedaje, mensajería y mantenimiento | B27: $ al mes | C27: 6000
A28: Póliza de responsabilidad civil | B28: $ al mes | C28: 3000
A29: Trabajo comunitario y difusión | B29: $ al mes | C29: 4000
A30: Contabilidad y facturación | B30: $ al mes | C30: 6000
A31: Inversión: adaptar la plataforma de vinculación | B31: $ | C31: 120000
A32: Inversión: protección de datos (LFPDPPP) | B32: $ | C32: 35000
A33: Inversión: equipamiento (kits, botiquines, teléfonos) | B33: $ | C33: 30000
A34: Inversión: lanzamiento en las colonias | B34: $ | C34: 20000
A35: Tasa de descuento real anual | B35: % | C35: 0.1 | F35: Tasa social de descuento de 10 % real (SHCP, Unidad de Inversiones, 2022).
A36: Colchón para imprevistos | B36: % | C36: 0.1
A37: Mes de revisión (decisión por etapas) | B37: mes | C37: 12
A38: Umbral para continuar (fracción de familias del punto de equilibrio) | B38: % | C38: 0.5
A39: Costo de cierre, en meses de costos fijos | B39: meses | C39: 2
A41: Derivado (fórmula) | B41: Unidad | C41: Valor | F41: Cómo se calcula
A42: Semanas por mes | B42: semanas | C42: =52/12 -> 4.3333333 | F42: 52 semanas ÷ 12 meses
A43: Costo variable por hora | B43: $ por hora | C43: =$C$15*(1+$C$16)+$C$17 -> 74.5 | F43: Pago × (1 + prestaciones) + insumos
A44: Costos fijos sin trabajadoras sociales | B44: $ al mes | C44: =$C$25+$C$27+$C$28+$C$29+$C$30 -> 48700 | F44: Coordinación + plataforma + seguro + difusión + administración
A45: Inversión inicial (mes 0) | B45: $ | C45: =$C$31+$C$32+$C$33+$C$34+$C$23*$C$20 -> 226000 | F45: Inversiones + capacitación de las cuidadoras del piloto
A46: Tasa de descuento mensual equivalente | B46: % | C46: =(1+$C$35)^(1/12)-1 -> 0.0079741404 | F46: (1 + tasa anual)^(1/12) − 1
A48: El horizonte es de 60 meses (vida útil de la plataforma y del equipo), sin valor de rescate. Cambiarlo requiere agregar o quitar filas en las hojas de flujo.

Sheet Flujo Pesimista
A1: Flujo mensual — escenario pesimista (pesos de 2026)
A2: Todas las celdas son fórmulas que leen la hoja «Supuestos» (texto verde: vínculo). Mes 0 = inversión inicial.
U3: Indicador | V3: Valor
U4: Escenario | V4: Pesimista
A5: Mes | B5: Familias | C5: Horas por semana | D5: Horas al mes | E5: Cuidadoras | F5: Cuidadoras nuevas (incluye rotación) | G5: Trabajadoras sociales | H5: Ingresos ($) | I5: Costo variable ($) | J5: Costos fijos ($) | K5: Capacitación ($) | L5: Inversión ($) | M5: Flujo neto ($) | N5: Flujo acumulado ($) | O5: Factor de descuento | P5: Flujo descontado ($) | Q5: Acumulado descontado ($) | R5: ¿Recuperado? | S5: ¿Recuperado (descontado)? | U5: Tarifa por hora (copago + subsidio) | V5: =Supuestos!$C$14+Supuestos!$C$7 -> 80
A6: 0 | B6: =IF(A6=0,0,IF(A6<=Supuestos!$C$24,Supuestos!$C$22,IF(A6>=Supuestos!$C$8,$V$7,Supuestos!$C$22+($V$7-Supuestos!$C$22)*(A6-Supuestos!$C$24)/(Supuestos!$C$8-Supuestos!$C$24)))) -> 0 | C6: =B6*Supuestos!$C$6 -> 0 | D6: =C6*Supuestos!$C$42 -> 0 | E6: =IF(A6=0,0,MAX(Supuestos!$C$23,ROUNDUP(C6/Supuestos!$C$18,0))) -> 0 | F6: 0 | G6: =IF(A6=0,0,MAX(1,ROUNDUP(B6/Supuestos!$C$21,0))) -> 0 | H6: =D6*(Supuestos!$C$14+Supuestos!$C$7) -> 0 | I6: =D6*Supuestos!$C$43 -> 0 | J6: =IF(A6=0,0,Supuestos!$C$44+G6*Supuestos!$C$26) -> 0 | K6: =F6*Supuestos!$C$20 -> 0 | L6: =IF(A6=0,Supuestos!$C$45,0) -> 226000 | M6: =IF(A6=0,-L6,H6-I6-J6-K6) -> -226000 | N6: =M6 -> -226000 | O6: =1/(1+Supuestos!$C$46)^A6 -> 1 | P6: =M6*O6 -> -226000 | Q6: =P6 -> -226000 | R6: =IF(AND(A6>0,N6>=0),1,0) -> 0 | S6: =IF(AND(A6>0,Q6>=0),1,0) -> 0 | U6: Margen por hora | V6: =V5-Supuestos!$C$43 -> 5.5
A7: 1 | B7: =IF(A7=0,0,IF(A7<=Supuestos!$C$24,Supuestos!$C$22,IF(A7>=Supuestos!$C$8,$V$7,Supuestos!$C$22+($V$7-Supuestos!$C$22)*(A7-Supuestos!$C$24)/(Supuestos!$C$8-Supuestos!$C$24)))) -> 15 | C7: =B7*Supuestos!$C$6 -> 90 | D7: =C7*Supuestos!$C$42 -> 390 | E7: =IF(A7=0,0,MAX(Supuestos!$C$23,ROUNDUP(C7/Supuestos!$C$18,0))) -> 6 | F7: =MAX(0,E7-IF(A6=0,Supuestos!$C$23,E6))+Supuestos!$C$19*E7 -> 0.18 | G7: =IF(A7=0,0,MAX(1,ROUNDUP(B7/Supuestos!$C$21,0))) -> 1 | H7: =D7*(Supuestos!$C$14+Supuestos!$C$7) -> 31200 | I7: =D7*Supuestos!$C$43 -> 29055 | J7: =IF(A7=0,0,Supuestos!$C$44+G7*Supuestos!$C$26) -> 73000 | K7: =F7*Supuestos!$C$20 -> 630 | L7: =IF(A7=0,Supuestos!$C$45,0) -> 0 | M7: =IF(A7=0,-L7,H7-I7-J7-K7) -> -71485 | N7: =N6+M7 -> -297485 | O7: =1/(1+Supuestos!$C$46)^A7 -> 0.99208894 | P7: =M7*O7 -> -70919.478 | Q7: =Q6+P7 -> -296919.48 | R7: =IF(AND(A7>0,N7>=0),1,0) -> 0 | S7: =IF(AND(A7>0,Q7>=0),1,0) -> 0 | U7: Familias objetivo (estado estable) | V7: =MAX(Supuestos!$C$13*Supuestos!$C$5,Supuestos!$C$22) -> 94.15
A8: 2 | B8: =IF(A8=0,0,IF(A8<=Supuestos!$C$24,Supuestos!$C$22,IF(A8>=Supuestos!$C$8,$V$7,Supuestos!$C$22+($V$7-Supuestos!$C$22)*(A8-Supuestos!$C$24)/(Supuestos!$C$8-Supuestos!$C$24)))) -> 15 | C8: =B8*Supuestos!$C$6 -> 90 | D8: =C8*Supuestos!$C$42 -> 390 | E8: =IF(A8=0,0,MAX(Supuestos!$C$23,ROUNDUP(C8/Supuestos!$C$18,0))) -> 6 | F8: =MAX(0,E8-IF(A7=0,Supuestos!$C$23,E7))+Supuestos!$C$19*E8 -> 0.18 | G8: =IF(A8=0,0,MAX(1,ROUNDUP(B8/Supuestos!$C$21,0))) -> 1 | H8: =D8*(Supuestos!$C$14+Supuestos!$C$7) -> 31200 | I8: =D8*Supuestos!$C$43 -> 29055 | J8: =IF(A8=0,0,Supuestos!$C$44+G8*Supuestos!$C$26) -> 73000 | K8: =F8*Supuestos!$C$20 -> 630 | L8: =IF(A8=0,Supuestos!$C$45,0) -> 0 | M8: =IF(A8=0,-L8,H8-I8-J8-K8) -> -71485 | N8: =N7+M8 -> -368970 | O8: =1/(1+Supuestos!$C$46)^A8 -> 0.98424047 | P8: =M8*O8 -> -70358.43 | Q8: =Q7+P8 -> -367277.91 | R8: =IF(AND(A8>0,N8>=0),1,0) -> 0 | S8: =IF(AND(A8>0,Q8>=0),1,0) -> 0 | U8: VAN a la tasa de descuento | V8: =SUM(P6:P66) -> -4031953.4
A9: 3 | B9: =IF(A9=0,0,IF(A9<=Supuestos!$C$24,Supuestos!$C$22,IF(A9>=Supuestos!$C$8,$V$7,Supuestos!$C$22+($V$7-Supuestos!$C$22)*(A9-Supuestos!$C$24)/(Supuestos!$C$8-Supuestos!$C$24)))) -> 15 | C9: =B9*Supuestos!$C$6 -> 90 | D9: =C9*Supuestos!$C$42 -> 390 | E9: =IF(A9=0,0,MAX(Supuestos!$C$23,ROUNDUP(C9/Supuestos!$C$18,0))) -> 6 | F9: =MAX(0,E9-IF(A8=0,Supuestos!$C$23,E8))+Supuestos!$C$19*E9 -> 0.18 | G9: =IF(A9=0,0,MAX(1,ROUNDUP(B9/Supuestos!$C$21,0))) -> 1 | H9: =D9*(Supuestos!$C$14+Supuestos!$C$7) -> 31200 | I9: =D9*Supuestos!$C$43 -> 29055 | J9: =IF(A9=0,0,Supuestos!$C$44+G9*Supuestos!$C$26) -> 73000 | K9: =F9*Supuestos!$C$20 -> 630 | L9: =IF(A9=0,Supuestos!$C$45,0) -> 0 | M9: =IF(A9=0,-L9,H9-I9-J9-K9) -> -71485 | N9: =N8+M9 -> -440455 | O9: =1/(1+Supuestos!$C$46)^A9 -> 0.97645409 | P9: =M9*O9 -> -69801.821 | Q9: =Q8+P9 -> -437079.73 | R9: =IF(AND(A9>0,N9>=0),1,0) -> 0 | S9: =IF(AND(A9>0,Q9>=0),1,0) -> 0 | U9: TIR mensual | V9: =IFERROR(IRR(M6:M66,0.02),"No existe") -> No existe
A10: 4 | B10: =IF(A10=0,0,IF(A10<=Supuestos!$C$24,Supuestos!$C$22,IF(A10>=Supuestos!$C$8,$V$7,Supuestos!$C$22+($V$7-Supuestos!$C$22)*(A10-Supuestos!$C$24)/(Supuestos!$C$8-Supuestos!$C$24)))) -> 15 | C10: =B10*Supuestos!$C$6 -> 90 | D10: =C10*Supuestos!$C$42 -> 390 | E10: =IF(A10=0,0,MAX(Supuestos!$C$23,ROUNDUP(C10/Supuestos!$C$18,0))) -> 6 | F10: =MAX(0,E10-IF(A9=0,Supuestos!$C$23,E9))+Supuestos!$C$19*E10 -> 0.18 | G10: =IF(A10=0,0,MAX(1,ROUNDUP(B10/Supuestos!$C$21,0))) -> 1 | H10: =D10*(Supuestos!$C$14+Supuestos!$C$7) -> 31200 | I10: =D10*Supuestos!$C$43 -> 29055 | J10: =IF(A10=0,0,Supuestos!$C$44+G10*Supuestos!$C$26) -> 73000 | K10: =F10*Supuestos!$C$20 -> 630 | L10: =IF(A10=0,Supuestos!$C$45,0) -> 0 | M10: =IF(A10=0,-L10,H10-I10-J10-K10) -> -71485 | N10: =N9+M10 -> -511940 | O10: =1/(1+Supuestos!$C$46)^A10 -> 0.96872931 | P10: =M10*O10 -> -69249.614 | Q10: =Q9+P10 -> -506329.34 | R10: =IF(AND(A10>0,N10>=0),1,0) -> 0 | S10: =IF(AND(A10>0,Q10>=0),1,0) -> 0 | U10: TIR anual equivalente | V10: =IFERROR((1+V9)^12-1,"No existe") -> No existe
A11: 5 | B11: =IF(A11=0,0,IF(A11<=Supuestos!$C$24,Supuestos!$C$22,IF(A11>=Supuestos!$C$8,$V$7,Supuestos!$C$22+($V$7-Supuestos!$C$22)*(A11-Supuestos!$C$24)/(Supuestos!$C$8-Supuestos!$C$24)))) -> 15 | C11: =B11*Supuestos!$C$6 -> 90 | D11: =C11*Supuestos!$C$42 -> 390 | E11: =IF(A11=0,0,MAX(Supuestos!$C$23,ROUNDUP(C11/Supuestos!$C$18,0))) -> 6 | F11: =MAX(0,E11-IF(A10=0,Supuestos!$C$23,E10))+Supuestos!$C$19*E11 -> 0.18 | G11: =IF(A11=0,0,MAX(1,ROUNDUP(B11/Supuestos!$C$21,0))) -> 1 | H11: =D11*(Supuestos!$C$14+Supuestos!$C$7) -> 31200 | I11: =D11*Supuestos!$C$43 -> 29055 | J11: =IF(A11=0,0,Supuestos!$C$44+G11*Supuestos!$C$26) -> 73000 | K11: =F11*Supuestos!$C$20 -> 630 | L11: =IF(A11=0,Supuestos!$C$45,0) -> 0 | M11: =IF(A11=0,-L11,H11-I11-J11-K11) -> -71485 | N11: =N10+M11 -> -583425 | O11: =1/(1+Supuestos!$C$46)^A11 -> 0.96106563 | P11: =M11*O11 -> -68701.777 | Q11: =Q10+P11 -> -575031.12 | R11: =IF(AND(A11>0,N11>=0),1,0) -> 0 | S11: =IF(AND(A11>0,Q11>=0),1,0) -> 0 | U11: Payback (meses) | V11: =IFERROR(INDEX(A6:A66,MATCH(1,R6:R66,0)),"No se recupera") -> No se recupera
A12: 6 | B12: =IF(A12=0,0,IF(A12<=Supuestos!$C$24,Supuestos!$C$22,IF(A12>=Supuestos!$C$8,$V$7,Supuestos!$C$22+($V$7-Supuestos!$C$22)*(A12-Supuestos!$C$24)/(Supuestos!$C$8-Supuestos!$C$24)))) -> 15 | C12: =B12*Supuestos!$C$6 -> 90 | D12: =C12*Supuestos!$C$42 -> 390 | E12: =IF(A12=0,0,MAX(Supuestos!$C$23,ROUNDUP(C12/Supuestos!$C$18,0))) -> 6 | F12: =MAX(0,E12-IF(A11=0,Supuestos!$C$23,E11))+Supuestos!$C$19*E12 -> 0.18 | G12: =IF(A12=0,0,MAX(1,ROUNDUP(B12/Supuestos!$C$21,0))) -> 1 | H12: =D12*(Supuestos!$C$14+Supuestos!$C$7) -> 31200 | I12: =D12*Supuestos!$C$43 -> 29055 | J12: =IF(A12=0,0,Supuestos!$C$44+G12*Supuestos!$C$26) -> 73000 | K12: =F12*Supuestos!$C$20 -> 630 | L12: =IF(A12=0,Supuestos!$C$45,0) -> 0 | M12: =IF(A12=0,-L12,H12-I12-J12-K12) -> -71485 | N12: =N11+M12 -> -654910 | O12: =1/(1+Supuestos!$C$46)^A12 -> 0.95346259 | P12: =M12*O12 -> -68158.273 | Q12: =Q11+P12 -> -643189.39 | R12: =IF(AND(A12>0,N12>=0),1,0) -> 0 | S12: =IF(AND(A12>0,Q12>=0),1,0) -> 0 | U12: Payback descontado (meses) | V12: =IFERROR(INDEX(A6:A66,MATCH(1,S6:S66,0)),"No se recupera") -> No se recupera
A13: 7 | B13: =IF(A13=0,0,IF(A13<=Supuestos!$C$24,Supuestos!$C$22,IF(A13>=Supuestos!$C$8,$V$7,Supuestos!$C$22+($V$7-Supuestos!$C$22)*(A13-Supuestos!$C$24)/(Supuestos!$C$8-Supuestos!$C$24)))) -> 19.397222 | C13: =B13*Supuestos!$C$6 -> 116.38333 | D13: =C13*Supuestos!$C$42 -> 504.32778 | E13: =IF(A13=0,0,MAX(Supuestos!$C$23,ROUNDUP(C13/Supuestos!$C$18,0))) -> 6 | F13: =MAX(0,E13-IF(A12=0,Supuestos!$C$23,E12))+Supuestos!$C$19*E13 -> 0.18 | G13: =IF(A13=0,0,MAX(1,ROUNDUP(B13/Supuestos!$C$21,0))) -> 1 | H13: =D13*(Supuestos!$C$14+Supuestos!$C$7) -> 40346.222 | I13: =D13*Supuestos!$C$43 -> 37572.419 | J13: =IF(A13=0,0,Supuestos!$C$44+G13*Supuestos!$C$26) -> 73000 | K13: =F13*Supuestos!$C$20 -> 630 | L13: =IF(A13=0,Supuestos!$C$45,0) -> 0 | M13: =IF(A13=0,-L13,H13-I13-J13-K13) -> -70856.197 | N13: =N12+M13 -> -725766.2 | O13: =1/(1+Supuestos!$C$46)^A13 -> 0.94591969 | P13: =M13*O13 -> -67024.272 | Q13: =Q12+P13 -> -710213.67 | R13: =IF(AND(A13>0,N13>=0),1,0) -> 0 | S13: =IF(AND(A13>0,Q13>=0),1,0) -> 0 | U13: Costos fijos en estado estable | V13: =J66 -> 97300
A14: 8 | B14: =IF(A14=0,0,IF(A14<=Supuestos!$C$24,Supuestos!$C$22,IF(A14>=Supuestos!$C$8,$V$7,Supuestos!$C$22+($V$7-Supuestos!$C$22)*(A14-Supuestos!$C$24)/(Supuestos!$C$8-Supuestos!$C$24)))) -> 23.794444 | C14: =B14*Supuestos!$C$6 -> 142.76667 | D14: =C14*Supuestos!$C$42 -> 618.65556 | E14: =IF(A14=0,0,MAX(Supuestos!$C$23,ROUNDUP(C14/Supuestos!$C$18,0))) -> 6 | F14: =MAX(0,E14-IF(A13=0,Supuestos!$C$23,E13))+Supuestos!$C$19*E14 -> 0.18 | G14: =IF(A14=0,0,MAX(1,ROUNDUP(B14/Supuestos!$C$21,0))) -> 1 | H14: =D14*(Supuestos!$C$14+Supuestos!$C$7) -> 49492.444 | I14: =D14*Supuestos!$C$43 -> 46089.839 | J14: =IF(A14=0,0,Supuestos!$C$44+G14*Supuestos!$C$26) -> 73000 | K14: =F14*Supuestos!$C$20 -> 630 | L14: =IF(A14=0,Supuestos!$C$45,0) -> 0 | M14: =IF(A14=0,-L14,H14-I14-J14-K14) -> -70227.394 | N14: =N13+M14 -> -795993.59 | O14: =1/(1+Supuestos!$C$46)^A14 -> 0.93843647 | P14: =M14*O14 -> -65903.948 | Q14: =Q13+P14 -> -776117.61 | R14: =IF(AND(A14>0,N14>=0),1,0) -> 0 | S14: =IF(AND(A14>0,Q14>=0),1,0) -> 0 | U14: Punto de equilibrio (horas al mes) | V14: =IF(V6>0,V13/V6,"No existe") -> 17690.909
A15: 9 | B15: =IF(A15=0,0,IF(A15<=Supuestos!$C$24,Supuestos!$C$22,IF(A15>=Supuestos!$C$8,$V$7,Supuestos!$C$22+($V$7-Supuestos!$C$22)*(A15-Supuestos!$C$24)/(Supuestos!$C$8-Supuestos!$C$24)))) -> 28.191667 | C15: =B15*Supuestos!$C$6 -> 169.15 | D15: =C15*Supuestos!$C$42 -> 732.98333 | E15: =IF(A15=0,0,MAX(Supuestos!$C$23,ROUNDUP(C15/Supuestos!$C$18,0))) -> 6 | F15: =MAX(0,E15-IF(A14=0,Supuestos!$C$23,E14))+Supuestos!$C$19*E15 -> 0.18 | G15: =IF(A15=0,0,MAX(1,ROUNDUP(B15/Supuestos!$C$21,0))) -> 1 | H15: =D15*(Supuestos!$C$14+Supuestos!$C$7) -> 58638.667 | I15: =D15*Supuestos!$C$43 -> 54607.258 | J15: =IF(A15=0,0,Supuestos!$C$44+G15*Supuestos!$C$26) -> 73000 | K15: =F15*Supuestos!$C$20 -> 630 | L15: =IF(A15=0,Supuestos!$C$45,0) -> 0 | M15: =IF(A15=0,-L15,H15-I15-J15-K15) -> -69598.592 | N15: =N14+M15 -> -865592.18 | O15: =1/(1+Supuestos!$C$46)^A15 -> 0.93101244 | P15: =M15*O15 -> -64797.155 | Q15: =Q14+P15 -> -840914.77 | R15: =IF(AND(A15>0,N15>=0),1,0) -> 0 | S15: =IF(AND(A15>0,Q15>=0),1,0) -> 0 | U15: Punto de equilibrio (familias) | V15: =IF(V6>0,V14/Supuestos!$C$42/Supuestos!$C$6,"No existe") -> 680.41958
A16: 10 | B16: =IF(A16=0,0,IF(A16<=Supuestos!$C$24,Supuestos!$C$22,IF(A16>=Supuestos!$C$8,$V$7,Supuestos!$C$22+($V$7-Supuestos!$C$22)*(A16-Supuestos!$C$24)/(Supuestos!$C$8-Supuestos!$C$24)))) -> 32.588889 | C16: =B16*Supuestos!$C$6 -> 195.53333 | D16: =C16*Supuestos!$C$42 -> 847.31111 | E16: =IF(A16=0,0,MAX(Supuestos!$C$23,ROUNDUP(C16/Supuestos!$C$18,0))) -> 7 | F16: =MAX(0,E16-IF(A15=0,Supuestos!$C$23,E15))+Supuestos!$C$19*E16 -> 1.21 | G16: =IF(A16=0,0,MAX(1,ROUNDUP(B16/Supuestos!$C$21,0))) -> 1 | H16: =D16*(Supuestos!$C$14+Supuestos!$C$7) -> 67784.889 | I16: =D16*Supuestos!$C$43 -> 63124.678 | J16: =IF(A16=0,0,Supuestos!$C$44+G16*Supuestos!$C$26) -> 73000 | K16: =F16*Supuestos!$C$20 -> 4235 | L16: =IF(A16=0,Supuestos!$C$45,0) -> 0 | M16: =IF(A16=0,-L16,H16-I16-J16-K16) -> -72574.789 | N16: =N15+M16 -> -938166.97 | O16: =1/(1+Supuestos!$C$46)^A16 -> 0.92364715 | P16: =M16*O16 -> -67033.497 | Q16: =Q15+P16 -> -907948.27 | R16: =IF(AND(A16>0,N16>=0),1,0) -> 0 | S16: =IF(AND(A16>0,Q16>=0),1,0) -> 0 | U16: Utilidad neta acumulada (60 meses) | V16: =N66 -> -5078090.5
A17: 11 | B17: =IF(A17=0,0,IF(A17<=Supuestos!$C$24,Supuestos!$C$22,IF(A17>=Supuestos!$C$8,$V$7,Supuestos!$C$22+($V$7-Supuestos!$C$22)*(A17-Supuestos!$C$24)/(Supuestos!$C$8-Supuestos!$C$24)))) -> 36.986111 | C17: =B17*Supuestos!$C$6 -> 221.91667 | D17: =C17*Supuestos!$C$42 -> 961.63889 | E17: =IF(A17=0,0,MAX(Supuestos!$C$23,ROUNDUP(C17/Supuestos!$C$18,0))) -> 8 | F17: =MAX(0,E17-IF(A16=0,Supuestos!$C$23,E16))+Supuestos!$C$19*E17 -> 1.24 | G17: =IF(A17=0,0,MAX(1,ROUNDUP(B17/Supuestos!$C$21,0))) -> 1 | H17: =D17*(Supuestos!$C$14+Supuestos!$C$7) -> 76931.111 | I17: =D17*Supuestos!$C$43 -> 71642.097 | J17: =IF(A17=0,0,Supuestos!$C$44+G17*Supuestos!$C$26) -> 73000 | K17: =F17*Supuestos!$C$20 -> 4340 | L17: =IF(A17=0,Supuestos!$C$45,0) -> 0 | M17: =IF(A17=0,-L17,H17-I17-J17-K17) -> -72050.986 | N17: =N16+M17 -> -1010218 | O17: =1/(1+Supuestos!$C$46)^A17 -> 0.91634013 | P17: =M17*O17 -> -66023.21 | Q17: =Q16+P17 -> -973971.48 | R17: =IF(AND(A17>0,N17>=0),1,0) -> 0 | S17: =IF(AND(A17>0,Q17>=0),1,0) -> 0 | U17: Inversión inicial | V17: =L6 -> 226000
A18: 12 | B18: =IF(A18=0,0,IF(A18<=Supuestos!$C$24,Supuestos!$C$22,IF(A18>=Supuestos!$C$8,$V$7,Supuestos!$C$22+($V$7-Supuestos!$C$22)*(A18-Supuestos!$C$24)/(Supuestos!$C$8-Supuestos!$C$24)))) -> 41.383333 | C18: =B18*Supuestos!$C$6 -> 248.3 | D18: =C18*Supuestos!$C$42 -> 1075.9667 | E18: =IF(A18=0,0,MAX(Supuestos!$C$23,ROUNDUP(C18/Supuestos!$C$18,0))) -> 9 | F18: =MAX(0,E18-IF(A17=0,Supuestos!$C$23,E17))+Supuestos!$C$19*E18 -> 1.27 | G18: =IF(A18=0,0,MAX(1,ROUNDUP(B18/Supuestos!$C$21,0))) -> 1 | H18: =D18*(Supuestos!$C$14+Supuestos!$C$7) -> 86077.333 | I18: =D18*Supuestos!$C$43 -> 80159.517 | J18: =IF(A18=0,0,Supuestos!$C$44+G18*Supuestos!$C$26) -> 73000 | K18: =F18*Supuestos!$C$20 -> 4445 | L18: =IF(A18=0,Supuestos!$C$45,0) -> 0 | M18: =IF(A18=0,-L18,H18-I18-J18-K18) -> -71527.183 | N18: =N17+M18 -> -1081745.1 | O18: =1/(1+Supuestos!$C$46)^A18 -> 0.90909091 | P18: =M18*O18 -> -65024.712 | Q18: =Q17+P18 -> -1038996.2 | R18: =IF(AND(A18>0,N18>=0),1,0) -> 0 | S18: =IF(AND(A18>0,Q18>=0),1,0) -> 0 | U18: Capital de operación (3 meses) | V18: =3*(J7+I7) -> 306165
A19: 13 | B19: =IF(A19=0,0,IF(A19<=Supuestos!$C$24,Supuestos!$C$22,IF(A19>=Supuestos!$C$8,$V$7,Supuestos!$C$22+($V$7-Supuestos!$C$22)*(A19-Supuestos!$C$24)/(Supuestos!$C$8-Supuestos!$C$24)))) -> 45.780556 | C19: =B19*Supuestos!$C$6 -> 274.68333 | D19: =C19*Supuestos!$C$42 -> 1190.2944 | E19: =IF(A19=0,0,MAX(Supuestos!$C$23,ROUNDUP(C19/Supuestos!$C$18,0))) -> 10 | F19: =MAX(0,E19-IF(A18=0,Supuestos!$C$23,E18))+Supuestos!$C$19*E19 -> 1.3 | G19: =IF(A19=0,0,MAX(1,ROUNDUP(B19/Supuestos!$C$21,0))) -> 1 | H19: =D19*(Supuestos!$C$14+Supuestos!$C$7) -> 95223.556 | I19: =D19*Supuestos!$C$43 -> 88676.936 | J19: =IF(A19=0,0,Supuestos!$C$44+G19*Supuestos!$C$26) -> 73000 | K19: =F19*Supuestos!$C$20 -> 4550 | L19: =IF(A19=0,Supuestos!$C$45,0) -> 0 | M19: =IF(A19=0,-L19,H19-I19-J19-K19) -> -71003.381 | N19: =N18+M19 -> -1152748.5 | O19: =1/(1+Supuestos!$C$46)^A19 -> 0.90189904 | P19: =M19*O19 -> -64037.881 | Q19: =Q18+P19 -> -1103034.1 | R19: =IF(AND(A19>0,N19>=0),1,0) -> 0 | S19: =IF(AND(A19>0,Q19>=0),1,0) -> 0 | U19: Colchón para imprevistos | V19: =Supuestos!$C$36*(V17+V18) -> 53216.5
A20: 14 | B20: =IF(A20=0,0,IF(A20<=Supuestos!$C$24,Supuestos!$C$22,IF(A20>=Supuestos!$C$8,$V$7,Supuestos!$C$22+($V$7-Supuestos!$C$22)*(A20-Supuestos!$C$24)/(Supuestos!$C$8-Supuestos!$C$24)))) -> 50.177778 | C20: =B20*Supuestos!$C$6 -> 301.06667 | D20: =C20*Supuestos!$C$42 -> 1304.6222 | E20: =IF(A20=0,0,MAX(Supuestos!$C$23,ROUNDUP(C20/Supuestos!$C$18,0))) -> 11 | F20: =MAX(0,E20-IF(A19=0,Supuestos!$C$23,E19))+Supuestos!$C$19*E20 -> 1.33 | G20: =IF(A20=0,0,MAX(1,ROUNDUP(B20/Supuestos!$C$21,0))) -> 1 | H20: =D20*(Supuestos!$C$14+Supuestos!$C$7) -> 104369.78 | I20: =D20*Supuestos!$C$43 -> 97194.356 | J20: =IF(A20=0,0,Supuestos!$C$44+G20*Supuestos!$C$26) -> 73000 | K20: =F20*Supuestos!$C$20 -> 4655 | L20: =IF(A20=0,Supuestos!$C$45,0) -> 0 | M20: =IF(A20=0,-L20,H20-I20-J20-K20) -> -70479.578 | N20: =N19+M20 -> -1223228.1 | O20: =1/(1+Supuestos!$C$46)^A20 -> 0.89476407 | P20: =M20*O20 -> -63062.594 | Q20: =Q19+P20 -> -1166096.7 | R20: =IF(AND(A20>0,N20>=0),1,0) -> 0 | S20: =IF(AND(A20>0,Q20>=0),1,0) -> 0 | U20: Requerimiento total de capital | V20: =V17+V18+V19 -> 585381.5
A21: 15 | B21: =IF(A21=0,0,IF(A21<=Supuestos!$C$24,Supuestos!$C$22,IF(A21>=Supuestos!$C$8,$V$7,Supuestos!$C$22+($V$7-Supuestos!$C$22)*(A21-Supuestos!$C$24)/(Supuestos!$C$8-Supuestos!$C$24)))) -> 54.575 | C21: =B21*Supuestos!$C$6 -> 327.45 | D21: =C21*Supuestos!$C$42 -> 1418.95 | E21: =IF(A21=0,0,MAX(Supuestos!$C$23,ROUNDUP(C21/Supuestos!$C$18,0))) -> 11 | F21: =MAX(0,E21-IF(A20=0,Supuestos!$C$23,E20))+Supuestos!$C$19*E21 -> 0.33 | G21: =IF(A21=0,0,MAX(1,ROUNDUP(B21/Supuestos!$C$21,0))) -> 1 | H21: =D21*(Supuestos!$C$14+Supuestos!$C$7) -> 113516 | I21: =D21*Supuestos!$C$43 -> 105711.77 | J21: =IF(A21=0,0,Supuestos!$C$44+G21*Supuestos!$C$26) -> 73000 | K21: =F21*Supuestos!$C$20 -> 1155 | L21: =IF(A21=0,Supuestos!$C$45,0) -> 0 | M21: =IF(A21=0,-L21,H21-I21-J21-K21) -> -66350.775 | N21: =N20+M21 -> -1289578.9 | O21: =1/(1+Supuestos!$C$46)^A21 -> 0.88768554 | P21: =M21*O21 -> -58898.623 | Q21: =Q20+P21 -> -1224995.3 | R21: =IF(AND(A21>0,N21>=0),1,0) -> 0 | S21: =IF(AND(A21>0,Q21>=0),1,0) -> 0 | U21: Déficit acumulado máximo | V21: =-MIN(0,MIN(N6:N66)) -> 5078090.5
A22: 16 | B22: =IF(A22=0,0,IF(A22<=Supuestos!$C$24,Supuestos!$C$22,IF(A22>=Supuestos!$C$8,$V$7,Supuestos!$C$22+($V$7-Supuestos!$C$22)*(A22-Supuestos!$C$24)/(Supuestos!$C$8-Supuestos!$C$24)))) -> 58.972222 | C22: =B22*Supuestos!$C$6 -> 353.83333 | D22: =C22*Supuestos!$C$42 -> 1533.2778 | E22: =IF(A22=0,0,MAX(Supuestos!$C$23,ROUNDUP(C22/Supuestos!$C$18,0))) -> 12 | F22: =MAX(0,E22-IF(A21=0,Supuestos!$C$23,E21))+Supuestos!$C$19*E22 -> 1.36 | G22: =IF(A22=0,0,MAX(1,ROUNDUP(B22/Supuestos!$C$21,0))) -> 1 | H22: =D22*(Supuestos!$C$14+Supuestos!$C$7) -> 122662.22 | I22: =D22*Supuestos!$C$43 -> 114229.19 | J22: =IF(A22=0,0,Supuestos!$C$44+G22*Supuestos!$C$26) -> 73000 | K22: =F22*Supuestos!$C$20 -> 4760 | L22: =IF(A22=0,Supuestos!$C$45,0) -> 0 | M22: =IF(A22=0,-L22,H22-I22-J22-K22) -> -69326.972 | N22: =N21+M22 -> -1358905.8 | O22: =1/(1+Supuestos!$C$46)^A22 -> 0.88066301 | P22: =M22*O22 -> -61053.7 | Q22: =Q21+P22 -> -1286049 | R22: =IF(AND(A22>0,N22>=0),1,0) -> 0 | S22: =IF(AND(A22>0,Q22>=0),1,0) -> 0 | U22: Familias en estado estable | V22: =B66 -> 94.15
A23: 17 | B23: =IF(A23=0,0,IF(A23<=Supuestos!$C$24,Supuestos!$C$22,IF(A23>=Supuestos!$C$8,$V$7,Supuestos!$C$22+($V$7-Supuestos!$C$22)*(A23-Supuestos!$C$24)/(Supuestos!$C$8-Supuestos!$C$24)))) -> 63.369444 | C23: =B23*Supuestos!$C$6 -> 380.21667 | D23: =C23*Supuestos!$C$42 -> 1647.6056 | E23: =IF(A23=0,0,MAX(Supuestos!$C$23,ROUNDUP(C23/Supuestos!$C$18,0))) -> 13 | F23: =MAX(0,E23-IF(A22=0,Supuestos!$C$23,E22))+Supuestos!$C$19*E23 -> 1.39 | G23: =IF(A23=0,0,MAX(1,ROUNDUP(B23/Supuestos!$C$21,0))) -> 1 | H23: =D23*(Supuestos!$C$14+Supuestos!$C$7) -> 131808.44 | I23: =D23*Supuestos!$C$43 -> 122746.61 | J23: =IF(A23=0,0,Supuestos!$C$44+G23*Supuestos!$C$26) -> 73000 | K23: =F23*Supuestos!$C$20 -> 4865 | L23: =IF(A23=0,Supuestos!$C$45,0) -> 0 | M23: =IF(A23=0,-L23,H23-I23-J23-K23) -> -68803.169 | N23: =N22+M23 -> -1427709 | O23: =1/(1+Supuestos!$C$46)^A23 -> 0.87369603 | P23: =M23*O23 -> -60113.056 | Q23: =Q22+P23 -> -1346162 | R23: =IF(AND(A23>0,N23>=0),1,0) -> 0 | S23: =IF(AND(A23>0,Q23>=0),1,0) -> 0 | U23: Horas de cuidado al mes en estado estable | V23: =D66 -> 2447.9
A24: 18 | B24: =IF(A24=0,0,IF(A24<=Supuestos!$C$24,Supuestos!$C$22,IF(A24>=Supuestos!$C$8,$V$7,Supuestos!$C$22+($V$7-Supuestos!$C$22)*(A24-Supuestos!$C$24)/(Supuestos!$C$8-Supuestos!$C$24)))) -> 67.766667 | C24: =B24*Supuestos!$C$6 -> 406.6 | D24: =C24*Supuestos!$C$42 -> 1761.9333 | E24: =IF(A24=0,0,MAX(Supuestos!$C$23,ROUNDUP(C24/Supuestos!$C$18,0))) -> 14 | F24: =MAX(0,E24-IF(A23=0,Supuestos!$C$23,E23))+Supuestos!$C$19*E24 -> 1.42 | G24: =IF(A24=0,0,MAX(1,ROUNDUP(B24/Supuestos!$C$21,0))) -> 1 | H24: =D24*(Supuestos!$C$14+Supuestos!$C$7) -> 140954.67 | I24: =D24*Supuestos!$C$43 -> 131264.03 | J24: =IF(A24=0,0,Supuestos!$C$44+G24*Supuestos!$C$26) -> 73000 | K24: =F24*Supuestos!$C$20 -> 4970 | L24: =IF(A24=0,Supuestos!$C$45,0) -> 0 | M24: =IF(A24=0,-L24,H24-I24-J24-K24) -> -68279.367 | N24: =N23+M24 -> -1495988.4 | O24: =1/(1+Supuestos!$C$46)^A24 -> 0.86678417 | P24: =M24*O24 -> -59183.474 | Q24: =Q23+P24 -> -1405345.5 | R24: =IF(AND(A24>0,N24>=0),1,0) -> 0 | S24: =IF(AND(A24>0,Q24>=0),1,0) -> 0 | U24: Cuidadoras empleadas en estado estable | V24: =E66 -> 19
A25: 19 | B25: =IF(A25=0,0,IF(A25<=Supuestos!$C$24,Supuestos!$C$22,IF(A25>=Supuestos!$C$8,$V$7,Supuestos!$C$22+($V$7-Supuestos!$C$22)*(A25-Supuestos!$C$24)/(Supuestos!$C$8-Supuestos!$C$24)))) -> 72.163889 | C25: =B25*Supuestos!$C$6 -> 432.98333 | D25: =C25*Supuestos!$C$42 -> 1876.2611 | E25: =IF(A25=0,0,MAX(Supuestos!$C$23,ROUNDUP(C25/Supuestos!$C$18,0))) -> 15 | F25: =MAX(0,E25-IF(A24=0,Supuestos!$C$23,E24))+Supuestos!$C$19*E25 -> 1.45 | G25: =IF(A25=0,0,MAX(1,ROUNDUP(B25/Supuestos!$C$21,0))) -> 1 | H25: =D25*(Supuestos!$C$14+Supuestos!$C$7) -> 150100.89 | I25: =D25*Supuestos!$C$43 -> 139781.45 | J25: =IF(A25=0,0,Supuestos!$C$44+G25*Supuestos!$C$26) -> 73000 | K25: =F25*Supuestos!$C$20 -> 5075 | L25: =IF(A25=0,Supuestos!$C$45,0) -> 0 | M25: =IF(A25=0,-L25,H25-I25-J25-K25) -> -67755.564 | N25: =N24+M25 -> -1563743.9 | O25: =1/(1+Supuestos!$C$46)^A25 -> 0.85992699 | P25: =M25*O25 -> -58264.838 | Q25: =Q24+P25 -> -1463610.4 | R25: =IF(AND(A25>0,N25>=0),1,0) -> 0 | S25: =IF(AND(A25>0,Q25>=0),1,0) -> 0 | U25: Familias en el mes de revisión | V25: =INDEX(B6:B66,(Supuestos!$C$37+1)) -> 41.383333
A26: 20 | B26: =IF(A26=0,0,IF(A26<=Supuestos!$C$24,Supuestos!$C$22,IF(A26>=Supuestos!$C$8,$V$7,Supuestos!$C$22+($V$7-Supuestos!$C$22)*(A26-Supuestos!$C$24)/(Supuestos!$C$8-Supuestos!$C$24)))) -> 76.561111 | C26: =B26*Supuestos!$C$6 -> 459.36667 | D26: =C26*Supuestos!$C$42 -> 1990.5889 | E26: =IF(A26=0,0,MAX(Supuestos!$C$23,ROUNDUP(C26/Supuestos!$C$18,0))) -> 16 | F26: =MAX(0,E26-IF(A25=0,Supuestos!$C$23,E25))+Supuestos!$C$19*E26 -> 1.48 | G26: =IF(A26=0,0,MAX(1,ROUNDUP(B26/Supuestos!$C$21,0))) -> 1 | H26: =D26*(Supuestos!$C$14+Supuestos!$C$7) -> 159247.11 | I26: =D26*Supuestos!$C$43 -> 148298.87 | J26: =IF(A26=0,0,Supuestos!$C$44+G26*Supuestos!$C$26) -> 73000 | K26: =F26*Supuestos!$C$20 -> 5180 | L26: =IF(A26=0,Supuestos!$C$45,0) -> 0 | M26: =IF(A26=0,-L26,H26-I26-J26-K26) -> -67231.761 | N26: =N25+M26 -> -1630975.7 | O26: =1/(1+Supuestos!$C$46)^A26 -> 0.85312406 | P26: =M26*O26 -> -57357.033 | Q26: =Q25+P26 -> -1520967.4 | R26: =IF(AND(A26>0,N26>=0),1,0) -> 0 | S26: =IF(AND(A26>0,Q26>=0),1,0) -> 0 | U26: ¿Se cierra en la revisión? | V26: =IF(ISNUMBER(V15),IF(V25<Supuestos!$C$38*V15,"Sí","No"),"Sí") -> Sí
A27: 21 | B27: =IF(A27=0,0,IF(A27<=Supuestos!$C$24,Supuestos!$C$22,IF(A27>=Supuestos!$C$8,$V$7,Supuestos!$C$22+($V$7-Supuestos!$C$22)*(A27-Supuestos!$C$24)/(Supuestos!$C$8-Supuestos!$C$24)))) -> 80.958333 | C27: =B27*Supuestos!$C$6 -> 485.75 | D27: =C27*Supuestos!$C$42 -> 2104.9167 | E27: =IF(A27=0,0,MAX(Supuestos!$C$23,ROUNDUP(C27/Supuestos!$C$18,0))) -> 17 | F27: =MAX(0,E27-IF(A26=0,Supuestos!$C$23,E26))+Supuestos!$C$19*E27 -> 1.51 | G27: =IF(A27=0,0,MAX(1,ROUNDUP(B27/Supuestos!$C$21,0))) -> 2 | H27: =D27*(Supuestos!$C$14+Supuestos!$C$7) -> 168393.33 | I27: =D27*Supuestos!$C$43 -> 156816.29 | J27: =IF(A27=0,0,Supuestos!$C$44+G27*Supuestos!$C$26) -> 97300 | K27: =F27*Supuestos!$C$20 -> 5285 | L27: =IF(A27=0,Supuestos!$C$45,0) -> 0 | M27: =IF(A27=0,-L27,H27-I27-J27-K27) -> -91007.958 | N27: =N26+M27 -> -1721983.7 | O27: =1/(1+Supuestos!$C$46)^A27 -> 0.84637495 | P27: =M27*O27 -> -77026.856 | Q27: =Q26+P27 -> -1597994.2 | R27: =IF(AND(A27>0,N27>=0),1,0) -> 0 | S27: =IF(AND(A27>0,Q27>=0),1,0) -> 0 | U27: Costo de cierre | V27: =Supuestos!$C$39*INDEX(J6:J66,(Supuestos!$C$37+1)) -> 146000
A28: 22 | B28: =IF(A28=0,0,IF(A28<=Supuestos!$C$24,Supuestos!$C$22,IF(A28>=Supuestos!$C$8,$V$7,Supuestos!$C$22+($V$7-Supuestos!$C$22)*(A28-Supuestos!$C$24)/(Supuestos!$C$8-Supuestos!$C$24)))) -> 85.355556 | C28: =B28*Supuestos!$C$6 -> 512.13333 | D28: =C28*Supuestos!$C$42 -> 2219.2444 | E28: =IF(A28=0,0,MAX(Supuestos!$C$23,ROUNDUP(C28/Supuestos!$C$18,0))) -> 18 | F28: =MAX(0,E28-IF(A27=0,Supuestos!$C$23,E27))+Supuestos!$C$19*E28 -> 1.54 | G28: =IF(A28=0,0,MAX(1,ROUNDUP(B28/Supuestos!$C$21,0))) -> 2 | H28: =D28*(Supuestos!$C$14+Supuestos!$C$7) -> 177539.56 | I28: =D28*Supuestos!$C$43 -> 165333.71 | J28: =IF(A28=0,0,Supuestos!$C$44+G28*Supuestos!$C$26) -> 97300 | K28: =F28*Supuestos!$C$20 -> 5390 | L28: =IF(A28=0,Supuestos!$C$45,0) -> 0 | M28: =IF(A28=0,-L28,H28-I28-J28-K28) -> -90484.156 | N28: =N27+M28 -> -1812467.8 | O28: =1/(1+Supuestos!$C$46)^A28 -> 0.83967923 | P28: =M28*O28 -> -75977.666 | Q28: =Q27+P28 -> -1673971.9 | R28: =IF(AND(A28>0,N28>=0),1,0) -> 0 | S28: =IF(AND(A28>0,Q28>=0),1,0) -> 0 | U28: VAN con revisión en el mes 12 | V28: =IF(V26="Sí",SUM(P6:INDEX(P6:P66,(Supuestos!$C$37+1)))-V27/(1+Supuestos!$C$46)^(Supuestos!$C$37+1),V8) -> -1170673.4
A29: 23 | B29: =IF(A29=0,0,IF(A29<=Supuestos!$C$24,Supuestos!$C$22,IF(A29>=Supuestos!$C$8,$V$7,Supuestos!$C$22+($V$7-Supuestos!$C$22)*(A29-Supuestos!$C$24)/(Supuestos!$C$8-Supuestos!$C$24)))) -> 89.752778 | C29: =B29*Supuestos!$C$6 -> 538.51667 | D29: =C29*Supuestos!$C$42 -> 2333.5722 | E29: =IF(A29=0,0,MAX(Supuestos!$C$23,ROUNDUP(C29/Supuestos!$C$18,0))) -> 18 | F29: =MAX(0,E29-IF(A28=0,Supuestos!$C$23,E28))+Supuestos!$C$19*E29 -> 0.54 | G29: =IF(A29=0,0,MAX(1,ROUNDUP(B29/Supuestos!$C$21,0))) -> 2 | H29: =D29*(Supuestos!$C$14+Supuestos!$C$7) -> 186685.78 | I29: =D29*Supuestos!$C$43 -> 173851.13 | J29: =IF(A29=0,0,Supuestos!$C$44+G29*Supuestos!$C$26) -> 97300 | K29: =F29*Supuestos!$C$20 -> 1890 | L29: =IF(A29=0,Supuestos!$C$45,0) -> 0 | M29: =IF(A29=0,-L29,H29-I29-J29-K29) -> -86355.353 | N29: =N28+M29 -> -1898823.2 | O29: =1/(1+Supuestos!$C$46)^A29 -> 0.83303648 | P29: =M29*O29 -> -71937.159 | Q29: =Q28+P29 -> -1745909.1 | R29: =IF(AND(A29>0,N29>=0),1,0) -> 0 | S29: =IF(AND(A29>0,Q29>=0),1,0) -> 0 | U29: Utilidad neta con revisión | V29: =IF(V26="Sí",SUM(M6:INDEX(M6:M66,(Supuestos!$C$37+1)))-V27,V16) -> -1227745.1
A30: 24 | B30: =IF(A30=0,0,IF(A30<=Supuestos!$C$24,Supuestos!$C$22,IF(A30>=Supuestos!$C$8,$V$7,Supuestos!$C$22+($V$7-Supuestos!$C$22)*(A30-Supuestos!$C$24)/(Supuestos!$C$8-Supuestos!$C$24)))) -> 94.15 | C30: =B30*Supuestos!$C$6 -> 564.9 | D30: =C30*Supuestos!$C$42 -> 2447.9 | E30: =IF(A30=0,0,MAX(Supuestos!$C$23,ROUNDUP(C30/Supuestos!$C$18,0))) -> 19 | F30: =MAX(0,E30-IF(A29=0,Supuestos!$C$23,E29))+Supuestos!$C$19*E30 -> 1.57 | G30: =IF(A30=0,0,MAX(1,ROUNDUP(B30/Supuestos!$C$21,0))) -> 2 | H30: =D30*(Supuestos!$C$14+Supuestos!$C$7) -> 195832 | I30: =D30*Supuestos!$C$43 -> 182368.55 | J30: =IF(A30=0,0,Supuestos!$C$44+G30*Supuestos!$C$26) -> 97300 | K30: =F30*Supuestos!$C$20 -> 5495 | L30: =IF(A30=0,Supuestos!$C$45,0) -> 0 | M30: =IF(A30=0,-L30,H30-I30-J30-K30) -> -89331.55 | N30: =N29+M30 -> -1988154.7 | O30: =1/(1+Supuestos!$C$46)^A30 -> 0.82644628 | P30: =M30*O30 -> -73827.727 | Q30: =Q29+P30 -> -1819736.8 | R30: =IF(AND(A30>0,N30>=0),1,0) -> 0 | S30: =IF(AND(A30>0,Q30>=0),1,0) -> 0
A31: 25 | B31: =IF(A31=0,0,IF(A31<=Supuestos!$C$24,Supuestos!$C$22,IF(A31>=Supuestos!$C$8,$V$7,Supuestos!$C$22+($V$7-Supuestos!$C$22)*(A31-Supuestos!$C$24)/(Supuestos!$C$8-Supuestos!$C$24)))) -> 94.15 | C31: =B31*Supuestos!$C$6 -> 564.9 | D31: =C31*Supuestos!$C$42 -> 2447.9 | E31: =IF(A31=0,0,MAX(Supuestos!$C$23,ROUNDUP(C31/Supuestos!$C$18,0))) -> 19 | F31: =MAX(0,E31-IF(A30=0,Supuestos!$C$23,E30))+Supuestos!$C$19*E31 -> 0.57 | G31: =IF(A31=0,0,MAX(1,ROUNDUP(B31/Supuestos!$C$21,0))) -> 2 | H31: =D31*(Supuestos!$C$14+Supuestos!$C$7) -> 195832 | I31: =D31*Supuestos!$C$43 -> 182368.55 | J31: =IF(A31=0,0,Supuestos!$C$44+G31*Supuestos!$C$26) -> 97300 | K31: =F31*Supuestos!$C$20 -> 1995 | L31: =IF(A31=0,Supuestos!$C$45,0) -> 0 | M31: =IF(A31=0,-L31,H31-I31-J31-K31) -> -85831.55 | N31: =N30+M31 -> -2073986.3 | O31: =1/(1+Supuestos!$C$46)^A31 -> 0.81990822 | P31: =M31*O31 -> -70373.993 | Q31: =Q30+P31 -> -1890110.8 | R31: =IF(AND(A31>0,N31>=0),1,0) -> 0 | S31: =IF(AND(A31>0,Q31>=0),1,0) -> 0
A32: 26 | B32: =IF(A32=0,0,IF(A32<=Supuestos!$C$24,Supuestos!$C$22,IF(A32>=Supuestos!$C$8,$V$7,Supuestos!$C$22+($V$7-Supuestos!$C$22)*(A32-Supuestos!$C$24)/(Supuestos!$C$8-Supuestos!$C$24)))) -> 94.15 | C32: =B32*Supuestos!$C$6 -> 564.9 | D32: =C32*Supuestos!$C$42 -> 2447.9 | E32: =IF(A32=0,0,MAX(Supuestos!$C$23,ROUNDUP(C32/Supuestos!$C$18,0))) -> 19 | F32: =MAX(0,E32-IF(A31=0,Supuestos!$C$23,E31))+Supuestos!$C$19*E32 -> 0.57 | G32: =IF(A32=0,0,MAX(1,ROUNDUP(B32/Supuestos!$C$21,0))) -> 2 | H32: =D32*(Supuestos!$C$14+Supuestos!$C$7) -> 195832 | I32: =D32*Supuestos!$C$43 -> 182368.55 | J32: =IF(A32=0,0,Supuestos!$C$44+G32*Supuestos!$C$26) -> 97300 | K32: =F32*Supuestos!$C$20 -> 1995 | L32: =IF(A32=0,Supuestos!$C$45,0) -> 0 | M32: =IF(A32=0,-L32,H32-I32-J32-K32) -> -85831.55 | N32: =N31+M32 -> -2159817.8 | O32: =1/(1+Supuestos!$C$46)^A32 -> 0.81342188 | P32: =M32*O32 -> -69817.261 | Q32: =Q31+P32 -> -1959928 | R32: =IF(AND(A32>0,N32>=0),1,0) -> 0 | S32: =IF(AND(A32>0,Q32>=0),1,0) -> 0
A33: 27 | B33: =IF(A33=0,0,IF(A33<=Supuestos!$C$24,Supuestos!$C$22,IF(A33>=Supuestos!$C$8,$V$7,Supuestos!$C$22+($V$7-Supuestos!$C$22)*(A33-Supuestos!$C$24)/(Supuestos!$C$8-Supuestos!$C$24)))) -> 94.15 | C33: =B33*Supuestos!$C$6 -> 564.9 | D33: =C33*Supuestos!$C$42 -> 2447.9 | E33: =IF(A33=0,0,MAX(Supuestos!$C$23,ROUNDUP(C33/Supuestos!$C$18,0))) -> 19 | F33: =MAX(0,E33-IF(A32=0,Supuestos!$C$23,E32))+Supuestos!$C$19*E33 -> 0.57 | G33: =IF(A33=0,0,MAX(1,ROUNDUP(B33/Supuestos!$C$21,0))) -> 2 | H33: =D33*(Supuestos!$C$14+Supuestos!$C$7) -> 195832 | I33: =D33*Supuestos!$C$43 -> 182368.55 | J33: =IF(A33=0,0,Supuestos!$C$44+G33*Supuestos!$C$26) -> 97300 | K33: =F33*Supuestos!$C$20 -> 1995 | L33: =IF(A33=0,Supuestos!$C$45,0) -> 0 | M33: =IF(A33=0,-L33,H33-I33-J33-K33) -> -85831.55 | N33: =N32+M33 -> -2245649.4 | O33: =1/(1+Supuestos!$C$46)^A33 -> 0.80698685 | P33: =M33*O33 -> -69264.932 | Q33: =Q32+P33 -> -2029193 | R33: =IF(AND(A33>0,N33>=0),1,0) -> 0 | S33: =IF(AND(A33>0,Q33>=0),1,0) -> 0
A34: 28 | B34: =IF(A34=0,0,IF(A34<=Supuestos!$C$24,Supuestos!$C$22,IF(A34>=Supuestos!$C$8,$V$7,Supuestos!$C$22+($V$7-Supuestos!$C$22)*(A34-Supuestos!$C$24)/(Supuestos!$C$8-Supuestos!$C$24)))) -> 94.15 | C34: =B34*Supuestos!$C$6 -> 564.9 | D34: =C34*Supuestos!$C$42 -> 2447.9 | E34: =IF(A34=0,0,MAX(Supuestos!$C$23,ROUNDUP(C34/Supuestos!$C$18,0))) -> 19 | F34: =MAX(0,E34-IF(A33=0,Supuestos!$C$23,E33))+Supuestos!$C$19*E34 -> 0.57 | G34: =IF(A34=0,0,MAX(1,ROUNDUP(B34/Supuestos!$C$21,0))) -> 2 | H34: =D34*(Supuestos!$C$14+Supuestos!$C$7) -> 195832 | I34: =D34*Supuestos!$C$43 -> 182368.55 | J34: =IF(A34=0,0,Supuestos!$C$44+G34*Supuestos!$C$26) -> 97300 | K34: =F34*Supuestos!$C$20 -> 1995 | L34: =IF(A34=0,Supuestos!$C$45,0) -> 0 | M34: =IF(A34=0,-L34,H34-I34-J34-K34) -> -85831.55 | N34: =N33+M34 -> -2331480.9 | O34: =1/(1+Supuestos!$C$46)^A34 -> 0.80060273 | P34: =M34*O34 -> -68716.973 | Q34: =Q33+P34 -> -2097910 | R34: =IF(AND(A34>0,N34>=0),1,0) -> 0 | S34: =IF(AND(A34>0,Q34>=0),1,0) -> 0
A35: 29 | B35: =IF(A35=0,0,IF(A35<=Supuestos!$C$24,Supuestos!$C$22,IF(A35>=Supuestos!$C$8,$V$7,Supuestos!$C$22+($V$7-Supuestos!$C$22)*(A35-Supuestos!$C$24)/(Supuestos!$C$8-Supuestos!$C$24)))) -> 94.15 | C35: =B35*Supuestos!$C$6 -> 564.9 | D35: =C35*Supuestos!$C$42 -> 2447.9 | E35: =IF(A35=0,0,MAX(Supuestos!$C$23,ROUNDUP(C35/Supuestos!$C$18,0))) -> 19 | F35: =MAX(0,E35-IF(A34=0,Supuestos!$C$23,E34))+Supuestos!$C$19*E35 -> 0.57 | G35: =IF(A35=0,0,MAX(1,ROUNDUP(B35/Supuestos!$C$21,0))) -> 2 | H35: =D35*(Supuestos!$C$14+Supuestos!$C$7) -> 195832 | I35: =D35*Supuestos!$C$43 -> 182368.55 | J35: =IF(A35=0,0,Supuestos!$C$44+G35*Supuestos!$C$26) -> 97300 | K35: =F35*Supuestos!$C$20 -> 1995 | L35: =IF(A35=0,Supuestos!$C$45,0) -> 0 | M35: =IF(A35=0,-L35,H35-I35-J35-K35) -> -85831.55 | N35: =N34+M35 -> -2417312.5 | O35: =1/(1+Supuestos!$C$46)^A35 -> 0.79426912 | P35: =M35*O35 -> -68173.35 | Q35: =Q34+P35 -> -2166083.3 | R35: =IF(AND(A35>0,N35>=0),1,0) -> 0 | S35: =IF(AND(A35>0,Q35>=0),1,0) -> 0
A36: 30 | B36: =IF(A36=0,0,IF(A36<=Supuestos!$C$24,Supuestos!$C$22,IF(A36>=Supuestos!$C$8,$V$7,Supuestos!$C$22+($V$7-Supuestos!$C$22)*(A36-Supuestos!$C$24)/(Supuestos!$C$8-Supuestos!$C$24)))) -> 94.15 | C36: =B36*Supuestos!$C$6 -> 564.9 | D36: =C36*Supuestos!$C$42 -> 2447.9 | E36: =IF(A36=0,0,MAX(Supuestos!$C$23,ROUNDUP(C36/Supuestos!$C$18,0))) -> 19 | F36: =MAX(0,E36-IF(A35=0,Supuestos!$C$23,E35))+Supuestos!$C$19*E36 -> 0.57 | G36: =IF(A36=0,0,MAX(1,ROUNDUP(B36/Supuestos!$C$21,0))) -> 2 | H36: =D36*(Supuestos!$C$14+Supuestos!$C$7) -> 195832 | I36: =D36*Supuestos!$C$43 -> 182368.55 | J36: =IF(A36=0,0,Supuestos!$C$44+G36*Supuestos!$C$26) -> 97300 | K36: =F36*Supuestos!$C$20 -> 1995 | L36: =IF(A36=0,Supuestos!$C$45,0) -> 0 | M36: =IF(A36=0,-L36,H36-I36-J36-K36) -> -85831.55 | N36: =N35+M36 -> -2503144 | O36: =1/(1+Supuestos!$C$46)^A36 -> 0.78798561 | P36: =M36*O36 -> -67634.026 | Q36: =Q35+P36 -> -2233717.3 | R36: =IF(AND(A36>0,N36>=0),1,0) -> 0 | S36: =IF(AND(A36>0,Q36>=0),1,0) -> 0
A37: 31 | B37: =IF(A37=0,0,IF(A37<=Supuestos!$C$24,Supuestos!$C$22,IF(A37>=Supuestos!$C$8,$V$7,Supuestos!$C$22+($V$7-Supuestos!$C$22)*(A37-Supuestos!$C$24)/(Supuestos!$C$8-Supuestos!$C$24)))) -> 94.15 | C37: =B37*Supuestos!$C$6 -> 564.9 | D37: =C37*Supuestos!$C$42 -> 2447.9 | E37: =IF(A37=0,0,MAX(Supuestos!$C$23,ROUNDUP(C37/Supuestos!$C$18,0))) -> 19 | F37: =MAX(0,E37-IF(A36=0,Supuestos!$C$23,E36))+Supuestos!$C$19*E37 -> 0.57 | G37: =IF(A37=0,0,MAX(1,ROUNDUP(B37/Supuestos!$C$21,0))) -> 2 | H37: =D37*(Supuestos!$C$14+Supuestos!$C$7) -> 195832 | I37: =D37*Supuestos!$C$43 -> 182368.55 | J37: =IF(A37=0,0,Supuestos!$C$44+G37*Supuestos!$C$26) -> 97300 | K37: =F37*Supuestos!$C$20 -> 1995 | L37: =IF(A37=0,Supuestos!$C$45,0) -> 0 | M37: =IF(A37=0,-L37,H37-I37-J37-K37) -> -85831.55 | N37: =N36+M37 -> -2588975.6 | O37: =1/(1+Supuestos!$C$46)^A37 -> 0.78175181 | P37: =M37*O37 -> -67098.97 | Q37: =Q36+P37 -> -2300816.3 | R37: =IF(AND(A37>0,N37>=0),1,0) -> 0 | S37: =IF(AND(A37>0,Q37>=0),1,0) -> 0
A38: 32 | B38: =IF(A38=0,0,IF(A38<=Supuestos!$C$24,Supuestos!$C$22,IF(A38>=Supuestos!$C$8,$V$7,Supuestos!$C$22+($V$7-Supuestos!$C$22)*(A38-Supuestos!$C$24)/(Supuestos!$C$8-Supuestos!$C$24)))) -> 94.15 | C38: =B38*Supuestos!$C$6 -> 564.9 | D38: =C38*Supuestos!$C$42 -> 2447.9 | E38: =IF(A38=0,0,MAX(Supuestos!$C$23,ROUNDUP(C38/Supuestos!$C$18,0))) -> 19 | F38: =MAX(0,E38-IF(A37=0,Supuestos!$C$23,E37))+Supuestos!$C$19*E38 -> 0.57 | G38: =IF(A38=0,0,MAX(1,ROUNDUP(B38/Supuestos!$C$21,0))) -> 2 | H38: =D38*(Supuestos!$C$14+Supuestos!$C$7) -> 195832 | I38: =D38*Supuestos!$C$43 -> 182368.55 | J38: =IF(A38=0,0,Supuestos!$C$44+G38*Supuestos!$C$26) -> 97300 | K38: =F38*Supuestos!$C$20 -> 1995 | L38: =IF(A38=0,Supuestos!$C$45,0) -> 0 | M38: =IF(A38=0,-L38,H38-I38-J38-K38) -> -85831.55 | N38: =N37+M38 -> -2674807.1 | O38: =1/(1+Supuestos!$C$46)^A38 -> 0.77556733 | P38: =M38*O38 -> -66568.146 | Q38: =Q37+P38 -> -2367384.4 | R38: =IF(AND(A38>0,N38>=0),1,0) -> 0 | S38: =IF(AND(A38>0,Q38>=0),1,0) -> 0
A39: 33 | B39: =IF(A39=0,0,IF(A39<=Supuestos!$C$24,Supuestos!$C$22,IF(A39>=Supuestos!$C$8,$V$7,Supuestos!$C$22+($V$7-Supuestos!$C$22)*(A39-Supuestos!$C$24)/(Supuestos!$C$8-Supuestos!$C$24)))) -> 94.15 | C39: =B39*Supuestos!$C$6 -> 564.9 | D39: =C39*Supuestos!$C$42 -> 2447.9 | E39: =IF(A39=0,0,MAX(Supuestos!$C$23,ROUNDUP(C39/Supuestos!$C$18,0))) -> 19 | F39: =MAX(0,E39-IF(A38=0,Supuestos!$C$23,E38))+Supuestos!$C$19*E39 -> 0.57 | G39: =IF(A39=0,0,MAX(1,ROUNDUP(B39/Supuestos!$C$21,0))) -> 2 | H39: =D39*(Supuestos!$C$14+Supuestos!$C$7) -> 195832 | I39: =D39*Supuestos!$C$43 -> 182368.55 | J39: =IF(A39=0,0,Supuestos!$C$44+G39*Supuestos!$C$26) -> 97300 | K39: =F39*Supuestos!$C$20 -> 1995 | L39: =IF(A39=0,Supuestos!$C$45,0) -> 0 | M39: =IF(A39=0,-L39,H39-I39-J39-K39) -> -85831.55 | N39: =N38+M39 -> -2760638.7 | O39: =1/(1+Supuestos!$C$46)^A39 -> 0.76943177 | P39: =M39*O39 -> -66041.522 | Q39: =Q38+P39 -> -2433426 | R39: =IF(AND(A39>0,N39>=0),1,0) -> 0 | S39: =IF(AND(A39>0,Q39>=0),1,0) -> 0
A40: 34 | B40: =IF(A40=0,0,IF(A40<=Supuestos!$C$24,Supuestos!$C$22,IF(A40>=Supuestos!$C$8,$V$7,Supuestos!$C$22+($V$7-Supuestos!$C$22)*(A40-Supuestos!$C$24)/(Supuestos!$C$8-Supuestos!$C$24)))) -> 94.15 | C40: =B40*Supuestos!$C$6 -> 564.9 | D40: =C40*Supuestos!$C$42 -> 2447.9 | E40: =IF(A40=0,0,MAX(Supuestos!$C$23,ROUNDUP(C40/Supuestos!$C$18,0))) -> 19 | F40: =MAX(0,E40-IF(A39=0,Supuestos!$C$23,E39))+Supuestos!$C$19*E40 -> 0.57 | G40: =IF(A40=0,0,MAX(1,ROUNDUP(B40/Supuestos!$C$21,0))) -> 2 | H40: =D40*(Supuestos!$C$14+Supuestos!$C$7) -> 195832 | I40: =D40*Supuestos!$C$43 -> 182368.55 | J40: =IF(A40=0,0,Supuestos!$C$44+G40*Supuestos!$C$26) -> 97300 | K40: =F40*Supuestos!$C$20 -> 1995 | L40: =IF(A40=0,Supuestos!$C$45,0) -> 0 | M40: =IF(A40=0,-L40,H40-I40-J40-K40) -> -85831.55 | N40: =N39+M40 -> -2846470.2 | O40: =1/(1+Supuestos!$C$46)^A40 -> 0.76334475 | P40: =M40*O40 -> -65519.063 | Q40: =Q39+P40 -> -2498945 | R40: =IF(AND(A40>0,N40>=0),1,0) -> 0 | S40: =IF(AND(A40>0,Q40>=0),1,0) -> 0
A41: 35 | B41: =IF(A41=0,0,IF(A41<=Supuestos!$C$24,Supuestos!$C$22,IF(A41>=Supuestos!$C$8,$V$7,Supuestos!$C$22+($V$7-Supuestos!$C$22)*(A41-Supuestos!$C$24)/(Supuestos!$C$8-Supuestos!$C$24)))) -> 94.15 | C41: =B41*Supuestos!$C$6 -> 564.9 | D41: =C41*Supuestos!$C$42 -> 2447.9 | E41: =IF(A41=0,0,MAX(Supuestos!$C$23,ROUNDUP(C41/Supuestos!$C$18,0))) -> 19 | F41: =MAX(0,E41-IF(A40=0,Supuestos!$C$23,E40))+Supuestos!$C$19*E41 -> 0.57 | G41: =IF(A41=0,0,MAX(1,ROUNDUP(B41/Supuestos!$C$21,0))) -> 2 | H41: =D41*(Supuestos!$C$14+Supuestos!$C$7) -> 195832 | I41: =D41*Supuestos!$C$43 -> 182368.55 | J41: =IF(A41=0,0,Supuestos!$C$44+G41*Supuestos!$C$26) -> 97300 | K41: =F41*Supuestos!$C$20 -> 1995 | L41: =IF(A41=0,Supuestos!$C$45,0) -> 0 | M41: =IF(A41=0,-L41,H41-I41-J41-K41) -> -85831.55 | N41: =N40+M41 -> -2932301.8 | O41: =1/(1+Supuestos!$C$46)^A41 -> 0.75730589 | P41: =M41*O41 -> -65000.738 | Q41: =Q40+P41 -> -2563945.8 | R41: =IF(AND(A41>0,N41>=0),1,0) -> 0 | S41: =IF(AND(A41>0,Q41>=0),1,0) -> 0
... A66: 60 | B66: =IF(A66=0,0,IF(A66<=Supuestos!$C$24,Supuestos!$C$22,IF(A66>=Supuestos!$C$8,$V$7,Supuestos!$C$22+($V$7-Supuestos!$C$22)*(A66-Supuestos!$C$24)/(Supuestos!$C$8-Supuestos!$C$24)))) -> 94.15 | C66: =B66*Supuestos!$C$6 -> 564.9 | D66: =C66*Supuestos!$C$42 -> 2447.9 | E66: =IF(A66=0,0,MAX(Supuestos!$C$23,ROUNDUP(C66/Supuestos!$C$18,0))) -> 19 | F66: =MAX(0,E66-IF(A65=0,Supuestos!$C$23,E65))+Supuestos!$C$19*E66 -> 0.57 | G66: =IF(A66=0,0,MAX(1,ROUNDUP(B66/Supuestos!$C$21,0))) -> 2 | H66: =D66*(Supuestos!$C$14+Supuestos!$C$7) -> 195832 | I66: =D66*Supuestos!$C$43 -> 182368.55 | J66: =IF(A66=0,0,Supuestos!$C$44+G66*Supuestos!$C$26) -> 97300 | K66: =F66*Supuestos!$C$20 -> 1995 | L66: =IF(A66=0,Supuestos!$C$45,0) -> 0 | M66: =IF(A66=0,-L66,H66-I66-J66-K66) -> -85831.55 | N66: =N65+M66 -> -5078090.5 | O66: =1/(1+Supuestos!$C$46)^A66 -> 0.62092132 | P66: =M66*O66 -> -53294.64 | Q66: =Q65+P66 -> -4031953.4 | R66: =IF(AND(A66>0,N66>=0),1,0) -> 0 | S66: =IF(AND(A66>0,Q66>=0),1,0) -> 0

Sheet Flujo Realista
A1: Flujo mensual — escenario realista (pesos de 2026)
A2: Todas las celdas son fórmulas que leen la hoja «Supuestos» (texto verde: vínculo). Mes 0 = inversión inicial.
U3: Indicador | V3: Valor
U4: Escenario | V4: Realista
A5: Mes | B5: Familias | C5: Horas por semana | D5: Horas al mes | E5: Cuidadoras | F5: Cuidadoras nuevas (incluye rotación) | G5: Trabajadoras sociales | H5: Ingresos ($) | I5: Costo variable ($) | J5: Costos fijos ($) | K5: Capacitación ($) | L5: Inversión ($) | M5: Flujo neto ($) | N5: Flujo acumulado ($) | O5: Factor de descuento | P5: Flujo descontado ($) | Q5: Acumulado descontado ($) | R5: ¿Recuperado? | S5: ¿Recuperado (descontado)? | U5: Tarifa por hora (copago + subsidio) | V5: =Supuestos!$C$14+Supuestos!$D$7 -> 100
A6: 0 | B6: =IF(A6=0,0,IF(A6<=Supuestos!$C$24,Supuestos!$C$22,IF(A6>=Supuestos!$D$8,$V$7,Supuestos!$C$22+($V$7-Supuestos!$C$22)*(A6-Supuestos!$C$24)/(Supuestos!$D$8-Supuestos!$C$24)))) -> 0 | C6: =B6*Supuestos!$D$6 -> 0 | D6: =C6*Supuestos!$C$42 -> 0 | E6: =IF(A6=0,0,MAX(Supuestos!$C$23,ROUNDUP(C6/Supuestos!$C$18,0))) -> 0 | F6: 0 | G6: =IF(A6=0,0,MAX(1,ROUNDUP(B6/Supuestos!$C$21,0))) -> 0 | H6: =D6*(Supuestos!$C$14+Supuestos!$D$7) -> 0 | I6: =D6*Supuestos!$C$43 -> 0 | J6: =IF(A6=0,0,Supuestos!$C$44+G6*Supuestos!$C$26) -> 0 | K6: =F6*Supuestos!$C$20 -> 0 | L6: =IF(A6=0,Supuestos!$C$45,0) -> 226000 | M6: =IF(A6=0,-L6,H6-I6-J6-K6) -> -226000 | N6: =M6 -> -226000 | O6: =1/(1+Supuestos!$C$46)^A6 -> 1 | P6: =M6*O6 -> -226000 | Q6: =P6 -> -226000 | R6: =IF(AND(A6>0,N6>=0),1,0) -> 0 | S6: =IF(AND(A6>0,Q6>=0),1,0) -> 0 | U6: Margen por hora | V6: =V5-Supuestos!$C$43 -> 25.5
A7: 1 | B7: =IF(A7=0,0,IF(A7<=Supuestos!$C$24,Supuestos!$C$22,IF(A7>=Supuestos!$D$8,$V$7,Supuestos!$C$22+($V$7-Supuestos!$C$22)*(A7-Supuestos!$C$24)/(Supuestos!$D$8-Supuestos!$C$24)))) -> 15 | C7: =B7*Supuestos!$D$6 -> 120 | D7: =C7*Supuestos!$C$42 -> 520 | E7: =IF(A7=0,0,MAX(Supuestos!$C$23,ROUNDUP(C7/Supuestos!$C$18,0))) -> 6 | F7: =MAX(0,E7-IF(A6=0,Supuestos!$C$23,E6))+Supuestos!$C$19*E7 -> 0.18 | G7: =IF(A7=0,0,MAX(1,ROUNDUP(B7/Supuestos!$C$21,0))) -> 1 | H7: =D7*(Supuestos!$C$14+Supuestos!$D$7) -> 52000 | I7: =D7*Supuestos!$C$43 -> 38740 | J7: =IF(A7=0,0,Supuestos!$C$44+G7*Supuestos!$C$26) -> 73000 | K7: =F7*Supuestos!$C$20 -> 630 | L7: =IF(A7=0,Supuestos!$C$45,0) -> 0 | M7: =IF(A7=0,-L7,H7-I7-J7-K7) -> -60370 | N7: =N6+M7 -> -286370 | O7: =1/(1+Supuestos!$C$46)^A7 -> 0.99208894 | P7: =M7*O7 -> -59892.41 | Q7: =Q6+P7 -> -285892.41 | R7: =IF(AND(A7>0,N7>=0),1,0) -> 0 | S7: =IF(AND(A7>0,Q7>=0),1,0) -> 0 | U7: Familias objetivo (estado estable) | V7: =MAX(Supuestos!$C$13*Supuestos!$D$5,Supuestos!$C$22) -> 188.3
A8: 2 | B8: =IF(A8=0,0,IF(A8<=Supuestos!$C$24,Supuestos!$C$22,IF(A8>=Supuestos!$D$8,$V$7,Supuestos!$C$22+($V$7-Supuestos!$C$22)*(A8-Supuestos!$C$24)/(Supuestos!$D$8-Supuestos!$C$24)))) -> 15 | C8: =B8*Supuestos!$D$6 -> 120 | D8: =C8*Supuestos!$C$42 -> 520 | E8: =IF(A8=0,0,MAX(Supuestos!$C$23,ROUNDUP(C8/Supuestos!$C$18,0))) -> 6 | F8: =MAX(0,E8-IF(A7=0,Supuestos!$C$23,E7))+Supuestos!$C$19*E8 -> 0.18 | G8: =IF(A8=0,0,MAX(1,ROUNDUP(B8/Supuestos!$C$21,0))) -> 1 | H8: =D8*(Supuestos!$C$14+Supuestos!$D$7) -> 52000 | I8: =D8*Supuestos!$C$43 -> 38740 | J8: =IF(A8=0,0,Supuestos!$C$44+G8*Supuestos!$C$26) -> 73000 | K8: =F8*Supuestos!$C$20 -> 630 | L8: =IF(A8=0,Supuestos!$C$45,0) -> 0 | M8: =IF(A8=0,-L8,H8-I8-J8-K8) -> -60370 | N8: =N7+M8 -> -346740 | O8: =1/(1+Supuestos!$C$46)^A8 -> 0.98424047 | P8: =M8*O8 -> -59418.597 | Q8: =Q7+P8 -> -345311.01 | R8: =IF(AND(A8>0,N8>=0),1,0) -> 0 | S8: =IF(AND(A8>0,Q8>=0),1,0) -> 0 | U8: VAN a la tasa de descuento | V8: =SUM(P6:P66) -> 487908
A9: 3 | B9: =IF(A9=0,0,IF(A9<=Supuestos!$C$24,Supuestos!$C$22,IF(A9>=Supuestos!$D$8,$V$7,Supuestos!$C$22+($V$7-Supuestos!$C$22)*(A9-Supuestos!$C$24)/(Supuestos!$D$8-Supuestos!$C$24)))) -> 15 | C9: =B9*Supuestos!$D$6 -> 120 | D9: =C9*Supuestos!$C$42 -> 520 | E9: =IF(A9=0,0,MAX(Supuestos!$C$23,ROUNDUP(C9/Supuestos!$C$18,0))) -> 6 | F9: =MAX(0,E9-IF(A8=0,Supuestos!$C$23,E8))+Supuestos!$C$19*E9 -> 0.18 | G9: =IF(A9=0,0,MAX(1,ROUNDUP(B9/Supuestos!$C$21,0))) -> 1 | H9: =D9*(Supuestos!$C$14+Supuestos!$D$7) -> 52000 | I9: =D9*Supuestos!$C$43 -> 38740 | J9: =IF(A9=0,0,Supuestos!$C$44+G9*Supuestos!$C$26) -> 73000 | K9: =F9*Supuestos!$C$20 -> 630 | L9: =IF(A9=0,Supuestos!$C$45,0) -> 0 | M9: =IF(A9=0,-L9,H9-I9-J9-K9) -> -60370 | N9: =N8+M9 -> -407110 | O9: =1/(1+Supuestos!$C$46)^A9 -> 0.97645409 | P9: =M9*O9 -> -58948.533 | Q9: =Q8+P9 -> -404259.54 | R9: =IF(AND(A9>0,N9>=0),1,0) -> 0 | S9: =IF(AND(A9>0,Q9>=0),1,0) -> 0 | U9: TIR mensual | V9: =IFERROR(IRR(M6:M66,0.02),"No existe") -> 0.023098352
A10: 4 | B10: =IF(A10=0,0,IF(A10<=Supuestos!$C$24,Supuestos!$C$22,IF(A10>=Supuestos!$D$8,$V$7,Supuestos!$C$22+($V$7-Supuestos!$C$22)*(A10-Supuestos!$C$24)/(Supuestos!$D$8-Supuestos!$C$24)))) -> 15 | C10: =B10*Supuestos!$D$6 -> 120 | D10: =C10*Supuestos!$C$42 -> 520 | E10: =IF(A10=0,0,MAX(Supuestos!$C$23,ROUNDUP(C10/Supuestos!$C$18,0))) -> 6 | F10: =MAX(0,E10-IF(A9=0,Supuestos!$C$23,E9))+Supuestos!$C$19*E10 -> 0.18 | G10: =IF(A10=0,0,MAX(1,ROUNDUP(B10/Supuestos!$C$21,0))) -> 1 | H10: =D10*(Supuestos!$C$14+Supuestos!$D$7) -> 52000 | I10: =D10*Supuestos!$C$43 -> 38740 | J10: =IF(A10=0,0,Supuestos!$C$44+G10*Supuestos!$C$26) -> 73000 | K10: =F10*Supuestos!$C$20 -> 630 | L10: =IF(A10=0,Supuestos!$C$45,0) -> 0 | M10: =IF(A10=0,-L10,H10-I10-J10-K10) -> -60370 | N10: =N9+M10 -> -467480 | O10: =1/(1+Supuestos!$C$46)^A10 -> 0.96872931 | P10: =M10*O10 -> -58482.188 | Q10: =Q9+P10 -> -462741.73 | R10: =IF(AND(A10>0,N10>=0),1,0) -> 0 | S10: =IF(AND(A10>0,Q10>=0),1,0) -> 0 | U10: TIR anual equivalente | V10: =IFERROR((1+V9)^12-1,"No existe") -> 0.31525095
A11: 5 | B11: =IF(A11=0,0,IF(A11<=Supuestos!$C$24,Supuestos!$C$22,IF(A11>=Supuestos!$D$8,$V$7,Supuestos!$C$22+($V$7-Supuestos!$C$22)*(A11-Supuestos!$C$24)/(Supuestos!$D$8-Supuestos!$C$24)))) -> 15 | C11: =B11*Supuestos!$D$6 -> 120 | D11: =C11*Supuestos!$C$42 -> 520 | E11: =IF(A11=0,0,MAX(Supuestos!$C$23,ROUNDUP(C11/Supuestos!$C$18,0))) -> 6 | F11: =MAX(0,E11-IF(A10=0,Supuestos!$C$23,E10))+Supuestos!$C$19*E11 -> 0.18 | G11: =IF(A11=0,0,MAX(1,ROUNDUP(B11/Supuestos!$C$21,0))) -> 1 | H11: =D11*(Supuestos!$C$14+Supuestos!$D$7) -> 52000 | I11: =D11*Supuestos!$C$43 -> 38740 | J11: =IF(A11=0,0,Supuestos!$C$44+G11*Supuestos!$C$26) -> 73000 | K11: =F11*Supuestos!$C$20 -> 630 | L11: =IF(A11=0,Supuestos!$C$45,0) -> 0 | M11: =IF(A11=0,-L11,H11-I11-J11-K11) -> -60370 | N11: =N10+M11 -> -527850 | O11: =1/(1+Supuestos!$C$46)^A11 -> 0.96106563 | P11: =M11*O11 -> -58019.532 | Q11: =Q10+P11 -> -520761.26 | R11: =IF(AND(A11>0,N11>=0),1,0) -> 0 | S11: =IF(AND(A11>0,Q11>=0),1,0) -> 0 | U11: Payback (meses) | V11: =IFERROR(INDEX(A6:A66,MATCH(1,R6:R66,0)),"No se recupera") -> 37
A12: 6 | B12: =IF(A12=0,0,IF(A12<=Supuestos!$C$24,Supuestos!$C$22,IF(A12>=Supuestos!$D$8,$V$7,Supuestos!$C$22+($V$7-Supuestos!$C$22)*(A12-Supuestos!$C$24)/(Supuestos!$D$8-Supuestos!$C$24)))) -> 15 | C12: =B12*Supuestos!$D$6 -> 120 | D12: =C12*Supuestos!$C$42 -> 520 | E12: =IF(A12=0,0,MAX(Supuestos!$C$23,ROUNDUP(C12/Supuestos!$C$18,0))) -> 6 | F12: =MAX(0,E12-IF(A11=0,Supuestos!$C$23,E11))+Supuestos!$C$19*E12 -> 0.18 | G12: =IF(A12=0,0,MAX(1,ROUNDUP(B12/Supuestos!$C$21,0))) -> 1 | H12: =D12*(Supuestos!$C$14+Supuestos!$D$7) -> 52000 | I12: =D12*Supuestos!$C$43 -> 38740 | J12: =IF(A12=0,0,Supuestos!$C$44+G12*Supuestos!$C$26) -> 73000 | K12: =F12*Supuestos!$C$20 -> 630 | L12: =IF(A12=0,Supuestos!$C$45,0) -> 0 | M12: =IF(A12=0,-L12,H12-I12-J12-K12) -> -60370 | N12: =N11+M12 -> -588220 | O12: =1/(1+Supuestos!$C$46)^A12 -> 0.95346259 | P12: =M12*O12 -> -57560.537 | Q12: =Q11+P12 -> -578321.8 | R12: =IF(AND(A12>0,N12>=0),1,0) -> 0 | S12: =IF(AND(A12>0,Q12>=0),1,0) -> 0 | U12: Payback descontado (meses) | V12: =IFERROR(INDEX(A6:A66,MATCH(1,S6:S66,0)),"No se recupera") -> 42
A13: 7 | B13: =IF(A13=0,0,IF(A13<=Supuestos!$C$24,Supuestos!$C$22,IF(A13>=Supuestos!$D$8,$V$7,Supuestos!$C$22+($V$7-Supuestos!$C$22)*(A13-Supuestos!$C$24)/(Supuestos!$D$8-Supuestos!$C$24)))) -> 29.441667 | C13: =B13*Supuestos!$D$6 -> 235.53333 | D13: =C13*Supuestos!$C$42 -> 1020.6444 | E13: =IF(A13=0,0,MAX(Supuestos!$C$23,ROUNDUP(C13/Supuestos!$C$18,0))) -> 8 | F13: =MAX(0,E13-IF(A12=0,Supuestos!$C$23,E12))+Supuestos!$C$19*E13 -> 2.24 | G13: =IF(A13=0,0,MAX(1,ROUNDUP(B13/Supuestos!$C$21,0))) -> 1 | H13: =D13*(Supuestos!$C$14+Supuestos!$D$7) -> 102064.44 | I13: =D13*Supuestos!$C$43 -> 76038.011 | J13: =IF(A13=0,0,Supuestos!$C$44+G13*Supuestos!$C$26) -> 73000 | K13: =F13*Supuestos!$C$20 -> 7840 | L13: =IF(A13=0,Supuestos!$C$45,0) -> 0 | M13: =IF(A13=0,-L13,H13-I13-J13-K13) -> -54813.567 | N13: =N12+M13 -> -643033.57 | O13: =1/(1+Supuestos!$C$46)^A13 -> 0.94591969 | P13: =M13*O13 -> -51849.232 | Q13: =Q12+P13 -> -630171.03 | R13: =IF(AND(A13>0,N13>=0),1,0) -> 0 | S13: =IF(AND(A13>0,Q13>=0),1,0) -> 0 | U13: Costos fijos en estado estable | V13: =J66 -> 121600
A14: 8 | B14: =IF(A14=0,0,IF(A14<=Supuestos!$C$24,Supuestos!$C$22,IF(A14>=Supuestos!$D$8,$V$7,Supuestos!$C$22+($V$7-Supuestos!$C$22)*(A14-Supuestos!$C$24)/(Supuestos!$D$8-Supuestos!$C$24)))) -> 43.883333 | C14: =B14*Supuestos!$D$6 -> 351.06667 | D14: =C14*Supuestos!$C$42 -> 1521.2889 | E14: =IF(A14=0,0,MAX(Supuestos!$C$23,ROUNDUP(C14/Supuestos!$C$18,0))) -> 12 | F14: =MAX(0,E14-IF(A13=0,Supuestos!$C$23,E13))+Supuestos!$C$19*E14 -> 4.36 | G14: =IF(A14=0,0,MAX(1,ROUNDUP(B14/Supuestos!$C$21,0))) -> 1 | H14: =D14*(Supuestos!$C$14+Supuestos!$D$7) -> 152128.89 | I14: =D14*Supuestos!$C$43 -> 113336.02 | J14: =IF(A14=0,0,Supuestos!$C$44+G14*Supuestos!$C$26) -> 73000 | K14: =F14*Supuestos!$C$20 -> 15260 | L14: =IF(A14=0,Supuestos!$C$45,0) -> 0 | M14: =IF(A14=0,-L14,H14-I14-J14-K14) -> -49467.133 | N14: =N13+M14 -> -692500.7 | O14: =1/(1+Supuestos!$C$46)^A14 -> 0.93843647 | P14: =M14*O14 -> -46421.762 | Q14: =Q13+P14 -> -676592.79 | R14: =IF(AND(A14>0,N14>=0),1,0) -> 0 | S14: =IF(AND(A14>0,Q14>=0),1,0) -> 0 | U14: Punto de equilibrio (horas al mes) | V14: =IF(V6>0,V13/V6,"No existe") -> 4768.6275
A15: 9 | B15: =IF(A15=0,0,IF(A15<=Supuestos!$C$24,Supuestos!$C$22,IF(A15>=Supuestos!$D$8,$V$7,Supuestos!$C$22+($V$7-Supuestos!$C$22)*(A15-Supuestos!$C$24)/(Supuestos!$D$8-Supuestos!$C$24)))) -> 58.325 | C15: =B15*Supuestos!$D$6 -> 466.6 | D15: =C15*Supuestos!$C$42 -> 2021.9333 | E15: =IF(A15=0,0,MAX(Supuestos!$C$23,ROUNDUP(C15/Supuestos!$C$18,0))) -> 16 | F15: =MAX(0,E15-IF(A14=0,Supuestos!$C$23,E14))+Supuestos!$C$19*E15 -> 4.48 | G15: =IF(A15=0,0,MAX(1,ROUNDUP(B15/Supuestos!$C$21,0))) -> 1 | H15: =D15*(Supuestos!$C$14+Supuestos!$D$7) -> 202193.33 | I15: =D15*Supuestos!$C$43 -> 150634.03 | J15: =IF(A15=0,0,Supuestos!$C$44+G15*Supuestos!$C$26) -> 73000 | K15: =F15*Supuestos!$C$20 -> 15680 | L15: =IF(A15=0,Supuestos!$C$45,0) -> 0 | M15: =IF(A15=0,-L15,H15-I15-J15-K15) -> -37120.7 | N15: =N14+M15 -> -729621.4 | O15: =1/(1+Supuestos!$C$46)^A15 -> 0.93101244 | P15: =M15*O15 -> -34559.834 | Q15: =Q14+P15 -> -711152.62 | R15: =IF(AND(A15>0,N15>=0),1,0) -> 0 | S15: =IF(AND(A15>0,Q15>=0),1,0) -> 0 | U15: Punto de equilibrio (familias) | V15: =IF(V6>0,V14/Supuestos!$C$42/Supuestos!$D$6,"No existe") -> 137.55656
A16: 10 | B16: =IF(A16=0,0,IF(A16<=Supuestos!$C$24,Supuestos!$C$22,IF(A16>=Supuestos!$D$8,$V$7,Supuestos!$C$22+($V$7-Supuestos!$C$22)*(A16-Supuestos!$C$24)/(Supuestos!$D$8-Supuestos!$C$24)))) -> 72.766667 | C16: =B16*Supuestos!$D$6 -> 582.13333 | D16: =C16*Supuestos!$C$42 -> 2522.5778 | E16: =IF(A16=0,0,MAX(Supuestos!$C$23,ROUNDUP(C16/Supuestos!$C$18,0))) -> 20 | F16: =MAX(0,E16-IF(A15=0,Supuestos!$C$23,E15))+Supuestos!$C$19*E16 -> 4.6 | G16: =IF(A16=0,0,MAX(1,ROUNDUP(B16/Supuestos!$C$21,0))) -> 1 | H16: =D16*(Supuestos!$C$14+Supuestos!$D$7) -> 252257.78 | I16: =D16*Supuestos!$C$43 -> 187932.04 | J16: =IF(A16=0,0,Supuestos!$C$44+G16*Supuestos!$C$26) -> 73000 | K16: =F16*Supuestos!$C$20 -> 16100 | L16: =IF(A16=0,Supuestos!$C$45,0) -> 0 | M16: =IF(A16=0,-L16,H16-I16-J16-K16) -> -24774.267 | N16: =N15+M16 -> -754395.67 | O16: =1/(1+Supuestos!$C$46)^A16 -> 0.92364715 | P16: =M16*O16 -> -22882.681 | Q16: =Q15+P16 -> -734035.31 | R16: =IF(AND(A16>0,N16>=0),1,0) -> 0 | S16: =IF(AND(A16>0,Q16>=0),1,0) -> 0 | U16: Utilidad neta acumulada (60 meses) | V16: =N66 -> 912104.2
A17: 11 | B17: =IF(A17=0,0,IF(A17<=Supuestos!$C$24,Supuestos!$C$22,IF(A17>=Supuestos!$D$8,$V$7,Supuestos!$C$22+($V$7-Supuestos!$C$22)*(A17-Supuestos!$C$24)/(Supuestos!$D$8-Supuestos!$C$24)))) -> 87.208333 | C17: =B17*Supuestos!$D$6 -> 697.66667 | D17: =C17*Supuestos!$C$42 -> 3023.2222 | E17: =IF(A17=0,0,MAX(Supuestos!$C$23,ROUNDUP(C17/Supuestos!$C$18,0))) -> 24 | F17: =MAX(0,E17-IF(A16=0,Supuestos!$C$23,E16))+Supuestos!$C$19*E17 -> 4.72 | G17: =IF(A17=0,0,MAX(1,ROUNDUP(B17/Supuestos!$C$21,0))) -> 2 | H17: =D17*(Supuestos!$C$14+Supuestos!$D$7) -> 302322.22 | I17: =D17*Supuestos!$C$43 -> 225230.06 | J17: =IF(A17=0,0,Supuestos!$C$44+G17*Supuestos!$C$26) -> 97300 | K17: =F17*Supuestos!$C$20 -> 16520 | L17: =IF(A17=0,Supuestos!$C$45,0) -> 0 | M17: =IF(A17=0,-L17,H17-I17-J17-K17) -> -36727.833 | N17: =N16+M17 -> -791123.5 | O17: =1/(1+Supuestos!$C$46)^A17 -> 0.91634013 | P17: =M17*O17 -> -33655.187 | Q17: =Q16+P17 -> -767690.49 | R17: =IF(AND(A17>0,N17>=0),1,0) -> 0 | S17: =IF(AND(A17>0,Q17>=0),1,0) -> 0 | U17: Inversión inicial | V17: =L6 -> 226000
A18: 12 | B18: =IF(A18=0,0,IF(A18<=Supuestos!$C$24,Supuestos!$C$22,IF(A18>=Supuestos!$D$8,$V$7,Supuestos!$C$22+($V$7-Supuestos!$C$22)*(A18-Supuestos!$C$24)/(Supuestos!$D$8-Supuestos!$C$24)))) -> 101.65 | C18: =B18*Supuestos!$D$6 -> 813.2 | D18: =C18*Supuestos!$C$42 -> 3523.8667 | E18: =IF(A18=0,0,MAX(Supuestos!$C$23,ROUNDUP(C18/Supuestos!$C$18,0))) -> 28 | F18: =MAX(0,E18-IF(A17=0,Supuestos!$C$23,E17))+Supuestos!$C$19*E18 -> 4.84 | G18: =IF(A18=0,0,MAX(1,ROUNDUP(B18/Supuestos!$C$21,0))) -> 2 | H18: =D18*(Supuestos!$C$14+Supuestos!$D$7) -> 352386.67 | I18: =D18*Supuestos!$C$43 -> 262528.07 | J18: =IF(A18=0,0,Supuestos!$C$44+G18*Supuestos!$C$26) -> 97300 | K18: =F18*Supuestos!$C$20 -> 16940 | L18: =IF(A18=0,Supuestos!$C$45,0) -> 0 | M18: =IF(A18=0,-L18,H18-I18-J18-K18) -> -24381.4 | N18: =N17+M18 -> -815504.9 | O18: =1/(1+Supuestos!$C$46)^A18 -> 0.90909091 | P18: =M18*O18 -> -22164.909 | Q18: =Q17+P18 -> -789855.4 | R18: =IF(AND(A18>0,N18>=0),1,0) -> 0 | S18: =IF(AND(A18>0,Q18>=0),1,0) -> 0 | U18: Capital de operación (3 meses) | V18: =3*(J7+I7) -> 335220
A19: 13 | B19: =IF(A19=0,0,IF(A19<=Supuestos!$C$24,Supuestos!$C$22,IF(A19>=Supuestos!$D$8,$V$7,Supuestos!$C$22+($V$7-Supuestos!$C$22)*(A19-Supuestos!$C$24)/(Supuestos!$D$8-Supuestos!$C$24)))) -> 116.09167 | C19: =B19*Supuestos!$D$6 -> 928.73333 | D19: =C19*Supuestos!$C$42 -> 4024.5111 | E19: =IF(A19=0,0,MAX(Supuestos!$C$23,ROUNDUP(C19/Supuestos!$C$18,0))) -> 31 | F19: =MAX(0,E19-IF(A18=0,Supuestos!$C$23,E18))+Supuestos!$C$19*E19 -> 3.93 | G19: =IF(A19=0,0,MAX(1,ROUNDUP(B19/Supuestos!$C$21,0))) -> 2 | H19: =D19*(Supuestos!$C$14+Supuestos!$D$7) -> 402451.11 | I19: =D19*Supuestos!$C$43 -> 299826.08 | J19: =IF(A19=0,0,Supuestos!$C$44+G19*Supuestos!$C$26) -> 97300 | K19: =F19*Supuestos!$C$20 -> 13755 | L19: =IF(A19=0,Supuestos!$C$45,0) -> 0 | M19: =IF(A19=0,-L19,H19-I19-J19-K19) -> -8429.9667 | N19: =N18+M19 -> -823934.87 | O19: =1/(1+Supuestos!$C$46)^A19 -> 0.90189904 | P19: =M19*O19 -> -7602.9788 | Q19: =Q18+P19 -> -797458.38 | R19: =IF(AND(A19>0,N19>=0),1,0) -> 0 | S19: =IF(AND(A19>0,Q19>=0),1,0) -> 0 | U19: Colchón para imprevistos | V19: =Supuestos!$C$36*(V17+V18) -> 56122
A20: 14 | B20: =IF(A20=0,0,IF(A20<=Supuestos!$C$24,Supuestos!$C$22,IF(A20>=Supuestos!$D$8,$V$7,Supuestos!$C$22+($V$7-Supuestos!$C$22)*(A20-Supuestos!$C$24)/(Supuestos!$D$8-Supuestos!$C$24)))) -> 130.53333 | C20: =B20*Supuestos!$D$6 -> 1044.2667 | D20: =C20*Supuestos!$C$42 -> 4525.1556 | E20: =IF(A20=0,0,MAX(Supuestos!$C$23,ROUNDUP(C20/Supuestos!$C$18,0))) -> 35 | F20: =MAX(0,E20-IF(A19=0,Supuestos!$C$23,E19))+Supuestos!$C$19*E20 -> 5.05 | G20: =IF(A20=0,0,MAX(1,ROUNDUP(B20/Supuestos!$C$21,0))) -> 2 | H20: =D20*(Supuestos!$C$14+Supuestos!$D$7) -> 452515.56 | I20: =D20*Supuestos!$C$43 -> 337124.09 | J20: =IF(A20=0,0,Supuestos!$C$44+G20*Supuestos!$C$26) -> 97300 | K20: =F20*Supuestos!$C$20 -> 17675 | L20: =IF(A20=0,Supuestos!$C$45,0) -> 0 | M20: =IF(A20=0,-L20,H20-I20-J20-K20) -> 416.46667 | N20: =N19+M20 -> -823518.4 | O20: =1/(1+Supuestos!$C$46)^A20 -> 0.89476407 | P20: =M20*O20 -> 372.63941 | Q20: =Q19+P20 -> -797085.74 | R20: =IF(AND(A20>0,N20>=0),1,0) -> 0 | S20: =IF(AND(A20>0,Q20>=0),1,0) -> 0 | U20: Requerimiento total de capital | V20: =V17+V18+V19 -> 617342
A21: 15 | B21: =IF(A21=0,0,IF(A21<=Supuestos!$C$24,Supuestos!$C$22,IF(A21>=Supuestos!$D$8,$V$7,Supuestos!$C$22+($V$7-Supuestos!$C$22)*(A21-Supuestos!$C$24)/(Supuestos!$D$8-Supuestos!$C$24)))) -> 144.975 | C21: =B21*Supuestos!$D$6 -> 1159.8 | D21: =C21*Supuestos!$C$42 -> 5025.8 | E21: =IF(A21=0,0,MAX(Supuestos!$C$23,ROUNDUP(C21/Supuestos!$C$18,0))) -> 39 | F21: =MAX(0,E21-IF(A20=0,Supuestos!$C$23,E20))+Supuestos!$C$19*E21 -> 5.17 | G21: =IF(A21=0,0,MAX(1,ROUNDUP(B21/Supuestos!$C$21,0))) -> 2 | H21: =D21*(Supuestos!$C$14+Supuestos!$D$7) -> 502580 | I21: =D21*Supuestos!$C$43 -> 374422.1 | J21: =IF(A21=0,0,Supuestos!$C$44+G21*Supuestos!$C$26) -> 97300 | K21: =F21*Supuestos!$C$20 -> 18095 | L21: =IF(A21=0,Supuestos!$C$45,0) -> 0 | M21: =IF(A21=0,-L21,H21-I21-J21-K21) -> 12762.9 | N21: =N20+M21 -> -810755.5 | O21: =1/(1+Supuestos!$C$46)^A21 -> 0.88768554 | P21: =M21*O21 -> 11329.442 | Q21: =Q20+P21 -> -785756.3 | R21: =IF(AND(A21>0,N21>=0),1,0) -> 0 | S21: =IF(AND(A21>0,Q21>=0),1,0) -> 0 | U21: Déficit acumulado máximo | V21: =-MIN(0,MIN(N6:N66)) -> 823934.87
A22: 16 | B22: =IF(A22=0,0,IF(A22<=Supuestos!$C$24,Supuestos!$C$22,IF(A22>=Supuestos!$D$8,$V$7,Supuestos!$C$22+($V$7-Supuestos!$C$22)*(A22-Supuestos!$C$24)/(Supuestos!$D$8-Supuestos!$C$24)))) -> 159.41667 | C22: =B22*Supuestos!$D$6 -> 1275.3333 | D22: =C22*Supuestos!$C$42 -> 5526.4444 | E22: =IF(A22=0,0,MAX(Supuestos!$C$23,ROUNDUP(C22/Supuestos!$C$18,0))) -> 43 | F22: =MAX(0,E22-IF(A21=0,Supuestos!$C$23,E21))+Supuestos!$C$19*E22 -> 5.29 | G22: =IF(A22=0,0,MAX(1,ROUNDUP(B22/Supuestos!$C$21,0))) -> 2 | H22: =D22*(Supuestos!$C$14+Supuestos!$D$7) -> 552644.44 | I22: =D22*Supuestos!$C$43 -> 411720.11 | J22: =IF(A22=0,0,Supuestos!$C$44+G22*Supuestos!$C$26) -> 97300 | K22: =F22*Supuestos!$C$20 -> 18515 | L22: =IF(A22=0,Supuestos!$C$45,0) -> 0 | M22: =IF(A22=0,-L22,H22-I22-J22-K22) -> 25109.333 | N22: =N21+M22 -> -785646.17 | O22: =1/(1+Supuestos!$C$46)^A22 -> 0.88066301 | P22: =M22*O22 -> 22112.861 | Q22: =Q21+P22 -> -763643.44 | R22: =IF(AND(A22>0,N22>=0),1,0) -> 0 | S22: =IF(AND(A22>0,Q22>=0),1,0) -> 0 | U22: Familias en estado estable | V22: =B66 -> 188.3
A23: 17 | B23: =IF(A23=0,0,IF(A23<=Supuestos!$C$24,Supuestos!$C$22,IF(A23>=Supuestos!$D$8,$V$7,Supuestos!$C$22+($V$7-Supuestos!$C$22)*(A23-Supuestos!$C$24)/(Supuestos!$D$8-Supuestos!$C$24)))) -> 173.85833 | C23: =B23*Supuestos!$D$6 -> 1390.8667 | D23: =C23*Supuestos!$C$42 -> 6027.0889 | E23: =IF(A23=0,0,MAX(Supuestos!$C$23,ROUNDUP(C23/Supuestos!$C$18,0))) -> 47 | F23: =MAX(0,E23-IF(A22=0,Supuestos!$C$23,E22))+Supuestos!$C$19*E23 -> 5.41 | G23: =IF(A23=0,0,MAX(1,ROUNDUP(B23/Supuestos!$C$21,0))) -> 3 | H23: =D23*(Supuestos!$C$14+Supuestos!$D$7) -> 602708.89 | I23: =D23*Supuestos!$C$43 -> 449018.12 | J23: =IF(A23=0,0,Supuestos!$C$44+G23*Supuestos!$C$26) -> 121600 | K23: =F23*Supuestos!$C$20 -> 18935 | L23: =IF(A23=0,Supuestos!$C$45,0) -> 0 | M23: =IF(A23=0,-L23,H23-I23-J23-K23) -> 13155.767 | N23: =N22+M23 -> -772490.4 | O23: =1/(1+Supuestos!$C$46)^A23 -> 0.87369603 | P23: =M23*O23 -> 11494.141 | Q23: =Q22+P23 -> -752149.3 | R23: =IF(AND(A23>0,N23>=0),1,0) -> 0 | S23: =IF(AND(A23>0,Q23>=0),1,0) -> 0 | U23: Horas de cuidado al mes en estado estable | V23: =D66 -> 6527.7333
A24: 18 | B24: =IF(A24=0,0,IF(A24<=Supuestos!$C$24,Supuestos!$C$22,IF(A24>=Supuestos!$D$8,$V$7,Supuestos!$C$22+($V$7-Supuestos!$C$22)*(A24-Supuestos!$C$24)/(Supuestos!$D$8-Supuestos!$C$24)))) -> 188.3 | C24: =B24*Supuestos!$D$6 -> 1506.4 | D24: =C24*Supuestos!$C$42 -> 6527.7333 | E24: =IF(A24=0,0,MAX(Supuestos!$C$23,ROUNDUP(C24/Supuestos!$C$18,0))) -> 51 | F24: =MAX(0,E24-IF(A23=0,Supuestos!$C$23,E23))+Supuestos!$C$19*E24 -> 5.53 | G24: =IF(A24=0,0,MAX(1,ROUNDUP(B24/Supuestos!$C$21,0))) -> 3 | H24: =D24*(Supuestos!$C$14+Supuestos!$D$7) -> 652773.33 | I24: =D24*Supuestos!$C$43 -> 486316.13 | J24: =IF(A24=0,0,Supuestos!$C$44+G24*Supuestos!$C$26) -> 121600 | K24: =F24*Supuestos!$C$20 -> 19355 | L24: =IF(A24=0,Supuestos!$C$45,0) -> 0 | M24: =IF(A24=0,-L24,H24-I24-J24-K24) -> 25502.2 | N24: =N23+M24 -> -746988.2 | O24: =1/(1+Supuestos!$C$46)^A24 -> 0.86678417 | P24: =M24*O24 -> 22104.903 | Q24: =Q23+P24 -> -730044.39 | R24: =IF(AND(A24>0,N24>=0),1,0) -> 0 | S24: =IF(AND(A24>0,Q24>=0),1,0) -> 0 | U24: Cuidadoras empleadas en estado estable | V24: =E66 -> 51
A25: 19 | B25: =IF(A25=0,0,IF(A25<=Supuestos!$C$24,Supuestos!$C$22,IF(A25>=Supuestos!$D$8,$V$7,Supuestos!$C$22+($V$7-Supuestos!$C$22)*(A25-Supuestos!$C$24)/(Supuestos!$D$8-Supuestos!$C$24)))) -> 188.3 | C25: =B25*Supuestos!$D$6 -> 1506.4 | D25: =C25*Supuestos!$C$42 -> 6527.7333 | E25: =IF(A25=0,0,MAX(Supuestos!$C$23,ROUNDUP(C25/Supuestos!$C$18,0))) -> 51 | F25: =MAX(0,E25-IF(A24=0,Supuestos!$C$23,E24))+Supuestos!$C$19*E25 -> 1.53 | G25: =IF(A25=0,0,MAX(1,ROUNDUP(B25/Supuestos!$C$21,0))) -> 3 | H25: =D25*(Supuestos!$C$14+Supuestos!$D$7) -> 652773.33 | I25: =D25*Supuestos!$C$43 -> 486316.13 | J25: =IF(A25=0,0,Supuestos!$C$44+G25*Supuestos!$C$26) -> 121600 | K25: =F25*Supuestos!$C$20 -> 5355 | L25: =IF(A25=0,Supuestos!$C$45,0) -> 0 | M25: =IF(A25=0,-L25,H25-I25-J25-K25) -> 39502.2 | N25: =N24+M25 -> -707486 | O25: =1/(1+Supuestos!$C$46)^A25 -> 0.85992699 | P25: =M25*O25 -> 33969.008 | Q25: =Q24+P25 -> -696075.39 | R25: =IF(AND(A25>0,N25>=0),1,0) -> 0 | S25: =IF(AND(A25>0,Q25>=0),1,0) -> 0 | U25: Familias en el mes de revisión | V25: =INDEX(B6:B66,(Supuestos!$C$37+1)) -> 101.65
A26: 20 | B26: =IF(A26=0,0,IF(A26<=Supuestos!$C$24,Supuestos!$C$22,IF(A26>=Supuestos!$D$8,$V$7,Supuestos!$C$22+($V$7-Supuestos!$C$22)*(A26-Supuestos!$C$24)/(Supuestos!$D$8-Supuestos!$C$24)))) -> 188.3 | C26: =B26*Supuestos!$D$6 -> 1506.4 | D26: =C26*Supuestos!$C$42 -> 6527.7333 | E26: =IF(A26=0,0,MAX(Supuestos!$C$23,ROUNDUP(C26/Supuestos!$C$18,0))) -> 51 | F26: =MAX(0,E26-IF(A25=0,Supuestos!$C$23,E25))+Supuestos!$C$19*E26 -> 1.53 | G26: =IF(A26=0,0,MAX(1,ROUNDUP(B26/Supuestos!$C$21,0))) -> 3 | H26: =D26*(Supuestos!$C$14+Supuestos!$D$7) -> 652773.33 | I26: =D26*Supuestos!$C$43 -> 486316.13 | J26: =IF(A26=0,0,Supuestos!$C$44+G26*Supuestos!$C$26) -> 121600 | K26: =F26*Supuestos!$C$20 -> 5355 | L26: =IF(A26=0,Supuestos!$C$45,0) -> 0 | M26: =IF(A26=0,-L26,H26-I26-J26-K26) -> 39502.2 | N26: =N25+M26 -> -667983.8 | O26: =1/(1+Supuestos!$C$46)^A26 -> 0.85312406 | P26: =M26*O26 -> 33700.277 | Q26: =Q25+P26 -> -662375.11 | R26: =IF(AND(A26>0,N26>=0),1,0) -> 0 | S26: =IF(AND(A26>0,Q26>=0),1,0) -> 0 | U26: ¿Se cierra en la revisión? | V26: =IF(ISNUMBER(V15),IF(V25<Supuestos!$C$38*V15,"Sí","No"),"Sí") -> No
A27: 21 | B27: =IF(A27=0,0,IF(A27<=Supuestos!$C$24,Supuestos!$C$22,IF(A27>=Supuestos!$D$8,$V$7,Supuestos!$C$22+($V$7-Supuestos!$C$22)*(A27-Supuestos!$C$24)/(Supuestos!$D$8-Supuestos!$C$24)))) -> 188.3 | C27: =B27*Supuestos!$D$6 -> 1506.4 | D27: =C27*Supuestos!$C$42 -> 6527.7333 | E27: =IF(A27=0,0,MAX(Supuestos!$C$23,ROUNDUP(C27/Supuestos!$C$18,0))) -> 51 | F27: =MAX(0,E27-IF(A26=0,Supuestos!$C$23,E26))+Supuestos!$C$19*E27 -> 1.53 | G27: =IF(A27=0,0,MAX(1,ROUNDUP(B27/Supuestos!$C$21,0))) -> 3 | H27: =D27*(Supuestos!$C$14+Supuestos!$D$7) -> 652773.33 | I27: =D27*Supuestos!$C$43 -> 486316.13 | J27: =IF(A27=0,0,Supuestos!$C$44+G27*Supuestos!$C$26) -> 121600 | K27: =F27*Supuestos!$C$20 -> 5355 | L27: =IF(A27=0,Supuestos!$C$45,0) -> 0 | M27: =IF(A27=0,-L27,H27-I27-J27-K27) -> 39502.2 | N27: =N26+M27 -> -628481.6 | O27: =1/(1+Supuestos!$C$46)^A27 -> 0.84637495 | P27: =M27*O27 -> 33433.673 | Q27: =Q26+P27 -> -628941.44 | R27: =IF(AND(A27>0,N27>=0),1,0) -> 0 | S27: =IF(AND(A27>0,Q27>=0),1,0) -> 0 | U27: Costo de cierre | V27: =Supuestos!$C$39*INDEX(J6:J66,(Supuestos!$C$37+1)) -> 194600
A28: 22 | B28: =IF(A28=0,0,IF(A28<=Supuestos!$C$24,Supuestos!$C$22,IF(A28>=Supuestos!$D$8,$V$7,Supuestos!$C$22+($V$7-Supuestos!$C$22)*(A28-Supuestos!$C$24)/(Supuestos!$D$8-Supuestos!$C$24)))) -> 188.3 | C28: =B28*Supuestos!$D$6 -> 1506.4 | D28: =C28*Supuestos!$C$42 -> 6527.7333 | E28: =IF(A28=0,0,MAX(Supuestos!$C$23,ROUNDUP(C28/Supuestos!$C$18,0))) -> 51 | F28: =MAX(0,E28-IF(A27=0,Supuestos!$C$23,E27))+Supuestos!$C$19*E28 -> 1.53 | G28: =IF(A28=0,0,MAX(1,ROUNDUP(B28/Supuestos!$C$21,0))) -> 3 | H28: =D28*(Supuestos!$C$14+Supuestos!$D$7) -> 652773.33 | I28: =D28*Supuestos!$C$43 -> 486316.13 | J28: =IF(A28=0,0,Supuestos!$C$44+G28*Supuestos!$C$26) -> 121600 | K28: =F28*Supuestos!$C$20 -> 5355 | L28: =IF(A28=0,Supuestos!$C$45,0) -> 0 | M28: =IF(A28=0,-L28,H28-I28-J28-K28) -> 39502.2 | N28: =N27+M28 -> -588979.4 | O28: =1/(1+Supuestos!$C$46)^A28 -> 0.83967923 | P28: =M28*O28 -> 33169.177 | Q28: =Q27+P28 -> -595772.26 | R28: =IF(AND(A28>0,N28>=0),1,0) -> 0 | S28: =IF(AND(A28>0,Q28>=0),1,0) -> 0 | U28: VAN con revisión en el mes 12 | V28: =IF(V26="Sí",SUM(P6:INDEX(P6:P66,(Supuestos!$C$37+1)))-V27/(1+Supuestos!$C$46)^(Supuestos!$C$37+1),V8) -> 487908
A29: 23 | B29: =IF(A29=0,0,IF(A29<=Supuestos!$C$24,Supuestos!$C$22,IF(A29>=Supuestos!$D$8,$V$7,Supuestos!$C$22+($V$7-Supuestos!$C$22)*(A29-Supuestos!$C$24)/(Supuestos!$D$8-Supuestos!$C$24)))) -> 188.3 | C29: =B29*Supuestos!$D$6 -> 1506.4 | D29: =C29*Supuestos!$C$42 -> 6527.7333 | E29: =IF(A29=0,0,MAX(Supuestos!$C$23,ROUNDUP(C29/Supuestos!$C$18,0))) -> 51 | F29: =MAX(0,E29-IF(A28=0,Supuestos!$C$23,E28))+Supuestos!$C$19*E29 -> 1.53 | G29: =IF(A29=0,0,MAX(1,ROUNDUP(B29/Supuestos!$C$21,0))) -> 3 | H29: =D29*(Supuestos!$C$14+Supuestos!$D$7) -> 652773.33 | I29: =D29*Supuestos!$C$43 -> 486316.13 | J29: =IF(A29=0,0,Supuestos!$C$44+G29*Supuestos!$C$26) -> 121600 | K29: =F29*Supuestos!$C$20 -> 5355 | L29: =IF(A29=0,Supuestos!$C$45,0) -> 0 | M29: =IF(A29=0,-L29,H29-I29-J29-K29) -> 39502.2 | N29: =N28+M29 -> -549477.2 | O29: =1/(1+Supuestos!$C$46)^A29 -> 0.83303648 | P29: =M29*O29 -> 32906.774 | Q29: =Q28+P29 -> -562865.49 | R29: =IF(AND(A29>0,N29>=0),1,0) -> 0 | S29: =IF(AND(A29>0,Q29>=0),1,0) -> 0 | U29: Utilidad neta con revisión | V29: =IF(V26="Sí",SUM(M6:INDEX(M6:M66,(Supuestos!$C$37+1)))-V27,V16) -> 912104.2
A30: 24 | B30: =IF(A30=0,0,IF(A30<=Supuestos!$C$24,Supuestos!$C$22,IF(A30>=Supuestos!$D$8,$V$7,Supuestos!$C$22+($V$7-Supuestos!$C$22)*(A30-Supuestos!$C$24)/(Supuestos!$D$8-Supuestos!$C$24)))) -> 188.3 | C30: =B30*Supuestos!$D$6 -> 1506.4 | D30: =C30*Supuestos!$C$42 -> 6527.7333 | E30: =IF(A30=0,0,MAX(Supuestos!$C$23,ROUNDUP(C30/Supuestos!$C$18,0))) -> 51 | F30: =MAX(0,E30-IF(A29=0,Supuestos!$C$23,E29))+Supuestos!$C$19*E30 -> 1.53 | G30: =IF(A30=0,0,MAX(1,ROUNDUP(B30/Supuestos!$C$21,0))) -> 3 | H30: =D30*(Supuestos!$C$14+Supuestos!$D$7) -> 652773.33 | I30: =D30*Supuestos!$C$43 -> 486316.13 | J30: =IF(A30=0,0,Supuestos!$C$44+G30*Supuestos!$C$26) -> 121600 | K30: =F30*Supuestos!$C$20 -> 5355 | L30: =IF(A30=0,Supuestos!$C$45,0) -> 0 | M30: =IF(A30=0,-L30,H30-I30-J30-K30) -> 39502.2 | N30: =N29+M30 -> -509975 | O30: =1/(1+Supuestos!$C$46)^A30 -> 0.82644628 | P30: =M30*O30 -> 32646.446 | Q30: =Q29+P30 -> -530219.04 | R30: =IF(AND(A30>0,N30>=0),1,0) -> 0 | S30: =IF(AND(A30>0,Q30>=0),1,0) -> 0
A31: 25 | B31: =IF(A31=0,0,IF(A31<=Supuestos!$C$24,Supuestos!$C$22,IF(A31>=Supuestos!$D$8,$V$7,Supuestos!$C$22+($V$7-Supuestos!$C$22)*(A31-Supuestos!$C$24)/(Supuestos!$D$8-Supuestos!$C$24)))) -> 188.3 | C31: =B31*Supuestos!$D$6 -> 1506.4 | D31: =C31*Supuestos!$C$42 -> 6527.7333 | E31: =IF(A31=0,0,MAX(Supuestos!$C$23,ROUNDUP(C31/Supuestos!$C$18,0))) -> 51 | F31: =MAX(0,E31-IF(A30=0,Supuestos!$C$23,E30))+Supuestos!$C$19*E31 -> 1.53 | G31: =IF(A31=0,0,MAX(1,ROUNDUP(B31/Supuestos!$C$21,0))) -> 3 | H31: =D31*(Supuestos!$C$14+Supuestos!$D$7) -> 652773.33 | I31: =D31*Supuestos!$C$43 -> 486316.13 | J31: =IF(A31=0,0,Supuestos!$C$44+G31*Supuestos!$C$26) -> 121600 | K31: =F31*Supuestos!$C$20 -> 5355 | L31: =IF(A31=0,Supuestos!$C$45,0) -> 0 | M31: =IF(A31=0,-L31,H31-I31-J31-K31) -> 39502.2 | N31: =N30+M31 -> -470472.8 | O31: =1/(1+Supuestos!$C$46)^A31 -> 0.81990822 | P31: =M31*O31 -> 32388.178 | Q31: =Q30+P31 -> -497830.86 | R31: =IF(AND(A31>0,N31>=0),1,0) -> 0 | S31: =IF(AND(A31>0,Q31>=0),1,0) -> 0
A32: 26 | B32: =IF(A32=0,0,IF(A32<=Supuestos!$C$24,Supuestos!$C$22,IF(A32>=Supuestos!$D$8,$V$7,Supuestos!$C$22+($V$7-Supuestos!$C$22)*(A32-Supuestos!$C$24)/(Supuestos!$D$8-Supuestos!$C$24)))) -> 188.3 | C32: =B32*Supuestos!$D$6 -> 1506.4 | D32: =C32*Supuestos!$C$42 -> 6527.7333 | E32: =IF(A32=0,0,MAX(Supuestos!$C$23,ROUNDUP(C32/Supuestos!$C$18,0))) -> 51 | F32: =MAX(0,E32-IF(A31=0,Supuestos!$C$23,E31))+Supuestos!$C$19*E32 -> 1.53 | G32: =IF(A32=0,0,MAX(1,ROUNDUP(B32/Supuestos!$C$21,0))) -> 3 | H32: =D32*(Supuestos!$C$14+Supuestos!$D$7) -> 652773.33 | I32: =D32*Supuestos!$C$43 -> 486316.13 | J32: =IF(A32=0,0,Supuestos!$C$44+G32*Supuestos!$C$26) -> 121600 | K32: =F32*Supuestos!$C$20 -> 5355 | L32: =IF(A32=0,Supuestos!$C$45,0) -> 0 | M32: =IF(A32=0,-L32,H32-I32-J32-K32) -> 39502.2 | N32: =N31+M32 -> -430970.6 | O32: =1/(1+Supuestos!$C$46)^A32 -> 0.81342188 | P32: =M32*O32 -> 32131.954 | Q32: =Q31+P32 -> -465698.91 | R32: =IF(AND(A32>0,N32>=0),1,0) -> 0 | S32: =IF(AND(A32>0,Q32>=0),1,0) -> 0
A33: 27 | B33: =IF(A33=0,0,IF(A33<=Supuestos!$C$24,Supuestos!$C$22,IF(A33>=Supuestos!$D$8,$V$7,Supuestos!$C$22+($V$7-Supuestos!$C$22)*(A33-Supuestos!$C$24)/(Supuestos!$D$8-Supuestos!$C$24)))) -> 188.3 | C33: =B33*Supuestos!$D$6 -> 1506.4 | D33: =C33*Supuestos!$C$42 -> 6527.7333 | E33: =IF(A33=0,0,MAX(Supuestos!$C$23,ROUNDUP(C33/Supuestos!$C$18,0))) -> 51 | F33: =MAX(0,E33-IF(A32=0,Supuestos!$C$23,E32))+Supuestos!$C$19*E33 -> 1.53 | G33: =IF(A33=0,0,MAX(1,ROUNDUP(B33/Supuestos!$C$21,0))) -> 3 | H33: =D33*(Supuestos!$C$14+Supuestos!$D$7) -> 652773.33 | I33: =D33*Supuestos!$C$43 -> 486316.13 | J33: =IF(A33=0,0,Supuestos!$C$44+G33*Supuestos!$C$26) -> 121600 | K33: =F33*Supuestos!$C$20 -> 5355 | L33: =IF(A33=0,Supuestos!$C$45,0) -> 0 | M33: =IF(A33=0,-L33,H33-I33-J33-K33) -> 39502.2 | N33: =N32+M33 -> -391468.4 | O33: =1/(1+Supuestos!$C$46)^A33 -> 0.80698685 | P33: =M33*O33 -> 31877.756 | Q33: =Q32+P33 -> -433821.15 | R33: =IF(AND(A33>0,N33>=0),1,0) -> 0 | S33: =IF(AND(A33>0,Q33>=0),1,0) -> 0
A34: 28 | B34: =IF(A34=0,0,IF(A34<=Supuestos!$C$24,Supuestos!$C$22,IF(A34>=Supuestos!$D$8,$V$7,Supuestos!$C$22+($V$7-Supuestos!$C$22)*(A34-Supuestos!$C$24)/(Supuestos!$D$8-Supuestos!$C$24)))) -> 188.3 | C34: =B34*Supuestos!$D$6 -> 1506.4 | D34: =C34*Supuestos!$C$42 -> 6527.7333 | E34: =IF(A34=0,0,MAX(Supuestos!$C$23,ROUNDUP(C34/Supuestos!$C$18,0))) -> 51 | F34: =MAX(0,E34-IF(A33=0,Supuestos!$C$23,E33))+Supuestos!$C$19*E34 -> 1.53 | G34: =IF(A34=0,0,MAX(1,ROUNDUP(B34/Supuestos!$C$21,0))) -> 3 | H34: =D34*(Supuestos!$C$14+Supuestos!$D$7) -> 652773.33 | I34: =D34*Supuestos!$C$43 -> 486316.13 | J34: =IF(A34=0,0,Supuestos!$C$44+G34*Supuestos!$C$26) -> 121600 | K34: =F34*Supuestos!$C$20 -> 5355 | L34: =IF(A34=0,Supuestos!$C$45,0) -> 0 | M34: =IF(A34=0,-L34,H34-I34-J34-K34) -> 39502.2 | N34: =N33+M34 -> -351966.2 | O34: =1/(1+Supuestos!$C$46)^A34 -> 0.80060273 | P34: =M34*O34 -> 31625.569 | Q34: =Q33+P34 -> -402195.58 | R34: =IF(AND(A34>0,N34>=0),1,0) -> 0 | S34: =IF(AND(A34>0,Q34>=0),1,0) -> 0
A35: 29 | B35: =IF(A35=0,0,IF(A35<=Supuestos!$C$24,Supuestos!$C$22,IF(A35>=Supuestos!$D$8,$V$7,Supuestos!$C$22+($V$7-Supuestos!$C$22)*(A35-Supuestos!$C$24)/(Supuestos!$D$8-Supuestos!$C$24)))) -> 188.3 | C35: =B35*Supuestos!$D$6 -> 1506.4 | D35: =C35*Supuestos!$C$42 -> 6527.7333 | E35: =IF(A35=0,0,MAX(Supuestos!$C$23,ROUNDUP(C35/Supuestos!$C$18,0))) -> 51 | F35: =MAX(0,E35-IF(A34=0,Supuestos!$C$23,E34))+Supuestos!$C$19*E35 -> 1.53 | G35: =IF(A35=0,0,MAX(1,ROUNDUP(B35/Supuestos!$C$21,0))) -> 3 | H35: =D35*(Supuestos!$C$14+Supuestos!$D$7) -> 652773.33 | I35: =D35*Supuestos!$C$43 -> 486316.13 | J35: =IF(A35=0,0,Supuestos!$C$44+G35*Supuestos!$C$26) -> 121600 | K35: =F35*Supuestos!$C$20 -> 5355 | L35: =IF(A35=0,Supuestos!$C$45,0) -> 0 | M35: =IF(A35=0,-L35,H35-I35-J35-K35) -> 39502.2 | N35: =N34+M35 -> -312464 | O35: =1/(1+Supuestos!$C$46)^A35 -> 0.79426912 | P35: =M35*O35 -> 31375.378 | Q35: =Q34+P35 -> -370820.21 | R35: =IF(AND(A35>0,N35>=0),1,0) -> 0 | S35: =IF(AND(A35>0,Q35>=0),1,0) -> 0
A36: 30 | B36: =IF(A36=0,0,IF(A36<=Supuestos!$C$24,Supuestos!$C$22,IF(A36>=Supuestos!$D$8,$V$7,Supuestos!$C$22+($V$7-Supuestos!$C$22)*(A36-Supuestos!$C$24)/(Supuestos!$D$8-Supuestos!$C$24)))) -> 188.3 | C36: =B36*Supuestos!$D$6 -> 1506.4 | D36: =C36*Supuestos!$C$42 -> 6527.7333 | E36: =IF(A36=0,0,MAX(Supuestos!$C$23,ROUNDUP(C36/Supuestos!$C$18,0))) -> 51 | F36: =MAX(0,E36-IF(A35=0,Supuestos!$C$23,E35))+Supuestos!$C$19*E36 -> 1.53 | G36: =IF(A36=0,0,MAX(1,ROUNDUP(B36/Supuestos!$C$21,0))) -> 3 | H36: =D36*(Supuestos!$C$14+Supuestos!$D$7) -> 652773.33 | I36: =D36*Supuestos!$C$43 -> 486316.13 | J36: =IF(A36=0,0,Supuestos!$C$44+G36*Supuestos!$C$26) -> 121600 | K36: =F36*Supuestos!$C$20 -> 5355 | L36: =IF(A36=0,Supuestos!$C$45,0) -> 0 | M36: =IF(A36=0,-L36,H36-I36-J36-K36) -> 39502.2 | N36: =N35+M36 -> -272961.8 | O36: =1/(1+Supuestos!$C$46)^A36 -> 0.78798561 | P36: =M36*O36 -> 31127.165 | Q36: =Q35+P36 -> -339693.04 | R36: =IF(AND(A36>0,N36>=0),1,0) -> 0 | S36: =IF(AND(A36>0,Q36>=0),1,0) -> 0
A37: 31 | B37: =IF(A37=0,0,IF(A37<=Supuestos!$C$24,Supuestos!$C$22,IF(A37>=Supuestos!$D$8,$V$7,Supuestos!$C$22+($V$7-Supuestos!$C$22)*(A37-Supuestos!$C$24)/(Supuestos!$D$8-Supuestos!$C$24)))) -> 188.3 | C37: =B37*Supuestos!$D$6 -> 1506.4 | D37: =C37*Supuestos!$C$42 -> 6527.7333 | E37: =IF(A37=0,0,MAX(Supuestos!$C$23,ROUNDUP(C37/Supuestos!$C$18,0))) -> 51 | F37: =MAX(0,E37-IF(A36=0,Supuestos!$C$23,E36))+Supuestos!$C$19*E37 -> 1.53 | G37: =IF(A37=0,0,MAX(1,ROUNDUP(B37/Supuestos!$C$21,0))) -> 3 | H37: =D37*(Supuestos!$C$14+Supuestos!$D$7) -> 652773.33 | I37: =D37*Supuestos!$C$43 -> 486316.13 | J37: =IF(A37=0,0,Supuestos!$C$44+G37*Supuestos!$C$26) -> 121600 | K37: =F37*Supuestos!$C$20 -> 5355 | L37: =IF(A37=0,Supuestos!$C$45,0) -> 0 | M37: =IF(A37=0,-L37,H37-I37-J37-K37) -> 39502.2 | N37: =N36+M37 -> -233459.6 | O37: =1/(1+Supuestos!$C$46)^A37 -> 0.78175181 | P37: =M37*O37 -> 30880.916 | Q37: =Q36+P37 -> -308812.12 | R37: =IF(AND(A37>0,N37>=0),1,0) -> 0 | S37: =IF(AND(A37>0,Q37>=0),1,0) -> 0
A38: 32 | B38: =IF(A38=0,0,IF(A38<=Supuestos!$C$24,Supuestos!$C$22,IF(A38>=Supuestos!$D$8,$V$7,Supuestos!$C$22+($V$7-Supuestos!$C$22)*(A38-Supuestos!$C$24)/(Supuestos!$D$8-Supuestos!$C$24)))) -> 188.3 | C38: =B38*Supuestos!$D$6 -> 1506.4 | D38: =C38*Supuestos!$C$42 -> 6527.7333 | E38: =IF(A38=0,0,MAX(Supuestos!$C$23,ROUNDUP(C38/Supuestos!$C$18,0))) -> 51 | F38: =MAX(0,E38-IF(A37=0,Supuestos!$C$23,E37))+Supuestos!$C$19*E38 -> 1.53 | G38: =IF(A38=0,0,MAX(1,ROUNDUP(B38/Supuestos!$C$21,0))) -> 3 | H38: =D38*(Supuestos!$C$14+Supuestos!$D$7) -> 652773.33 | I38: =D38*Supuestos!$C$43 -> 486316.13 | J38: =IF(A38=0,0,Supuestos!$C$44+G38*Supuestos!$C$26) -> 121600 | K38: =F38*Supuestos!$C$20 -> 5355 | L38: =IF(A38=0,Supuestos!$C$45,0) -> 0 | M38: =IF(A38=0,-L38,H38-I38-J38-K38) -> 39502.2 | N38: =N37+M38 -> -193957.4 | O38: =1/(1+Supuestos!$C$46)^A38 -> 0.77556733 | P38: =M38*O38 -> 30636.616 | Q38: =Q37+P38 -> -278175.51 | R38: =IF(AND(A38>0,N38>=0),1,0) -> 0 | S38: =IF(AND(A38>0,Q38>=0),1,0) -> 0
A39: 33 | B39: =IF(A39=0,0,IF(A39<=Supuestos!$C$24,Supuestos!$C$22,IF(A39>=Supuestos!$D$8,$V$7,Supuestos!$C$22+($V$7-Supuestos!$C$22)*(A39-Supuestos!$C$24)/(Supuestos!$D$8-Supuestos!$C$24)))) -> 188.3 | C39: =B39*Supuestos!$D$6 -> 1506.4 | D39: =C39*Supuestos!$C$42 -> 6527.7333 | E39: =IF(A39=0,0,MAX(Supuestos!$C$23,ROUNDUP(C39/Supuestos!$C$18,0))) -> 51 | F39: =MAX(0,E39-IF(A38=0,Supuestos!$C$23,E38))+Supuestos!$C$19*E39 -> 1.53 | G39: =IF(A39=0,0,MAX(1,ROUNDUP(B39/Supuestos!$C$21,0))) -> 3 | H39: =D39*(Supuestos!$C$14+Supuestos!$D$7) -> 652773.33 | I39: =D39*Supuestos!$C$43 -> 486316.13 | J39: =IF(A39=0,0,Supuestos!$C$44+G39*Supuestos!$C$26) -> 121600 | K39: =F39*Supuestos!$C$20 -> 5355 | L39: =IF(A39=0,Supuestos!$C$45,0) -> 0 | M39: =IF(A39=0,-L39,H39-I39-J39-K39) -> 39502.2 | N39: =N38+M39 -> -154455.2 | O39: =1/(1+Supuestos!$C$46)^A39 -> 0.76943177 | P39: =M39*O39 -> 30394.248 | Q39: =Q38+P39 -> -247781.26 | R39: =IF(AND(A39>0,N39>=0),1,0) -> 0 | S39: =IF(AND(A39>0,Q39>=0),1,0) -> 0
A40: 34 | B40: =IF(A40=0,0,IF(A40<=Supuestos!$C$24,Supuestos!$C$22,IF(A40>=Supuestos!$D$8,$V$7,Supuestos!$C$22+($V$7-Supuestos!$C$22)*(A40-Supuestos!$C$24)/(Supuestos!$D$8-Supuestos!$C$24)))) -> 188.3 | C40: =B40*Supuestos!$D$6 -> 1506.4 | D40: =C40*Supuestos!$C$42 -> 6527.7333 | E40: =IF(A40=0,0,MAX(Supuestos!$C$23,ROUNDUP(C40/Supuestos!$C$18,0))) -> 51 | F40: =MAX(0,E40-IF(A39=0,Supuestos!$C$23,E39))+Supuestos!$C$19*E40 -> 1.53 | G40: =IF(A40=0,0,MAX(1,ROUNDUP(B40/Supuestos!$C$21,0))) -> 3 | H40: =D40*(Supuestos!$C$14+Supuestos!$D$7) -> 652773.33 | I40: =D40*Supuestos!$C$43 -> 486316.13 | J40: =IF(A40=0,0,Supuestos!$C$44+G40*Supuestos!$C$26) -> 121600 | K40: =F40*Supuestos!$C$20 -> 5355 | L40: =IF(A40=0,Supuestos!$C$45,0) -> 0 | M40: =IF(A40=0,-L40,H40-I40-J40-K40) -> 39502.2 | N40: =N39+M40 -> -114953 | O40: =1/(1+Supuestos!$C$46)^A40 -> 0.76334475 | P40: =M40*O40 -> 30153.797 | Q40: =Q39+P40 -> -217627.46 | R40: =IF(AND(A40>0,N40>=0),1,0) -> 0 | S40: =IF(AND(A40>0,Q40>=0),1,0) -> 0
A41: 35 | B41: =IF(A41=0,0,IF(A41<=Supuestos!$C$24,Supuestos!$C$22,IF(A41>=Supuestos!$D$8,$V$7,Supuestos!$C$22+($V$7-Supuestos!$C$22)*(A41-Supuestos!$C$24)/(Supuestos!$D$8-Supuestos!$C$24)))) -> 188.3 | C41: =B41*Supuestos!$D$6 -> 1506.4 | D41: =C41*Supuestos!$C$42 -> 6527.7333 | E41: =IF(A41=0,0,MAX(Supuestos!$C$23,ROUNDUP(C41/Supuestos!$C$18,0))) -> 51 | F41: =MAX(0,E41-IF(A40=0,Supuestos!$C$23,E40))+Supuestos!$C$19*E41 -> 1.53 | G41: =IF(A41=0,0,MAX(1,ROUNDUP(B41/Supuestos!$C$21,0))) -> 3 | H41: =D41*(Supuestos!$C$14+Supuestos!$D$7) -> 652773.33 | I41: =D41*Supuestos!$C$43 -> 486316.13 | J41: =IF(A41=0,0,Supuestos!$C$44+G41*Supuestos!$C$26) -> 121600 | K41: =F41*Supuestos!$C$20 -> 5355 | L41: =IF(A41=0,Supuestos!$C$45,0) -> 0 | M41: =IF(A41=0,-L41,H41-I41-J41-K41) -> 39502.2 | N41: =N40+M41 -> -75450.8 | O41: =1/(1+Supuestos!$C$46)^A41 -> 0.75730589 | P41: =M41*O41 -> 29915.249 | Q41: =Q40+P41 -> -187712.21 | R41: =IF(AND(A41>0,N41>=0),1,0) -> 0 | S41: =IF(AND(A41>0,Q41>=0),1,0) -> 0
... A66: 60 | B66: =IF(A66=0,0,IF(A66<=Supuestos!$C$24,Supuestos!$C$22,IF(A66>=Supuestos!$D$8,$V$7,Supuestos!$C$22+($V$7-Supuestos!$C$22)*(A66-Supuestos!$C$24)/(Supuestos!$D$8-Supuestos!$C$24)))) -> 188.3 | C66: =B66*Supuestos!$D$6 -> 1506.4 | D66: =C66*Supuestos!$C$42 -> 6527.7333 | E66: =IF(A66=0,0,MAX(Supuestos!$C$23,ROUNDUP(C66/Supuestos!$C$18,0))) -> 51 | F66: =MAX(0,E66-IF(A65=0,Supuestos!$C$23,E65))+Supuestos!$C$19*E66 -> 1.53 | G66: =IF(A66=0,0,MAX(1,ROUNDUP(B66/Supuestos!$C$21,0))) -> 3 | H66: =D66*(Supuestos!$C$14+Supuestos!$D$7) -> 652773.33 | I66: =D66*Supuestos!$C$43 -> 486316.13 | J66: =IF(A66=0,0,Supuestos!$C$44+G66*Supuestos!$C$26) -> 121600 | K66: =F66*Supuestos!$C$20 -> 5355 | L66: =IF(A66=0,Supuestos!$C$45,0) -> 0 | M66: =IF(A66=0,-L66,H66-I66-J66-K66) -> 39502.2 | N66: =N65+M66 -> 912104.2 | O66: =1/(1+Supuestos!$C$46)^A66 -> 0.62092132 | P66: =M66*O66 -> 24527.758 | Q66: =Q65+P66 -> 487908 | R66: =IF(AND(A66>0,N66>=0),1,0) -> 1 | S66: =IF(AND(A66>0,Q66>=0),1,0) -> 1

Sheet Flujo Optimista
A1: Flujo mensual — escenario optimista (pesos de 2026)
A2: Todas las celdas son fórmulas que leen la hoja «Supuestos» (texto verde: vínculo). Mes 0 = inversión inicial.
U3: Indicador | V3: Valor
U4: Escenario | V4: Optimista
A5: Mes | B5: Familias | C5: Horas por semana | D5: Horas al mes | E5: Cuidadoras | F5: Cuidadoras nuevas (incluye rotación) | G5: Trabajadoras sociales | H5: Ingresos ($) | I5: Costo variable ($) | J5: Costos fijos ($) | K5: Capacitación ($) | L5: Inversión ($) | M5: Flujo neto ($) | N5: Flujo acumulado ($) | O5: Factor de descuento | P5: Flujo descontado ($) | Q5: Acumulado descontado ($) | R5: ¿Recuperado? | S5: ¿Recuperado (descontado)? | U5: Tarifa por hora (copago + subsidio) | V5: =Supuestos!$C$14+Supuestos!$E$7 -> 100
A6: 0 | B6: =IF(A6=0,0,IF(A6<=Supuestos!$C$24,Supuestos!$C$22,IF(A6>=Supuestos!$E$8,$V$7,Supuestos!$C$22+($V$7-Supuestos!$C$22)*(A6-Supuestos!$C$24)/(Supuestos!$E$8-Supuestos!$C$24)))) -> 0 | C6: =B6*Supuestos!$E$6 -> 0 | D6: =C6*Supuestos!$C$42 -> 0 | E6: =IF(A6=0,0,MAX(Supuestos!$C$23,ROUNDUP(C6/Supuestos!$C$18,0))) -> 0 | F6: 0 | G6: =IF(A6=0,0,MAX(1,ROUNDUP(B6/Supuestos!$C$21,0))) -> 0 | H6: =D6*(Supuestos!$C$14+Supuestos!$E$7) -> 0 | I6: =D6*Supuestos!$C$43 -> 0 | J6: =IF(A6=0,0,Supuestos!$C$44+G6*Supuestos!$C$26) -> 0 | K6: =F6*Supuestos!$C$20 -> 0 | L6: =IF(A6=0,Supuestos!$C$45,0) -> 226000 | M6: =IF(A6=0,-L6,H6-I6-J6-K6) -> -226000 | N6: =M6 -> -226000 | O6: =1/(1+Supuestos!$C$46)^A6 -> 1 | P6: =M6*O6 -> -226000 | Q6: =P6 -> -226000 | R6: =IF(AND(A6>0,N6>=0),1,0) -> 0 | S6: =IF(AND(A6>0,Q6>=0),1,0) -> 0 | U6: Margen por hora | V6: =V5-Supuestos!$C$43 -> 25.5
A7: 1 | B7: =IF(A7=0,0,IF(A7<=Supuestos!$C$24,Supuestos!$C$22,IF(A7>=Supuestos!$E$8,$V$7,Supuestos!$C$22+($V$7-Supuestos!$C$22)*(A7-Supuestos!$C$24)/(Supuestos!$E$8-Supuestos!$C$24)))) -> 15 | C7: =B7*Supuestos!$E$6 -> 150 | D7: =C7*Supuestos!$C$42 -> 650 | E7: =IF(A7=0,0,MAX(Supuestos!$C$23,ROUNDUP(C7/Supuestos!$C$18,0))) -> 6 | F7: =MAX(0,E7-IF(A6=0,Supuestos!$C$23,E6))+Supuestos!$C$19*E7 -> 0.18 | G7: =IF(A7=0,0,MAX(1,ROUNDUP(B7/Supuestos!$C$21,0))) -> 1 | H7: =D7*(Supuestos!$C$14+Supuestos!$E$7) -> 65000 | I7: =D7*Supuestos!$C$43 -> 48425 | J7: =IF(A7=0,0,Supuestos!$C$44+G7*Supuestos!$C$26) -> 73000 | K7: =F7*Supuestos!$C$20 -> 630 | L7: =IF(A7=0,Supuestos!$C$45,0) -> 0 | M7: =IF(A7=0,-L7,H7-I7-J7-K7) -> -57055 | N7: =N6+M7 -> -283055 | O7: =1/(1+Supuestos!$C$46)^A7 -> 0.99208894 | P7: =M7*O7 -> -56603.635 | Q7: =Q6+P7 -> -282603.63 | R7: =IF(AND(A7>0,N7>=0),1,0) -> 0 | S7: =IF(AND(A7>0,Q7>=0),1,0) -> 0 | U7: Familias objetivo (estado estable) | V7: =MAX(Supuestos!$C$13*Supuestos!$E$5,Supuestos!$C$22) -> 301.28
A8: 2 | B8: =IF(A8=0,0,IF(A8<=Supuestos!$C$24,Supuestos!$C$22,IF(A8>=Supuestos!$E$8,$V$7,Supuestos!$C$22+($V$7-Supuestos!$C$22)*(A8-Supuestos!$C$24)/(Supuestos!$E$8-Supuestos!$C$24)))) -> 15 | C8: =B8*Supuestos!$E$6 -> 150 | D8: =C8*Supuestos!$C$42 -> 650 | E8: =IF(A8=0,0,MAX(Supuestos!$C$23,ROUNDUP(C8/Supuestos!$C$18,0))) -> 6 | F8: =MAX(0,E8-IF(A7=0,Supuestos!$C$23,E7))+Supuestos!$C$19*E8 -> 0.18 | G8: =IF(A8=0,0,MAX(1,ROUNDUP(B8/Supuestos!$C$21,0))) -> 1 | H8: =D8*(Supuestos!$C$14+Supuestos!$E$7) -> 65000 | I8: =D8*Supuestos!$C$43 -> 48425 | J8: =IF(A8=0,0,Supuestos!$C$44+G8*Supuestos!$C$26) -> 73000 | K8: =F8*Supuestos!$C$20 -> 630 | L8: =IF(A8=0,Supuestos!$C$45,0) -> 0 | M8: =IF(A8=0,-L8,H8-I8-J8-K8) -> -57055 | N8: =N7+M8 -> -340110 | O8: =1/(1+Supuestos!$C$46)^A8 -> 0.98424047 | P8: =M8*O8 -> -56155.84 | Q8: =Q7+P8 -> -338759.47 | R8: =IF(AND(A8>0,N8>=0),1,0) -> 0 | S8: =IF(AND(A8>0,Q8>=0),1,0) -> 0 | U8: VAN a la tasa de descuento | V8: =SUM(P6:P66) -> 5955041.8
A9: 3 | B9: =IF(A9=0,0,IF(A9<=Supuestos!$C$24,Supuestos!$C$22,IF(A9>=Supuestos!$E$8,$V$7,Supuestos!$C$22+($V$7-Supuestos!$C$22)*(A9-Supuestos!$C$24)/(Supuestos!$E$8-Supuestos!$C$24)))) -> 15 | C9: =B9*Supuestos!$E$6 -> 150 | D9: =C9*Supuestos!$C$42 -> 650 | E9: =IF(A9=0,0,MAX(Supuestos!$C$23,ROUNDUP(C9/Supuestos!$C$18,0))) -> 6 | F9: =MAX(0,E9-IF(A8=0,Supuestos!$C$23,E8))+Supuestos!$C$19*E9 -> 0.18 | G9: =IF(A9=0,0,MAX(1,ROUNDUP(B9/Supuestos!$C$21,0))) -> 1 | H9: =D9*(Supuestos!$C$14+Supuestos!$E$7) -> 65000 | I9: =D9*Supuestos!$C$43 -> 48425 | J9: =IF(A9=0,0,Supuestos!$C$44+G9*Supuestos!$C$26) -> 73000 | K9: =F9*Supuestos!$C$20 -> 630 | L9: =IF(A9=0,Supuestos!$C$45,0) -> 0 | M9: =IF(A9=0,-L9,H9-I9-J9-K9) -> -57055 | N9: =N8+M9 -> -397165 | O9: =1/(1+Supuestos!$C$46)^A9 -> 0.97645409 | P9: =M9*O9 -> -55711.588 | Q9: =Q8+P9 -> -394471.06 | R9: =IF(AND(A9>0,N9>=0),1,0) -> 0 | S9: =IF(AND(A9>0,Q9>=0),1,0) -> 0 | U9: TIR mensual | V9: =IFERROR(IRR(M6:M66,0.02),"No existe") -> 0.1126316
A10: 4 | B10: =IF(A10=0,0,IF(A10<=Supuestos!$C$24,Supuestos!$C$22,IF(A10>=Supuestos!$E$8,$V$7,Supuestos!$C$22+($V$7-Supuestos!$C$22)*(A10-Supuestos!$C$24)/(Supuestos!$E$8-Supuestos!$C$24)))) -> 15 | C10: =B10*Supuestos!$E$6 -> 150 | D10: =C10*Supuestos!$C$42 -> 650 | E10: =IF(A10=0,0,MAX(Supuestos!$C$23,ROUNDUP(C10/Supuestos!$C$18,0))) -> 6 | F10: =MAX(0,E10-IF(A9=0,Supuestos!$C$23,E9))+Supuestos!$C$19*E10 -> 0.18 | G10: =IF(A10=0,0,MAX(1,ROUNDUP(B10/Supuestos!$C$21,0))) -> 1 | H10: =D10*(Supuestos!$C$14+Supuestos!$E$7) -> 65000 | I10: =D10*Supuestos!$C$43 -> 48425 | J10: =IF(A10=0,0,Supuestos!$C$44+G10*Supuestos!$C$26) -> 73000 | K10: =F10*Supuestos!$C$20 -> 630 | L10: =IF(A10=0,Supuestos!$C$45,0) -> 0 | M10: =IF(A10=0,-L10,H10-I10-J10-K10) -> -57055 | N10: =N9+M10 -> -454220 | O10: =1/(1+Supuestos!$C$46)^A10 -> 0.96872931 | P10: =M10*O10 -> -55270.851 | Q10: =Q9+P10 -> -449741.91 | R10: =IF(AND(A10>0,N10>=0),1,0) -> 0 | S10: =IF(AND(A10>0,Q10>=0),1,0) -> 0 | U10: TIR anual equivalente | V10: =IFERROR((1+V9)^12-1,"No existe") -> 2.5992888
A11: 5 | B11: =IF(A11=0,0,IF(A11<=Supuestos!$C$24,Supuestos!$C$22,IF(A11>=Supuestos!$E$8,$V$7,Supuestos!$C$22+($V$7-Supuestos!$C$22)*(A11-Supuestos!$C$24)/(Supuestos!$E$8-Supuestos!$C$24)))) -> 15 | C11: =B11*Supuestos!$E$6 -> 150 | D11: =C11*Supuestos!$C$42 -> 650 | E11: =IF(A11=0,0,MAX(Supuestos!$C$23,ROUNDUP(C11/Supuestos!$C$18,0))) -> 6 | F11: =MAX(0,E11-IF(A10=0,Supuestos!$C$23,E10))+Supuestos!$C$19*E11 -> 0.18 | G11: =IF(A11=0,0,MAX(1,ROUNDUP(B11/Supuestos!$C$21,0))) -> 1 | H11: =D11*(Supuestos!$C$14+Supuestos!$E$7) -> 65000 | I11: =D11*Supuestos!$C$43 -> 48425 | J11: =IF(A11=0,0,Supuestos!$C$44+G11*Supuestos!$C$26) -> 73000 | K11: =F11*Supuestos!$C$20 -> 630 | L11: =IF(A11=0,Supuestos!$C$45,0) -> 0 | M11: =IF(A11=0,-L11,H11-I11-J11-K11) -> -57055 | N11: =N10+M11 -> -511275 | O11: =1/(1+Supuestos!$C$46)^A11 -> 0.96106563 | P11: =M11*O11 -> -54833.6 | Q11: =Q10+P11 -> -504575.51 | R11: =IF(AND(A11>0,N11>=0),1,0) -> 0 | S11: =IF(AND(A11>0,Q11>=0),1,0) -> 0 | U11: Payback (meses) | V11: =IFERROR(INDEX(A6:A66,MATCH(1,R6:R66,0)),"No se recupera") -> 15
A12: 6 | B12: =IF(A12=0,0,IF(A12<=Supuestos!$C$24,Supuestos!$C$22,IF(A12>=Supuestos!$E$8,$V$7,Supuestos!$C$22+($V$7-Supuestos!$C$22)*(A12-Supuestos!$C$24)/(Supuestos!$E$8-Supuestos!$C$24)))) -> 15 | C12: =B12*Supuestos!$E$6 -> 150 | D12: =C12*Supuestos!$C$42 -> 650 | E12: =IF(A12=0,0,MAX(Supuestos!$C$23,ROUNDUP(C12/Supuestos!$C$18,0))) -> 6 | F12: =MAX(0,E12-IF(A11=0,Supuestos!$C$23,E11))+Supuestos!$C$19*E12 -> 0.18 | G12: =IF(A12=0,0,MAX(1,ROUNDUP(B12/Supuestos!$C$21,0))) -> 1 | H12: =D12*(Supuestos!$C$14+Supuestos!$E$7) -> 65000 | I12: =D12*Supuestos!$C$43 -> 48425 | J12: =IF(A12=0,0,Supuestos!$C$44+G12*Supuestos!$C$26) -> 73000 | K12: =F12*Supuestos!$C$20 -> 630 | L12: =IF(A12=0,Supuestos!$C$45,0) -> 0 | M12: =IF(A12=0,-L12,H12-I12-J12-K12) -> -57055 | N12: =N11+M12 -> -568330 | O12: =1/(1+Supuestos!$C$46)^A12 -> 0.95346259 | P12: =M12*O12 -> -54399.808 | Q12: =Q11+P12 -> -558975.32 | R12: =IF(AND(A12>0,N12>=0),1,0) -> 0 | S12: =IF(AND(A12>0,Q12>=0),1,0) -> 0 | U12: Payback descontado (meses) | V12: =IFERROR(INDEX(A6:A66,MATCH(1,S6:S66,0)),"No se recupera") -> 15
A13: 7 | B13: =IF(A13=0,0,IF(A13<=Supuestos!$C$24,Supuestos!$C$22,IF(A13>=Supuestos!$E$8,$V$7,Supuestos!$C$22+($V$7-Supuestos!$C$22)*(A13-Supuestos!$C$24)/(Supuestos!$E$8-Supuestos!$C$24)))) -> 62.713333 | C13: =B13*Supuestos!$E$6 -> 627.13333 | D13: =C13*Supuestos!$C$42 -> 2717.5778 | E13: =IF(A13=0,0,MAX(Supuestos!$C$23,ROUNDUP(C13/Supuestos!$C$18,0))) -> 21 | F13: =MAX(0,E13-IF(A12=0,Supuestos!$C$23,E12))+Supuestos!$C$19*E13 -> 15.63 | G13: =IF(A13=0,0,MAX(1,ROUNDUP(B13/Supuestos!$C$21,0))) -> 1 | H13: =D13*(Supuestos!$C$14+Supuestos!$E$7) -> 271757.78 | I13: =D13*Supuestos!$C$43 -> 202459.54 | J13: =IF(A13=0,0,Supuestos!$C$44+G13*Supuestos!$C$26) -> 73000 | K13: =F13*Supuestos!$C$20 -> 54705 | L13: =IF(A13=0,Supuestos!$C$45,0) -> 0 | M13: =IF(A13=0,-L13,H13-I13-J13-K13) -> -58406.767 | N13: =N12+M13 -> -626736.77 | O13: =1/(1+Supuestos!$C$46)^A13 -> 0.94591969 | P13: =M13*O13 -> -55248.111 | Q13: =Q12+P13 -> -614223.43 | R13: =IF(AND(A13>0,N13>=0),1,0) -> 0 | S13: =IF(AND(A13>0,Q13>=0),1,0) -> 0 | U13: Costos fijos en estado estable | V13: =J66 -> 145900
A14: 8 | B14: =IF(A14=0,0,IF(A14<=Supuestos!$C$24,Supuestos!$C$22,IF(A14>=Supuestos!$E$8,$V$7,Supuestos!$C$22+($V$7-Supuestos!$C$22)*(A14-Supuestos!$C$24)/(Supuestos!$E$8-Supuestos!$C$24)))) -> 110.42667 | C14: =B14*Supuestos!$E$6 -> 1104.2667 | D14: =C14*Supuestos!$C$42 -> 4785.1556 | E14: =IF(A14=0,0,MAX(Supuestos!$C$23,ROUNDUP(C14/Supuestos!$C$18,0))) -> 37 | F14: =MAX(0,E14-IF(A13=0,Supuestos!$C$23,E13))+Supuestos!$C$19*E14 -> 17.11 | G14: =IF(A14=0,0,MAX(1,ROUNDUP(B14/Supuestos!$C$21,0))) -> 2 | H14: =D14*(Supuestos!$C$14+Supuestos!$E$7) -> 478515.56 | I14: =D14*Supuestos!$C$43 -> 356494.09 | J14: =IF(A14=0,0,Supuestos!$C$44+G14*Supuestos!$C$26) -> 97300 | K14: =F14*Supuestos!$C$20 -> 59885 | L14: =IF(A14=0,Supuestos!$C$45,0) -> 0 | M14: =IF(A14=0,-L14,H14-I14-J14-K14) -> -35163.533 | N14: =N13+M14 -> -661900.3 | O14: =1/(1+Supuestos!$C$46)^A14 -> 0.93843647 | P14: =M14*O14 -> -32998.742 | Q14: =Q13+P14 -> -647222.17 | R14: =IF(AND(A14>0,N14>=0),1,0) -> 0 | S14: =IF(AND(A14>0,Q14>=0),1,0) -> 0 | U14: Punto de equilibrio (horas al mes) | V14: =IF(V6>0,V13/V6,"No existe") -> 5721.5686
A15: 9 | B15: =IF(A15=0,0,IF(A15<=Supuestos!$C$24,Supuestos!$C$22,IF(A15>=Supuestos!$E$8,$V$7,Supuestos!$C$22+($V$7-Supuestos!$C$22)*(A15-Supuestos!$C$24)/(Supuestos!$E$8-Supuestos!$C$24)))) -> 158.14 | C15: =B15*Supuestos!$E$6 -> 1581.4 | D15: =C15*Supuestos!$C$42 -> 6852.7333 | E15: =IF(A15=0,0,MAX(Supuestos!$C$23,ROUNDUP(C15/Supuestos!$C$18,0))) -> 53 | F15: =MAX(0,E15-IF(A14=0,Supuestos!$C$23,E14))+Supuestos!$C$19*E15 -> 17.59 | G15: =IF(A15=0,0,MAX(1,ROUNDUP(B15/Supuestos!$C$21,0))) -> 2 | H15: =D15*(Supuestos!$C$14+Supuestos!$E$7) -> 685273.33 | I15: =D15*Supuestos!$C$43 -> 510528.63 | J15: =IF(A15=0,0,Supuestos!$C$44+G15*Supuestos!$C$26) -> 97300 | K15: =F15*Supuestos!$C$20 -> 61565 | L15: =IF(A15=0,Supuestos!$C$45,0) -> 0 | M15: =IF(A15=0,-L15,H15-I15-J15-K15) -> 15879.7 | N15: =N14+M15 -> -646020.6 | O15: =1/(1+Supuestos!$C$46)^A15 -> 0.93101244 | P15: =M15*O15 -> 14784.198 | Q15: =Q14+P15 -> -632437.98 | R15: =IF(AND(A15>0,N15>=0),1,0) -> 0 | S15: =IF(AND(A15>0,Q15>=0),1,0) -> 0 | U15: Punto de equilibrio (familias) | V15: =IF(V6>0,V14/Supuestos!$C$42/Supuestos!$E$6,"No existe") -> 132.0362
A16: 10 | B16: =IF(A16=0,0,IF(A16<=Supuestos!$C$24,Supuestos!$C$22,IF(A16>=Supuestos!$E$8,$V$7,Supuestos!$C$22+($V$7-Supuestos!$C$22)*(A16-Supuestos!$C$24)/(Supuestos!$E$8-Supuestos!$C$24)))) -> 205.85333 | C16: =B16*Supuestos!$E$6 -> 2058.5333 | D16: =C16*Supuestos!$C$42 -> 8920.3111 | E16: =IF(A16=0,0,MAX(Supuestos!$C$23,ROUNDUP(C16/Supuestos!$C$18,0))) -> 69 | F16: =MAX(0,E16-IF(A15=0,Supuestos!$C$23,E15))+Supuestos!$C$19*E16 -> 18.07 | G16: =IF(A16=0,0,MAX(1,ROUNDUP(B16/Supuestos!$C$21,0))) -> 3 | H16: =D16*(Supuestos!$C$14+Supuestos!$E$7) -> 892031.11 | I16: =D16*Supuestos!$C$43 -> 664563.18 | J16: =IF(A16=0,0,Supuestos!$C$44+G16*Supuestos!$C$26) -> 121600 | K16: =F16*Supuestos!$C$20 -> 63245 | L16: =IF(A16=0,Supuestos!$C$45,0) -> 0 | M16: =IF(A16=0,-L16,H16-I16-J16-K16) -> 42622.933 | N16: =N15+M16 -> -603397.67 | O16: =1/(1+Supuestos!$C$46)^A16 -> 0.92364715 | P16: =M16*O16 -> 39368.551 | Q16: =Q15+P16 -> -593069.42 | R16: =IF(AND(A16>0,N16>=0),1,0) -> 0 | S16: =IF(AND(A16>0,Q16>=0),1,0) -> 0 | U16: Utilidad neta acumulada (60 meses) | V16: =N66 -> 8054029.1
A17: 11 | B17: =IF(A17=0,0,IF(A17<=Supuestos!$C$24,Supuestos!$C$22,IF(A17>=Supuestos!$E$8,$V$7,Supuestos!$C$22+($V$7-Supuestos!$C$22)*(A17-Supuestos!$C$24)/(Supuestos!$E$8-Supuestos!$C$24)))) -> 253.56667 | C17: =B17*Supuestos!$E$6 -> 2535.6667 | D17: =C17*Supuestos!$C$42 -> 10987.889 | E17: =IF(A17=0,0,MAX(Supuestos!$C$23,ROUNDUP(C17/Supuestos!$C$18,0))) -> 85 | F17: =MAX(0,E17-IF(A16=0,Supuestos!$C$23,E16))+Supuestos!$C$19*E17 -> 18.55 | G17: =IF(A17=0,0,MAX(1,ROUNDUP(B17/Supuestos!$C$21,0))) -> 4 | H17: =D17*(Supuestos!$C$14+Supuestos!$E$7) -> 1098788.9 | I17: =D17*Supuestos!$C$43 -> 818597.72 | J17: =IF(A17=0,0,Supuestos!$C$44+G17*Supuestos!$C$26) -> 145900 | K17: =F17*Supuestos!$C$20 -> 64925 | L17: =IF(A17=0,Supuestos!$C$45,0) -> 0 | M17: =IF(A17=0,-L17,H17-I17-J17-K17) -> 69366.167 | N17: =N16+M17 -> -534031.5 | O17: =1/(1+Supuestos!$C$46)^A17 -> 0.91634013 | P17: =M17*O17 -> 63563.002 | Q17: =Q16+P17 -> -529506.42 | R17: =IF(AND(A17>0,N17>=0),1,0) -> 0 | S17: =IF(AND(A17>0,Q17>=0),1,0) -> 0 | U17: Inversión inicial | V17: =L6 -> 226000
A18: 12 | B18: =IF(A18=0,0,IF(A18<=Supuestos!$C$24,Supuestos!$C$22,IF(A18>=Supuestos!$E$8,$V$7,Supuestos!$C$22+($V$7-Supuestos!$C$22)*(A18-Supuestos!$C$24)/(Supuestos!$E$8-Supuestos!$C$24)))) -> 301.28 | C18: =B18*Supuestos!$E$6 -> 3012.8 | D18: =C18*Supuestos!$C$42 -> 13055.467 | E18: =IF(A18=0,0,MAX(Supuestos!$C$23,ROUNDUP(C18/Supuestos!$C$18,0))) -> 101 | F18: =MAX(0,E18-IF(A17=0,Supuestos!$C$23,E17))+Supuestos!$C$19*E18 -> 19.03 | G18: =IF(A18=0,0,MAX(1,ROUNDUP(B18/Supuestos!$C$21,0))) -> 4 | H18: =D18*(Supuestos!$C$14+Supuestos!$E$7) -> 1305546.7 | I18: =D18*Supuestos!$C$43 -> 972632.27 | J18: =IF(A18=0,0,Supuestos!$C$44+G18*Supuestos!$C$26) -> 145900 | K18: =F18*Supuestos!$C$20 -> 66605 | L18: =IF(A18=0,Supuestos!$C$45,0) -> 0 | M18: =IF(A18=0,-L18,H18-I18-J18-K18) -> 120409.4 | N18: =N17+M18 -> -413622.1 | O18: =1/(1+Supuestos!$C$46)^A18 -> 0.90909091 | P18: =M18*O18 -> 109463.09 | Q18: =Q17+P18 -> -420043.33 | R18: =IF(AND(A18>0,N18>=0),1,0) -> 0 | S18: =IF(AND(A18>0,Q18>=0),1,0) -> 0 | U18: Capital de operación (3 meses) | V18: =3*(J7+I7) -> 364275
A19: 13 | B19: =IF(A19=0,0,IF(A19<=Supuestos!$C$24,Supuestos!$C$22,IF(A19>=Supuestos!$E$8,$V$7,Supuestos!$C$22+($V$7-Supuestos!$C$22)*(A19-Supuestos!$C$24)/(Supuestos!$E$8-Supuestos!$C$24)))) -> 301.28 | C19: =B19*Supuestos!$E$6 -> 3012.8 | D19: =C19*Supuestos!$C$42 -> 13055.467 | E19: =IF(A19=0,0,MAX(Supuestos!$C$23,ROUNDUP(C19/Supuestos!$C$18,0))) -> 101 | F19: =MAX(0,E19-IF(A18=0,Supuestos!$C$23,E18))+Supuestos!$C$19*E19 -> 3.03 | G19: =IF(A19=0,0,MAX(1,ROUNDUP(B19/Supuestos!$C$21,0))) -> 4 | H19: =D19*(Supuestos!$C$14+Supuestos!$E$7) -> 1305546.7 | I19: =D19*Supuestos!$C$43 -> 972632.27 | J19: =IF(A19=0,0,Supuestos!$C$44+G19*Supuestos!$C$26) -> 145900 | K19: =F19*Supuestos!$C$20 -> 10605 | L19: =IF(A19=0,Supuestos!$C$45,0) -> 0 | M19: =IF(A19=0,-L19,H19-I19-J19-K19) -> 176409.4 | N19: =N18+M19 -> -237212.7 | O19: =1/(1+Supuestos!$C$46)^A19 -> 0.90189904 | P19: =M19*O19 -> 159103.47 | Q19: =Q18+P19 -> -260939.86 | R19: =IF(AND(A19>0,N19>=0),1,0) -> 0 | S19: =IF(AND(A19>0,Q19>=0),1,0) -> 0 | U19: Colchón para imprevistos | V19: =Supuestos!$C$36*(V17+V18) -> 59027.5
A20: 14 | B20: =IF(A20=0,0,IF(A20<=Supuestos!$C$24,Supuestos!$C$22,IF(A20>=Supuestos!$E$8,$V$7,Supuestos!$C$22+($V$7-Supuestos!$C$22)*(A20-Supuestos!$C$24)/(Supuestos!$E$8-Supuestos!$C$24)))) -> 301.28 | C20: =B20*Supuestos!$E$6 -> 3012.8 | D20: =C20*Supuestos!$C$42 -> 13055.467 | E20: =IF(A20=0,0,MAX(Supuestos!$C$23,ROUNDUP(C20/Supuestos!$C$18,0))) -> 101 | F20: =MAX(0,E20-IF(A19=0,Supuestos!$C$23,E19))+Supuestos!$C$19*E20 -> 3.03 | G20: =IF(A20=0,0,MAX(1,ROUNDUP(B20/Supuestos!$C$21,0))) -> 4 | H20: =D20*(Supuestos!$C$14+Supuestos!$E$7) -> 1305546.7 | I20: =D20*Supuestos!$C$43 -> 972632.27 | J20: =IF(A20=0,0,Supuestos!$C$44+G20*Supuestos!$C$26) -> 145900 | K20: =F20*Supuestos!$C$20 -> 10605 | L20: =IF(A20=0,Supuestos!$C$45,0) -> 0 | M20: =IF(A20=0,-L20,H20-I20-J20-K20) -> 176409.4 | N20: =N19+M20 -> -60803.3 | O20: =1/(1+Supuestos!$C$46)^A20 -> 0.89476407 | P20: =M20*O20 -> 157844.79 | Q20: =Q19+P20 -> -103095.07 | R20: =IF(AND(A20>0,N20>=0),1,0) -> 0 | S20: =IF(AND(A20>0,Q20>=0),1,0) -> 0 | U20: Requerimiento total de capital | V20: =V17+V18+V19 -> 649302.5
A21: 15 | B21: =IF(A21=0,0,IF(A21<=Supuestos!$C$24,Supuestos!$C$22,IF(A21>=Supuestos!$E$8,$V$7,Supuestos!$C$22+($V$7-Supuestos!$C$22)*(A21-Supuestos!$C$24)/(Supuestos!$E$8-Supuestos!$C$24)))) -> 301.28 | C21: =B21*Supuestos!$E$6 -> 3012.8 | D21: =C21*Supuestos!$C$42 -> 13055.467 | E21: =IF(A21=0,0,MAX(Supuestos!$C$23,ROUNDUP(C21/Supuestos!$C$18,0))) -> 101 | F21: =MAX(0,E21-IF(A20=0,Supuestos!$C$23,E20))+Supuestos!$C$19*E21 -> 3.03 | G21: =IF(A21=0,0,MAX(1,ROUNDUP(B21/Supuestos!$C$21,0))) -> 4 | H21: =D21*(Supuestos!$C$14+Supuestos!$E$7) -> 1305546.7 | I21: =D21*Supuestos!$C$43 -> 972632.27 | J21: =IF(A21=0,0,Supuestos!$C$44+G21*Supuestos!$C$26) -> 145900 | K21: =F21*Supuestos!$C$20 -> 10605 | L21: =IF(A21=0,Supuestos!$C$45,0) -> 0 | M21: =IF(A21=0,-L21,H21-I21-J21-K21) -> 176409.4 | N21: =N20+M21 -> 115606.1 | O21: =1/(1+Supuestos!$C$46)^A21 -> 0.88768554 | P21: =M21*O21 -> 156596.07 | Q21: =Q20+P21 -> 53501.001 | R21: =IF(AND(A21>0,N21>=0),1,0) -> 1 | S21: =IF(AND(A21>0,Q21>=0),1,0) -> 1 | U21: Déficit acumulado máximo | V21: =-MIN(0,MIN(N6:N66)) -> 661900.3
A22: 16 | B22: =IF(A22=0,0,IF(A22<=Supuestos!$C$24,Supuestos!$C$22,IF(A22>=Supuestos!$E$8,$V$7,Supuestos!$C$22+($V$7-Supuestos!$C$22)*(A22-Supuestos!$C$24)/(Supuestos!$E$8-Supuestos!$C$24)))) -> 301.28 | C22: =B22*Supuestos!$E$6 -> 3012.8 | D22: =C22*Supuestos!$C$42 -> 13055.467 | E22: =IF(A22=0,0,MAX(Supuestos!$C$23,ROUNDUP(C22/Supuestos!$C$18,0))) -> 101 | F22: =MAX(0,E22-IF(A21=0,Supuestos!$C$23,E21))+Supuestos!$C$19*E22 -> 3.03 | G22: =IF(A22=0,0,MAX(1,ROUNDUP(B22/Supuestos!$C$21,0))) -> 4 | H22: =D22*(Supuestos!$C$14+Supuestos!$E$7) -> 1305546.7 | I22: =D22*Supuestos!$C$43 -> 972632.27 | J22: =IF(A22=0,0,Supuestos!$C$44+G22*Supuestos!$C$26) -> 145900 | K22: =F22*Supuestos!$C$20 -> 10605 | L22: =IF(A22=0,Supuestos!$C$45,0) -> 0 | M22: =IF(A22=0,-L22,H22-I22-J22-K22) -> 176409.4 | N22: =N21+M22 -> 292015.5 | O22: =1/(1+Supuestos!$C$46)^A22 -> 0.88066301 | P22: =M22*O22 -> 155357.23 | Q22: =Q21+P22 -> 208858.23 | R22: =IF(AND(A22>0,N22>=0),1,0) -> 1 | S22: =IF(AND(A22>0,Q22>=0),1,0) -> 1 | U22: Familias en estado estable | V22: =B66 -> 301.28
A23: 17 | B23: =IF(A23=0,0,IF(A23<=Supuestos!$C$24,Supuestos!$C$22,IF(A23>=Supuestos!$E$8,$V$7,Supuestos!$C$22+($V$7-Supuestos!$C$22)*(A23-Supuestos!$C$24)/(Supuestos!$E$8-Supuestos!$C$24)))) -> 301.28 | C23: =B23*Supuestos!$E$6 -> 3012.8 | D23: =C23*Supuestos!$C$42 -> 13055.467 | E23: =IF(A23=0,0,MAX(Supuestos!$C$23,ROUNDUP(C23/Supuestos!$C$18,0))) -> 101 | F23: =MAX(0,E23-IF(A22=0,Supuestos!$C$23,E22))+Supuestos!$C$19*E23 -> 3.03 | G23: =IF(A23=0,0,MAX(1,ROUNDUP(B23/Supuestos!$C$21,0))) -> 4 | H23: =D23*(Supuestos!$C$14+Supuestos!$E$7) -> 1305546.7 | I23: =D23*Supuestos!$C$43 -> 972632.27 | J23: =IF(A23=0,0,Supuestos!$C$44+G23*Supuestos!$C$26) -> 145900 | K23: =F23*Supuestos!$C$20 -> 10605 | L23: =IF(A23=0,Supuestos!$C$45,0) -> 0 | M23: =IF(A23=0,-L23,H23-I23-J23-K23) -> 176409.4 | N23: =N22+M23 -> 468424.9 | O23: =1/(1+Supuestos!$C$46)^A23 -> 0.87369603 | P23: =M23*O23 -> 154128.19 | Q23: =Q22+P23 -> 362986.43 | R23: =IF(AND(A23>0,N23>=0),1,0) -> 1 | S23: =IF(AND(A23>0,Q23>=0),1,0) -> 1 | U23: Horas de cuidado al mes en estado estable | V23: =D66 -> 13055.467
A24: 18 | B24: =IF(A24=0,0,IF(A24<=Supuestos!$C$24,Supuestos!$C$22,IF(A24>=Supuestos!$E$8,$V$7,Supuestos!$C$22+($V$7-Supuestos!$C$22)*(A24-Supuestos!$C$24)/(Supuestos!$E$8-Supuestos!$C$24)))) -> 301.28 | C24: =B24*Supuestos!$E$6 -> 3012.8 | D24: =C24*Supuestos!$C$42 -> 13055.467 | E24: =IF(A24=0,0,MAX(Supuestos!$C$23,ROUNDUP(C24/Supuestos!$C$18,0))) -> 101 | F24: =MAX(0,E24-IF(A23=0,Supuestos!$C$23,E23))+Supuestos!$C$19*E24 -> 3.03 | G24: =IF(A24=0,0,MAX(1,ROUNDUP(B24/Supuestos!$C$21,0))) -> 4 | H24: =D24*(Supuestos!$C$14+Supuestos!$E$7) -> 1305546.7 | I24: =D24*Supuestos!$C$43 -> 972632.27 | J24: =IF(A24=0,0,Supuestos!$C$44+G24*Supuestos!$C$26) -> 145900 | K24: =F24*Supuestos!$C$20 -> 10605 | L24: =IF(A24=0,Supuestos!$C$45,0) -> 0 | M24: =IF(A24=0,-L24,H24-I24-J24-K24) -> 176409.4 | N24: =N23+M24 -> 644834.3 | O24: =1/(1+Supuestos!$C$46)^A24 -> 0.86678417 | P24: =M24*O24 -> 152908.88 | Q24: =Q23+P24 -> 515895.3 | R24: =IF(AND(A24>0,N24>=0),1,0) -> 1 | S24: =IF(AND(A24>0,Q24>=0),1,0) -> 1 | U24: Cuidadoras empleadas en estado estable | V24: =E66 -> 101
A25: 19 | B25: =IF(A25=0,0,IF(A25<=Supuestos!$C$24,Supuestos!$C$22,IF(A25>=Supuestos!$E$8,$V$7,Supuestos!$C$22+($V$7-Supuestos!$C$22)*(A25-Supuestos!$C$24)/(Supuestos!$E$8-Supuestos!$C$24)))) -> 301.28 | C25: =B25*Supuestos!$E$6 -> 3012.8 | D25: =C25*Supuestos!$C$42 -> 13055.467 | E25: =IF(A25=0,0,MAX(Supuestos!$C$23,ROUNDUP(C25/Supuestos!$C$18,0))) -> 101 | F25: =MAX(0,E25-IF(A24=0,Supuestos!$C$23,E24))+Supuestos!$C$19*E25 -> 3.03 | G25: =IF(A25=0,0,MAX(1,ROUNDUP(B25/Supuestos!$C$21,0))) -> 4 | H25: =D25*(Supuestos!$C$14+Supuestos!$E$7) -> 1305546.7 | I25: =D25*Supuestos!$C$43 -> 972632.27 | J25: =IF(A25=0,0,Supuestos!$C$44+G25*Supuestos!$C$26) -> 145900 | K25: =F25*Supuestos!$C$20 -> 10605 | L25: =IF(A25=0,Supuestos!$C$45,0) -> 0 | M25: =IF(A25=0,-L25,H25-I25-J25-K25) -> 176409.4 | N25: =N24+M25 -> 821243.7 | O25: =1/(1+Supuestos!$C$46)^A25 -> 0.85992699 | P25: =M25*O25 -> 151699.2 | Q25: =Q24+P25 -> 667594.51 | R25: =IF(AND(A25>0,N25>=0),1,0) -> 1 | S25: =IF(AND(A25>0,Q25>=0),1,0) -> 1 | U25: Familias en el mes de revisión | V25: =INDEX(B6:B66,(Supuestos!$C$37+1)) -> 301.28
A26: 20 | B26: =IF(A26=0,0,IF(A26<=Supuestos!$C$24,Supuestos!$C$22,IF(A26>=Supuestos!$E$8,$V$7,Supuestos!$C$22+($V$7-Supuestos!$C$22)*(A26-Supuestos!$C$24)/(Supuestos!$E$8-Supuestos!$C$24)))) -> 301.28 | C26: =B26*Supuestos!$E$6 -> 3012.8 | D26: =C26*Supuestos!$C$42 -> 13055.467 | E26: =IF(A26=0,0,MAX(Supuestos!$C$23,ROUNDUP(C26/Supuestos!$C$18,0))) -> 101 | F26: =MAX(0,E26-IF(A25=0,Supuestos!$C$23,E25))+Supuestos!$C$19*E26 -> 3.03 | G26: =IF(A26=0,0,MAX(1,ROUNDUP(B26/Supuestos!$C$21,0))) -> 4 | H26: =D26*(Supuestos!$C$14+Supuestos!$E$7) -> 1305546.7 | I26: =D26*Supuestos!$C$43 -> 972632.27 | J26: =IF(A26=0,0,Supuestos!$C$44+G26*Supuestos!$C$26) -> 145900 | K26: =F26*Supuestos!$C$20 -> 10605 | L26: =IF(A26=0,Supuestos!$C$45,0) -> 0 | M26: =IF(A26=0,-L26,H26-I26-J26-K26) -> 176409.4 | N26: =N25+M26 -> 997653.1 | O26: =1/(1+Supuestos!$C$46)^A26 -> 0.85312406 | P26: =M26*O26 -> 150499.1 | Q26: =Q25+P26 -> 818093.61 | R26: =IF(AND(A26>0,N26>=0),1,0) -> 1 | S26: =IF(AND(A26>0,Q26>=0),1,0) -> 1 | U26: ¿Se cierra en la revisión? | V26: =IF(ISNUMBER(V15),IF(V25<Supuestos!$C$38*V15,"Sí","No"),"Sí") -> No
A27: 21 | B27: =IF(A27=0,0,IF(A27<=Supuestos!$C$24,Supuestos!$C$22,IF(A27>=Supuestos!$E$8,$V$7,Supuestos!$C$22+($V$7-Supuestos!$C$22)*(A27-Supuestos!$C$24)/(Supuestos!$E$8-Supuestos!$C$24)))) -> 301.28 | C27: =B27*Supuestos!$E$6 -> 3012.8 | D27: =C27*Supuestos!$C$42 -> 13055.467 | E27: =IF(A27=0,0,MAX(Supuestos!$C$23,ROUNDUP(C27/Supuestos!$C$18,0))) -> 101 | F27: =MAX(0,E27-IF(A26=0,Supuestos!$C$23,E26))+Supuestos!$C$19*E27 -> 3.03 | G27: =IF(A27=0,0,MAX(1,ROUNDUP(B27/Supuestos!$C$21,0))) -> 4 | H27: =D27*(Supuestos!$C$14+Supuestos!$E$7) -> 1305546.7 | I27: =D27*Supuestos!$C$43 -> 972632.27 | J27: =IF(A27=0,0,Supuestos!$C$44+G27*Supuestos!$C$26) -> 145900 | K27: =F27*Supuestos!$C$20 -> 10605 | L27: =IF(A27=0,Supuestos!$C$45,0) -> 0 | M27: =IF(A27=0,-L27,H27-I27-J27-K27) -> 176409.4 | N27: =N26+M27 -> 1174062.5 | O27: =1/(1+Supuestos!$C$46)^A27 -> 0.84637495 | P27: =M27*O27 -> 149308.5 | Q27: =Q26+P27 -> 967402.11 | R27: =IF(AND(A27>0,N27>=0),1,0) -> 1 | S27: =IF(AND(A27>0,Q27>=0),1,0) -> 1 | U27: Costo de cierre | V27: =Supuestos!$C$39*INDEX(J6:J66,(Supuestos!$C$37+1)) -> 291800
A28: 22 | B28: =IF(A28=0,0,IF(A28<=Supuestos!$C$24,Supuestos!$C$22,IF(A28>=Supuestos!$E$8,$V$7,Supuestos!$C$22+($V$7-Supuestos!$C$22)*(A28-Supuestos!$C$24)/(Supuestos!$E$8-Supuestos!$C$24)))) -> 301.28 | C28: =B28*Supuestos!$E$6 -> 3012.8 | D28: =C28*Supuestos!$C$42 -> 13055.467 | E28: =IF(A28=0,0,MAX(Supuestos!$C$23,ROUNDUP(C28/Supuestos!$C$18,0))) -> 101 | F28: =MAX(0,E28-IF(A27=0,Supuestos!$C$23,E27))+Supuestos!$C$19*E28 -> 3.03 | G28: =IF(A28=0,0,MAX(1,ROUNDUP(B28/Supuestos!$C$21,0))) -> 4 | H28: =D28*(Supuestos!$C$14+Supuestos!$E$7) -> 1305546.7 | I28: =D28*Supuestos!$C$43 -> 972632.27 | J28: =IF(A28=0,0,Supuestos!$C$44+G28*Supuestos!$C$26) -> 145900 | K28: =F28*Supuestos!$C$20 -> 10605 | L28: =IF(A28=0,Supuestos!$C$45,0) -> 0 | M28: =IF(A28=0,-L28,H28-I28-J28-K28) -> 176409.4 | N28: =N27+M28 -> 1350471.9 | O28: =1/(1+Supuestos!$C$46)^A28 -> 0.83967923 | P28: =M28*O28 -> 148127.31 | Q28: =Q27+P28 -> 1115529.4 | R28: =IF(AND(A28>0,N28>=0),1,0) -> 1 | S28: =IF(AND(A28>0,Q28>=0),1,0) -> 1 | U28: VAN con revisión en el mes 12 | V28: =IF(V26="Sí",SUM(P6:INDEX(P6:P66,(Supuestos!$C$37+1)))-V27/(1+Supuestos!$C$46)^(Supuestos!$C$37+1),V8) -> 5955041.8
A29: 23 | B29: =IF(A29=0,0,IF(A29<=Supuestos!$C$24,Supuestos!$C$22,IF(A29>=Supuestos!$E$8,$V$7,Supuestos!$C$22+($V$7-Supuestos!$C$22)*(A29-Supuestos!$C$24)/(Supuestos!$E$8-Supuestos!$C$24)))) -> 301.28 | C29: =B29*Supuestos!$E$6 -> 3012.8 | D29: =C29*Supuestos!$C$42 -> 13055.467 | E29: =IF(A29=0,0,MAX(Supuestos!$C$23,ROUNDUP(C29/Supuestos!$C$18,0))) -> 101 | F29: =MAX(0,E29-IF(A28=0,Supuestos!$C$23,E28))+Supuestos!$C$19*E29 -> 3.03 | G29: =IF(A29=0,0,MAX(1,ROUNDUP(B29/Supuestos!$C$21,0))) -> 4 | H29: =D29*(Supuestos!$C$14+Supuestos!$E$7) -> 1305546.7 | I29: =D29*Supuestos!$C$43 -> 972632.27 | J29: =IF(A29=0,0,Supuestos!$C$44+G29*Supuestos!$C$26) -> 145900 | K29: =F29*Supuestos!$C$20 -> 10605 | L29: =IF(A29=0,Supuestos!$C$45,0) -> 0 | M29: =IF(A29=0,-L29,H29-I29-J29-K29) -> 176409.4 | N29: =N28+M29 -> 1526881.3 | O29: =1/(1+Supuestos!$C$46)^A29 -> 0.83303648 | P29: =M29*O29 -> 146955.47 | Q29: =Q28+P29 -> 1262484.9 | R29: =IF(AND(A29>0,N29>=0),1,0) -> 1 | S29: =IF(AND(A29>0,Q29>=0),1,0) -> 1 | U29: Utilidad neta con revisión | V29: =IF(V26="Sí",SUM(M6:INDEX(M6:M66,(Supuestos!$C$37+1)))-V27,V16) -> 8054029.1
A30: 24 | B30: =IF(A30=0,0,IF(A30<=Supuestos!$C$24,Supuestos!$C$22,IF(A30>=Supuestos!$E$8,$V$7,Supuestos!$C$22+($V$7-Supuestos!$C$22)*(A30-Supuestos!$C$24)/(Supuestos!$E$8-Supuestos!$C$24)))) -> 301.28 | C30: =B30*Supuestos!$E$6 -> 3012.8 | D30: =C30*Supuestos!$C$42 -> 13055.467 | E30: =IF(A30=0,0,MAX(Supuestos!$C$23,ROUNDUP(C30/Supuestos!$C$18,0))) -> 101 | F30: =MAX(0,E30-IF(A29=0,Supuestos!$C$23,E29))+Supuestos!$C$19*E30 -> 3.03 | G30: =IF(A30=0,0,MAX(1,ROUNDUP(B30/Supuestos!$C$21,0))) -> 4 | H30: =D30*(Supuestos!$C$14+Supuestos!$E$7) -> 1305546.7 | I30: =D30*Supuestos!$C$43 -> 972632.27 | J30: =IF(A30=0,0,Supuestos!$C$44+G30*Supuestos!$C$26) -> 145900 | K30: =F30*Supuestos!$C$20 -> 10605 | L30: =IF(A30=0,Supuestos!$C$45,0) -> 0 | M30: =IF(A30=0,-L30,H30-I30-J30-K30) -> 176409.4 | N30: =N29+M30 -> 1703290.7 | O30: =1/(1+Supuestos!$C$46)^A30 -> 0.82644628 | P30: =M30*O30 -> 145792.89 | Q30: =Q29+P30 -> 1408277.8 | R30: =IF(AND(A30>0,N30>=0),1,0) -> 1 | S30: =IF(AND(A30>0,Q30>=0),1,0) -> 1
A31: 25 | B31: =IF(A31=0,0,IF(A31<=Supuestos!$C$24,Supuestos!$C$22,IF(A31>=Supuestos!$E$8,$V$7,Supuestos!$C$22+($V$7-Supuestos!$C$22)*(A31-Supuestos!$C$24)/(Supuestos!$E$8-Supuestos!$C$24)))) -> 301.28 | C31: =B31*Supuestos!$E$6 -> 3012.8 | D31: =C31*Supuestos!$C$42 -> 13055.467 | E31: =IF(A31=0,0,MAX(Supuestos!$C$23,ROUNDUP(C31/Supuestos!$C$18,0))) -> 101 | F31: =MAX(0,E31-IF(A30=0,Supuestos!$C$23,E30))+Supuestos!$C$19*E31 -> 3.03 | G31: =IF(A31=0,0,MAX(1,ROUNDUP(B31/Supuestos!$C$21,0))) -> 4 | H31: =D31*(Supuestos!$C$14+Supuestos!$E$7) -> 1305546.7 | I31: =D31*Supuestos!$C$43 -> 972632.27 | J31: =IF(A31=0,0,Supuestos!$C$44+G31*Supuestos!$C$26) -> 145900 | K31: =F31*Supuestos!$C$20 -> 10605 | L31: =IF(A31=0,Supuestos!$C$45,0) -> 0 | M31: =IF(A31=0,-L31,H31-I31-J31-K31) -> 176409.4 | N31: =N30+M31 -> 1879700.1 | O31: =1/(1+Supuestos!$C$46)^A31 -> 0.81990822 | P31: =M31*O31 -> 144639.52 | Q31: =Q30+P31 -> 1552917.3 | R31: =IF(AND(A31>0,N31>=0),1,0) -> 1 | S31: =IF(AND(A31>0,Q31>=0),1,0) -> 1
A32: 26 | B32: =IF(A32=0,0,IF(A32<=Supuestos!$C$24,Supuestos!$C$22,IF(A32>=Supuestos!$E$8,$V$7,Supuestos!$C$22+($V$7-Supuestos!$C$22)*(A32-Supuestos!$C$24)/(Supuestos!$E$8-Supuestos!$C$24)))) -> 301.28 | C32: =B32*Supuestos!$E$6 -> 3012.8 | D32: =C32*Supuestos!$C$42 -> 13055.467 | E32: =IF(A32=0,0,MAX(Supuestos!$C$23,ROUNDUP(C32/Supuestos!$C$18,0))) -> 101 | F32: =MAX(0,E32-IF(A31=0,Supuestos!$C$23,E31))+Supuestos!$C$19*E32 -> 3.03 | G32: =IF(A32=0,0,MAX(1,ROUNDUP(B32/Supuestos!$C$21,0))) -> 4 | H32: =D32*(Supuestos!$C$14+Supuestos!$E$7) -> 1305546.7 | I32: =D32*Supuestos!$C$43 -> 972632.27 | J32: =IF(A32=0,0,Supuestos!$C$44+G32*Supuestos!$C$26) -> 145900 | K32: =F32*Supuestos!$C$20 -> 10605 | L32: =IF(A32=0,Supuestos!$C$45,0) -> 0 | M32: =IF(A32=0,-L32,H32-I32-J32-K32) -> 176409.4 | N32: =N31+M32 -> 2056109.5 | O32: =1/(1+Supuestos!$C$46)^A32 -> 0.81342188 | P32: =M32*O32 -> 143495.27 | Q32: =Q31+P32 -> 1696412.6 | R32: =IF(AND(A32>0,N32>=0),1,0) -> 1 | S32: =IF(AND(A32>0,Q32>=0),1,0) -> 1
A33: 27 | B33: =IF(A33=0,0,IF(A33<=Supuestos!$C$24,Supuestos!$C$22,IF(A33>=Supuestos!$E$8,$V$7,Supuestos!$C$22+($V$7-Supuestos!$C$22)*(A33-Supuestos!$C$24)/(Supuestos!$E$8-Supuestos!$C$24)))) -> 301.28 | C33: =B33*Supuestos!$E$6 -> 3012.8 | D33: =C33*Supuestos!$C$42 -> 13055.467 | E33: =IF(A33=0,0,MAX(Supuestos!$C$23,ROUNDUP(C33/Supuestos!$C$18,0))) -> 101 | F33: =MAX(0,E33-IF(A32=0,Supuestos!$C$23,E32))+Supuestos!$C$19*E33 -> 3.03 | G33: =IF(A33=0,0,MAX(1,ROUNDUP(B33/Supuestos!$C$21,0))) -> 4 | H33: =D33*(Supuestos!$C$14+Supuestos!$E$7) -> 1305546.7 | I33: =D33*Supuestos!$C$43 -> 972632.27 | J33: =IF(A33=0,0,Supuestos!$C$44+G33*Supuestos!$C$26) -> 145900 | K33: =F33*Supuestos!$C$20 -> 10605 | L33: =IF(A33=0,Supuestos!$C$45,0) -> 0 | M33: =IF(A33=0,-L33,H33-I33-J33-K33) -> 176409.4 | N33: =N32+M33 -> 2232518.9 | O33: =1/(1+Supuestos!$C$46)^A33 -> 0.80698685 | P33: =M33*O33 -> 142360.07 | Q33: =Q32+P33 -> 1838772.6 | R33: =IF(AND(A33>0,N33>=0),1,0) -> 1 | S33: =IF(AND(A33>0,Q33>=0),1,0) -> 1
A34: 28 | B34: =IF(A34=0,0,IF(A34<=Supuestos!$C$24,Supuestos!$C$22,IF(A34>=Supuestos!$E$8,$V$7,Supuestos!$C$22+($V$7-Supuestos!$C$22)*(A34-Supuestos!$C$24)/(Supuestos!$E$8-Supuestos!$C$24)))) -> 301.28 | C34: =B34*Supuestos!$E$6 -> 3012.8 | D34: =C34*Supuestos!$C$42 -> 13055.467 | E34: =IF(A34=0,0,MAX(Supuestos!$C$23,ROUNDUP(C34/Supuestos!$C$18,0))) -> 101 | F34: =MAX(0,E34-IF(A33=0,Supuestos!$C$23,E33))+Supuestos!$C$19*E34 -> 3.03 | G34: =IF(A34=0,0,MAX(1,ROUNDUP(B34/Supuestos!$C$21,0))) -> 4 | H34: =D34*(Supuestos!$C$14+Supuestos!$E$7) -> 1305546.7 | I34: =D34*Supuestos!$C$43 -> 972632.27 | J34: =IF(A34=0,0,Supuestos!$C$44+G34*Supuestos!$C$26) -> 145900 | K34: =F34*Supuestos!$C$20 -> 10605 | L34: =IF(A34=0,Supuestos!$C$45,0) -> 0 | M34: =IF(A34=0,-L34,H34-I34-J34-K34) -> 176409.4 | N34: =N33+M34 -> 2408928.3 | O34: =1/(1+Supuestos!$C$46)^A34 -> 0.80060273 | P34: =M34*O34 -> 141233.85 | Q34: =Q33+P34 -> 1980006.5 | R34: =IF(AND(A34>0,N34>=0),1,0) -> 1 | S34: =IF(AND(A34>0,Q34>=0),1,0) -> 1
A35: 29 | B35: =IF(A35=0,0,IF(A35<=Supuestos!$C$24,Supuestos!$C$22,IF(A35>=Supuestos!$E$8,$V$7,Supuestos!$C$22+($V$7-Supuestos!$C$22)*(A35-Supuestos!$C$24)/(Supuestos!$E$8-Supuestos!$C$24)))) -> 301.28 | C35: =B35*Supuestos!$E$6 -> 3012.8 | D35: =C35*Supuestos!$C$42 -> 13055.467 | E35: =IF(A35=0,0,MAX(Supuestos!$C$23,ROUNDUP(C35/Supuestos!$C$18,0))) -> 101 | F35: =MAX(0,E35-IF(A34=0,Supuestos!$C$23,E34))+Supuestos!$C$19*E35 -> 3.03 | G35: =IF(A35=0,0,MAX(1,ROUNDUP(B35/Supuestos!$C$21,0))) -> 4 | H35: =D35*(Supuestos!$C$14+Supuestos!$E$7) -> 1305546.7 | I35: =D35*Supuestos!$C$43 -> 972632.27 | J35: =IF(A35=0,0,Supuestos!$C$44+G35*Supuestos!$C$26) -> 145900 | K35: =F35*Supuestos!$C$20 -> 10605 | L35: =IF(A35=0,Supuestos!$C$45,0) -> 0 | M35: =IF(A35=0,-L35,H35-I35-J35-K35) -> 176409.4 | N35: =N34+M35 -> 2585337.7 | O35: =1/(1+Supuestos!$C$46)^A35 -> 0.79426912 | P35: =M35*O35 -> 140116.54 | Q35: =Q34+P35 -> 2120123 | R35: =IF(AND(A35>0,N35>=0),1,0) -> 1 | S35: =IF(AND(A35>0,Q35>=0),1,0) -> 1
A36: 30 | B36: =IF(A36=0,0,IF(A36<=Supuestos!$C$24,Supuestos!$C$22,IF(A36>=Supuestos!$E$8,$V$7,Supuestos!$C$22+($V$7-Supuestos!$C$22)*(A36-Supuestos!$C$24)/(Supuestos!$E$8-Supuestos!$C$24)))) -> 301.28 | C36: =B36*Supuestos!$E$6 -> 3012.8 | D36: =C36*Supuestos!$C$42 -> 13055.467 | E36: =IF(A36=0,0,MAX(Supuestos!$C$23,ROUNDUP(C36/Supuestos!$C$18,0))) -> 101 | F36: =MAX(0,E36-IF(A35=0,Supuestos!$C$23,E35))+Supuestos!$C$19*E36 -> 3.03 | G36: =IF(A36=0,0,MAX(1,ROUNDUP(B36/Supuestos!$C$21,0))) -> 4 | H36: =D36*(Supuestos!$C$14+Supuestos!$E$7) -> 1305546.7 | I36: =D36*Supuestos!$C$43 -> 972632.27 | J36: =IF(A36=0,0,Supuestos!$C$44+G36*Supuestos!$C$26) -> 145900 | K36: =F36*Supuestos!$C$20 -> 10605 | L36: =IF(A36=0,Supuestos!$C$45,0) -> 0 | M36: =IF(A36=0,-L36,H36-I36-J36-K36) -> 176409.4 | N36: =N35+M36 -> 2761747.1 | O36: =1/(1+Supuestos!$C$46)^A36 -> 0.78798561 | P36: =M36*O36 -> 139008.07 | Q36: =Q35+P36 -> 2259131.1 | R36: =IF(AND(A36>0,N36>=0),1,0) -> 1 | S36: =IF(AND(A36>0,Q36>=0),1,0) -> 1
A37: 31 | B37: =IF(A37=0,0,IF(A37<=Supuestos!$C$24,Supuestos!$C$22,IF(A37>=Supuestos!$E$8,$V$7,Supuestos!$C$22+($V$7-Supuestos!$C$22)*(A37-Supuestos!$C$24)/(Supuestos!$E$8-Supuestos!$C$24)))) -> 301.28 | C37: =B37*Supuestos!$E$6 -> 3012.8 | D37: =C37*Supuestos!$C$42 -> 13055.467 | E37: =IF(A37=0,0,MAX(Supuestos!$C$23,ROUNDUP(C37/Supuestos!$C$18,0))) -> 101 | F37: =MAX(0,E37-IF(A36=0,Supuestos!$C$23,E36))+Supuestos!$C$19*E37 -> 3.03 | G37: =IF(A37=0,0,MAX(1,ROUNDUP(B37/Supuestos!$C$21,0))) -> 4 | H37: =D37*(Supuestos!$C$14+Supuestos!$E$7) -> 1305546.7 | I37: =D37*Supuestos!$C$43 -> 972632.27 | J37: =IF(A37=0,0,Supuestos!$C$44+G37*Supuestos!$C$26) -> 145900 | K37: =F37*Supuestos!$C$20 -> 10605 | L37: =IF(A37=0,Supuestos!$C$45,0) -> 0 | M37: =IF(A37=0,-L37,H37-I37-J37-K37) -> 176409.4 | N37: =N36+M37 -> 2938156.5 | O37: =1/(1+Supuestos!$C$46)^A37 -> 0.78175181 | P37: =M37*O37 -> 137908.37 | Q37: =Q36+P37 -> 2397039.4 | R37: =IF(AND(A37>0,N37>=0),1,0) -> 1 | S37: =IF(AND(A37>0,Q37>=0),1,0) -> 1
A38: 32 | B38: =IF(A38=0,0,IF(A38<=Supuestos!$C$24,Supuestos!$C$22,IF(A38>=Supuestos!$E$8,$V$7,Supuestos!$C$22+($V$7-Supuestos!$C$22)*(A38-Supuestos!$C$24)/(Supuestos!$E$8-Supuestos!$C$24)))) -> 301.28 | C38: =B38*Supuestos!$E$6 -> 3012.8 | D38: =C38*Supuestos!$C$42 -> 13055.467 | E38: =IF(A38=0,0,MAX(Supuestos!$C$23,ROUNDUP(C38/Supuestos!$C$18,0))) -> 101 | F38: =MAX(0,E38-IF(A37=0,Supuestos!$C$23,E37))+Supuestos!$C$19*E38 -> 3.03 | G38: =IF(A38=0,0,MAX(1,ROUNDUP(B38/Supuestos!$C$21,0))) -> 4 | H38: =D38*(Supuestos!$C$14+Supuestos!$E$7) -> 1305546.7 | I38: =D38*Supuestos!$C$43 -> 972632.27 | J38: =IF(A38=0,0,Supuestos!$C$44+G38*Supuestos!$C$26) -> 145900 | K38: =F38*Supuestos!$C$20 -> 10605 | L38: =IF(A38=0,Supuestos!$C$45,0) -> 0 | M38: =IF(A38=0,-L38,H38-I38-J38-K38) -> 176409.4 | N38: =N37+M38 -> 3114565.9 | O38: =1/(1+Supuestos!$C$46)^A38 -> 0.77556733 | P38: =M38*O38 -> 136817.37 | Q38: =Q37+P38 -> 2533856.8 | R38: =IF(AND(A38>0,N38>=0),1,0) -> 1 | S38: =IF(AND(A38>0,Q38>=0),1,0) -> 1
A39: 33 | B39: =IF(A39=0,0,IF(A39<=Supuestos!$C$24,Supuestos!$C$22,IF(A39>=Supuestos!$E$8,$V$7,Supuestos!$C$22+($V$7-Supuestos!$C$22)*(A39-Supuestos!$C$24)/(Supuestos!$E$8-Supuestos!$C$24)))) -> 301.28 | C39: =B39*Supuestos!$E$6 -> 3012.8 | D39: =C39*Supuestos!$C$42 -> 13055.467 | E39: =IF(A39=0,0,MAX(Supuestos!$C$23,ROUNDUP(C39/Supuestos!$C$18,0))) -> 101 | F39: =MAX(0,E39-IF(A38=0,Supuestos!$C$23,E38))+Supuestos!$C$19*E39 -> 3.03 | G39: =IF(A39=0,0,MAX(1,ROUNDUP(B39/Supuestos!$C$21,0))) -> 4 | H39: =D39*(Supuestos!$C$14+Supuestos!$E$7) -> 1305546.7 | I39: =D39*Supuestos!$C$43 -> 972632.27 | J39: =IF(A39=0,0,Supuestos!$C$44+G39*Supuestos!$C$26) -> 145900 | K39: =F39*Supuestos!$C$20 -> 10605 | L39: =IF(A39=0,Supuestos!$C$45,0) -> 0 | M39: =IF(A39=0,-L39,H39-I39-J39-K39) -> 176409.4 | N39: =N38+M39 -> 3290975.3 | O39: =1/(1+Supuestos!$C$46)^A39 -> 0.76943177 | P39: =M39*O39 -> 135735 | Q39: =Q38+P39 -> 2669591.8 | R39: =IF(AND(A39>0,N39>=0),1,0) -> 1 | S39: =IF(AND(A39>0,Q39>=0),1,0) -> 1
A40: 34 | B40: =IF(A40=0,0,IF(A40<=Supuestos!$C$24,Supuestos!$C$22,IF(A40>=Supuestos!$E$8,$V$7,Supuestos!$C$22+($V$7-Supuestos!$C$22)*(A40-Supuestos!$C$24)/(Supuestos!$E$8-Supuestos!$C$24)))) -> 301.28 | C40: =B40*Supuestos!$E$6 -> 3012.8 | D40: =C40*Supuestos!$C$42 -> 13055.467 | E40: =IF(A40=0,0,MAX(Supuestos!$C$23,ROUNDUP(C40/Supuestos!$C$18,0))) -> 101 | F40: =MAX(0,E40-IF(A39=0,Supuestos!$C$23,E39))+Supuestos!$C$19*E40 -> 3.03 | G40: =IF(A40=0,0,MAX(1,ROUNDUP(B40/Supuestos!$C$21,0))) -> 4 | H40: =D40*(Supuestos!$C$14+Supuestos!$E$7) -> 1305546.7 | I40: =D40*Supuestos!$C$43 -> 972632.27 | J40: =IF(A40=0,0,Supuestos!$C$44+G40*Supuestos!$C$26) -> 145900 | K40: =F40*Supuestos!$C$20 -> 10605 | L40: =IF(A40=0,Supuestos!$C$45,0) -> 0 | M40: =IF(A40=0,-L40,H40-I40-J40-K40) -> 176409.4 | N40: =N39+M40 -> 3467384.7 | O40: =1/(1+Supuestos!$C$46)^A40 -> 0.76334475 | P40: =M40*O40 -> 134661.19 | Q40: =Q39+P40 -> 2804253 | R40: =IF(AND(A40>0,N40>=0),1,0) -> 1 | S40: =IF(AND(A40>0,Q40>=0),1,0) -> 1
A41: 35 | B41: =IF(A41=0,0,IF(A41<=Supuestos!$C$24,Supuestos!$C$22,IF(A41>=Supuestos!$E$8,$V$7,Supuestos!$C$22+($V$7-Supuestos!$C$22)*(A41-Supuestos!$C$24)/(Supuestos!$E$8-Supuestos!$C$24)))) -> 301.28 | C41: =B41*Supuestos!$E$6 -> 3012.8 | D41: =C41*Supuestos!$C$42 -> 13055.467 | E41: =IF(A41=0,0,MAX(Supuestos!$C$23,ROUNDUP(C41/Supuestos!$C$18,0))) -> 101 | F41: =MAX(0,E41-IF(A40=0,Supuestos!$C$23,E40))+Supuestos!$C$19*E41 -> 3.03 | G41: =IF(A41=0,0,MAX(1,ROUNDUP(B41/Supuestos!$C$21,0))) -> 4 | H41: =D41*(Supuestos!$C$14+Supuestos!$E$7) -> 1305546.7 | I41: =D41*Supuestos!$C$43 -> 972632.27 | J41: =IF(A41=0,0,Supuestos!$C$44+G41*Supuestos!$C$26) -> 145900 | K41: =F41*Supuestos!$C$20 -> 10605 | L41: =IF(A41=0,Supuestos!$C$45,0) -> 0 | M41: =IF(A41=0,-L41,H41-I41-J41-K41) -> 176409.4 | N41: =N40+M41 -> 3643794.1 | O41: =1/(1+Supuestos!$C$46)^A41 -> 0.75730589 | P41: =M41*O41 -> 133595.88 | Q41: =Q40+P41 -> 2937848.9 | R41: =IF(AND(A41>0,N41>=0),1,0) -> 1 | S41: =IF(AND(A41>0,Q41>=0),1,0) -> 1
... A66: 60 | B66: =IF(A66=0,0,IF(A66<=Supuestos!$C$24,Supuestos!$C$22,IF(A66>=Supuestos!$E$8,$V$7,Supuestos!$C$22+($V$7-Supuestos!$C$22)*(A66-Supuestos!$C$24)/(Supuestos!$E$8-Supuestos!$C$24)))) -> 301.28 | C66: =B66*Supuestos!$E$6 -> 3012.8 | D66: =C66*Supuestos!$C$42 -> 13055.467 | E66: =IF(A66=0,0,MAX(Supuestos!$C$23,ROUNDUP(C66/Supuestos!$C$18,0))) -> 101 | F66: =MAX(0,E66-IF(A65=0,Supuestos!$C$23,E65))+Supuestos!$C$19*E66 -> 3.03 | G66: =IF(A66=0,0,MAX(1,ROUNDUP(B66/Supuestos!$C$21,0))) -> 4 | H66: =D66*(Supuestos!$C$14+Supuestos!$E$7) -> 1305546.7 | I66: =D66*Supuestos!$C$43 -> 972632.27 | J66: =IF(A66=0,0,Supuestos!$C$44+G66*Supuestos!$C$26) -> 145900 | K66: =F66*Supuestos!$C$20 -> 10605 | L66: =IF(A66=0,Supuestos!$C$45,0) -> 0 | M66: =IF(A66=0,-L66,H66-I66-J66-K66) -> 176409.4 | N66: =N65+M66 -> 8054029.1 | O66: =1/(1+Supuestos!$C$46)^A66 -> 0.62092132 | P66: =M66*O66 -> 109536.36 | Q66: =Q65+P66 -> 5955041.8 | R66: =IF(AND(A66>0,N66>=0),1,0) -> 1 | S66: =IF(AND(A66>0,Q66>=0),1,0) -> 1

Sheet Escenarios
A1: Tabla comparativa de escenarios y valor esperado
A2: Vínculos (verde) a las hojas de flujo. El valor esperado pondera con las probabilidades de «Supuestos».
A4: Indicador | B4: Pesimista | C4: Realista | D4: Optimista | E4: Valor esperado
A5: Probabilidad asignada | B5: =Supuestos!C9 -> 0.3 | C5: =Supuestos!D9 -> 0.5 | D5: =Supuestos!E9 -> 0.2
A6: VAN | B6: ='Flujo Pesimista'!V8 -> -4031953.4 | C6: ='Flujo Realista'!V8 -> 487908 | D6: ='Flujo Optimista'!V8 -> 5955041.8 | E6: =SUMPRODUCT($B$5:$D$5,B6:D6) -> 225376.34
A7: VAN con revisión en el mes 12 | B7: ='Flujo Pesimista'!V28 -> -1170673.4 | C7: ='Flujo Realista'!V28 -> 487908 | D7: ='Flujo Optimista'!V28 -> 5955041.8 | E7: =SUMPRODUCT($B$5:$D$5,B7:D7) -> 1083760.3
A8: ¿Se cierra en la revisión del mes 12? | B8: ='Flujo Pesimista'!V26 -> Sí | C8: ='Flujo Realista'!V26 -> No | D8: ='Flujo Optimista'!V26 -> No
A9: TIR anual | B9: ='Flujo Pesimista'!V10 -> No existe | C9: ='Flujo Realista'!V10 -> 0.31525095 | D9: ='Flujo Optimista'!V10 -> 2.5992888
A10: Payback (meses) | B10: ='Flujo Pesimista'!V11 -> No se recupera | C10: ='Flujo Realista'!V11 -> 37 | D10: ='Flujo Optimista'!V11 -> 15
A11: Payback descontado (meses) | B11: ='Flujo Pesimista'!V12 -> No se recupera | C11: ='Flujo Realista'!V12 -> 42 | D11: ='Flujo Optimista'!V12 -> 15
A12: Punto de equilibrio (horas al mes) | B12: ='Flujo Pesimista'!V14 -> 17690.909 | C12: ='Flujo Realista'!V14 -> 4768.6275 | D12: ='Flujo Optimista'!V14 -> 5721.5686
A13: Punto de equilibrio (familias) | B13: ='Flujo Pesimista'!V15 -> 680.41958 | C13: ='Flujo Realista'!V15 -> 137.55656 | D13: ='Flujo Optimista'!V15 -> 132.0362
A14: Utilidad neta acumulada (60 meses) | B14: ='Flujo Pesimista'!V16 -> -5078090.5 | C14: ='Flujo Realista'!V16 -> 912104.2 | D14: ='Flujo Optimista'!V16 -> 8054029.1 | E14: =SUMPRODUCT($B$5:$D$5,B14:D14) -> 543430.76
A15: Utilidad neta con revisión | B15: ='Flujo Pesimista'!V29 -> -1227745.1 | C15: ='Flujo Realista'!V29 -> 912104.2 | D15: ='Flujo Optimista'!V29 -> 8054029.1 | E15: =SUMPRODUCT($B$5:$D$5,B15:D15) -> 1698534.4
A16: Requerimiento total de capital | B16: ='Flujo Pesimista'!V20 -> 585381.5 | C16: ='Flujo Realista'!V20 -> 617342 | D16: ='Flujo Optimista'!V20 -> 649302.5
A17: Déficit acumulado máximo | B17: ='Flujo Pesimista'!V21 -> 5078090.5 | C17: ='Flujo Realista'!V21 -> 823934.87 | D17: ='Flujo Optimista'!V21 -> 661900.3
A18: Familias en estado estable | B18: ='Flujo Pesimista'!V22 -> 94.15 | C18: ='Flujo Realista'!V22 -> 188.3 | D18: ='Flujo Optimista'!V22 -> 301.28
A19: Horas de cuidado al mes en estado estable | B19: ='Flujo Pesimista'!V23 -> 2447.9 | C19: ='Flujo Realista'!V23 -> 6527.7333 | D19: ='Flujo Optimista'!V23 -> 13055.467
A20: Cuidadoras empleadas en estado estable | B20: ='Flujo Pesimista'!V24 -> 19 | C20: ='Flujo Realista'!V24 -> 51 | D20: ='Flujo Optimista'!V24 -> 101
A22: Subsidio mínimo por hora para VAN ≥ 0 (realista) | B22: 38.007005
A24: Decisión recomendada
A25: INVERTIR CONDICIONADO A: (1) convenio de subsidio ≥ $40 por hora con el Sistema Público de Cuidados; (2) revisión en el mes 12 con al menos 50 % de las familias del punto de equilibrio; (3) financiamiento comprometido por el déficit acumulado máximo del escenario realista más 10 %.

Sheet Pronóstico oferta
A1: Serie semestral de la oferta de respaldo (DENUE) y pronóstico ingenuo
A2: Datos del DENUE en azul. El backtesting y los intervalos del modelo ingenuo son fórmulas; las métricas de los otros modelos se calcularon en Python (statsmodels) y se copian como valores.
A4: Índice | B4: Semestre | C4: Total de respaldo | D4: Guardería | E4: Residencia / asilo | F4: Centro de día | G4: Δ a 1 semestre | H4: Δ a 2 semestres | I4: Δ a 3 semestres
A5: 0 | B5: 2016-S1 | C5: 1337 | D5: 1144 | E5: 84 | F5: 109 | G5: =C6-C5 -> 2 | H5: =C7-C5 -> 0 | I5: =C8-C5 -> 9
A6: 1 | B6: 2016-S2 | C6: 1339 | D6: 1146 | E6: 84 | F6: 109 | G6: =C7-C6 -> -2 | H6: =C8-C6 -> 7 | I6: =C9-C6 -> 7
A7: 2 | B7: 2017-S1 | C7: 1337 | D7: 1145 | E7: 84 | F7: 108 | G7: =C8-C7 -> 9 | H7: =C9-C7 -> 9 | I7: =C10-C7 -> 9
A8: 3 | B8: 2017-S2 | C8: 1346 | D8: 1152 | E8: 87 | F8: 107 | G8: =C9-C8 -> 0 | H8: =C10-C8 -> 0 | I8: =C11-C8 -> -3
A9: 4 | B9: 2018-S1 | C9: 1346 | D9: 1152 | E9: 87 | F9: 107 | G9: =C10-C9 -> 0 | H9: =C11-C9 -> -3 | I9: =C12-C9 -> -196
A10: 5 | B10: 2018-S2 | C10: 1346 | D10: 1152 | E10: 87 | F10: 107 | G10: =C11-C10 -> -3 | H10: =C12-C10 -> -196 | I10: =C13-C10 -> -356
A11: 6 | B11: 2019-S1 | C11: 1343 | D11: 1152 | E11: 84 | F11: 107 | G11: =C12-C11 -> -193 | H11: =C13-C11 -> -353 | I11: =C14-C11 -> -351
A12: 7 | B12: 2019-S2 | C12: 1150 | D12: 936 | E12: 102 | F12: 112 | G12: =C13-C12 -> -160 | H12: =C14-C12 -> -158 | I12: =C15-C12 -> -163
A13: 8 | B13: 2020-S1 | C13: 990 | D13: 761 | E13: 105 | F13: 124 | G13: =C14-C13 -> 2 | H13: =C15-C13 -> -3 | I13: =C16-C13 -> -3
A14: 9 | B14: 2020-S2 | C14: 992 | D14: 760 | E14: 108 | F14: 124 | G14: =C15-C14 -> -5 | H14: =C16-C14 -> -5 | I14: =C17-C14 -> -6
A15: 10 | B15: 2021-S1 | C15: 987 | D15: 756 | E15: 107 | F15: 124 | G15: =C16-C15 -> 0 | H15: =C17-C15 -> -1 | I15: =C18-C15 -> -1
A16: 11 | B16: 2021-S2 | C16: 987 | D16: 756 | E16: 107 | F16: 124 | G16: =C17-C16 -> -1 | H16: =C18-C16 -> -1 | I16: =C19-C16 -> -1
... A22: 17 | B22: 2024-S2 | C22: 822 | D22: 592 | E22: 108 | F22: 122 | G22: =C23-C22 -> -9 | H22: =C24-C22 -> -9 | I22: =C25-C22 -> 16
A23: 18 | B23: 2025-S1 | C23: 813 | D23: 581 | E23: 109 | F23: 123 | G23: =C24-C23 -> 0 | H23: =C25-C23 -> 25
A24: 19 | B24: 2025-S2 | C24: 813 | D24: 581 | E24: 109 | F24: 123 | G24: =C25-C24 -> 25
A25: 20 | B25: 2026-S1 | C25: 838 | D25: 603 | E25: 109 | F25: 126
B26: Semestres sin edición (2023-S1, 2025-S2) llevan el valor anterior.
A28: Backtesting del modelo ingenuo, serie total (origen móvil)
A29: h | B29: Origen (índice) | C29: Real | D29: Pronóstico | E29: Error | F29: |Error| / Real | G29: Error²
A30: 1 | B30: 12 | C30: =INDEX($C$5:$C$25,B30+A30) -> 986 | D30: =INDEX($C$5:$C$25,B30) -> 987 | E30: =C30-D30 -> -1 | F30: =ABS(E30)/C30 -> 0.0010141988 | G30: =E30^2 -> 1
A31: 1 | B31: 13 | C31: =INDEX($C$5:$C$25,B31+A31) -> 986 | D31: =INDEX($C$5:$C$25,B31) -> 986 | E31: =C31-D31 -> 0 | F31: =ABS(E31)/C31 -> 0 | G31: =E31^2 -> 0
A32: 1 | B32: 14 | C32: =INDEX($C$5:$C$25,B32+A32) -> 986 | D32: =INDEX($C$5:$C$25,B32) -> 986 | E32: =C32-D32 -> 0 | F32: =ABS(E32)/C32 -> 0 | G32: =E32^2 -> 0
A33: 1 | B33: 15 | C33: =INDEX($C$5:$C$25,B33+A33) -> 996 | D33: =INDEX($C$5:$C$25,B33) -> 986 | E33: =C33-D33 -> 10 | F33: =ABS(E33)/C33 -> 0.010040161 | G33: =E33^2 -> 100
A34: 1 | B34: 16 | C34: =INDEX($C$5:$C$25,B34+A34) -> 994 | D34: =INDEX($C$5:$C$25,B34) -> 996 | E34: =C34-D34 -> -2 | F34: =ABS(E34)/C34 -> 0.0020120724 | G34: =E34^2 -> 4
A35: 1 | B35: 17 | C35: =INDEX($C$5:$C$25,B35+A35) -> 822 | D35: =INDEX($C$5:$C$25,B35) -> 994 | E35: =C35-D35 -> -172 | F35: =ABS(E35)/C35 -> 0.20924574 | G35: =E35^2 -> 29584
A36: 1 | B36: 18 | C36: =INDEX($C$5:$C$25,B36+A36) -> 813 | D36: =INDEX($C$5:$C$25,B36) -> 822 | E36: =C36-D36 -> -9 | F36: =ABS(E36)/C36 -> 0.011070111 | G36: =E36^2 -> 81
A37: 1 | B37: 19 | C37: =INDEX($C$5:$C$25,B37+A37) -> 813 | D37: =INDEX($C$5:$C$25,B37) -> 813 | E37: =C37-D37 -> 0 | F37: =ABS(E37)/C37 -> 0 | G37: =E37^2 -> 0
A38: 1 | B38: 20 | C38: =INDEX($C$5:$C$25,B38+A38) -> 838 | D38: =INDEX($C$5:$C$25,B38) -> 813 | E38: =C38-D38 -> 25 | F38: =ABS(E38)/C38 -> 0.029832936 | G38: =E38^2 -> 625
A39: 3 | B39: 12 | C39: =INDEX($C$5:$C$25,B39+A39) -> 986 | D39: =INDEX($C$5:$C$25,B39) -> 987 | E39: =C39-D39 -> -1 | F39: =ABS(E39)/C39 -> 0.0010141988 | G39: =E39^2 -> 1
A40: 3 | B40: 13 | C40: =INDEX($C$5:$C$25,B40+A40) -> 996 | D40: =INDEX($C$5:$C$25,B40) -> 986 | E40: =C40-D40 -> 10 | F40: =ABS(E40)/C40 -> 0.010040161 | G40: =E40^2 -> 100
A41: 3 | B41: 14 | C41: =INDEX($C$5:$C$25,B41+A41) -> 994 | D41: =INDEX($C$5:$C$25,B41) -> 986 | E41: =C41-D41 -> 8 | F41: =ABS(E41)/C41 -> 0.0080482897 | G41: =E41^2 -> 64
... A45: 3 | B45: 18 | C45: =INDEX($C$5:$C$25,B45+A45) -> 838 | D45: =INDEX($C$5:$C$25,B45) -> 822 | E45: =C45-D45 -> 16 | F45: =ABS(E45)/C45 -> 0.019093079 | G45: =E45^2 -> 256
A47: Comparación de modelos (origen móvil)
A48: Modelo | B48: h | C48: MAPE | D48: RMSE | E48: MAE | F48: Evaluaciones | G48: Origen del cálculo
A49: Ingenuo (elegido) | B49: 1 | C49: =AVERAGE(F30:F38) -> 0.029246136 | D49: =SQRT(AVERAGE(G30:G38)) -> 58.113873 | E49: =SUMPRODUCT(ABS(E30:E38))/COUNT(E30:E38) -> 24.333333 | F49: =COUNT(E30:E38) -> 9 | G49: Fórmula
A50: Deriva | B50: 1 | C50: 0.050253743 | D50: 58.621865 | E50: 44.046624 | F50: 9 | G50: Python (statsmodels), valor copiado
A51: Suavizamiento simple | B51: 1 | C51: 0.029246136 | D51: 58.113873 | E51: 24.333334 | F51: 9 | G51: Python (statsmodels), valor copiado
A52: Holt amortiguado | B52: 1 | C52: 0.049386235 | D52: 59.151467 | E52: 43.202119 | F52: 9 | G52: Python (statsmodels), valor copiado
A53: ARIMA(0,1,1) | B53: 1 | C53: 0.055205281 | D53: 72.362914 | E53: 46.037466 | F53: 9 | G53: Python (statsmodels), valor copiado
A54: Ingenuo (elegido) | B54: 3 | C54: =AVERAGE(F39:F45) -> 0.097919084 | D54: =SQRT(AVERAGE(G39:G45)) -> 115.61451 | E54: =SUMPRODUCT(ABS(E39:E45))/COUNT(E39:E45) -> 80.428571 | F54: =COUNT(E39:E45) -> 7 | G54: Fórmula
A55: Deriva | B55: 3 | C55: 0.11482348 | D55: 101.76968 | E55: 101.1943 | F55: 7 | G55: Python (statsmodels), valor copiado
A56: Suavizamiento simple | B56: 3 | C56: 0.097919083 | D56: 115.61451 | E56: 80.428571 | F56: 7 | G56: Python (statsmodels), valor copiado
A57: Holt amortiguado | B57: 3 | C57: 0.1167991 | D57: 103.76052 | E57: 102.49248 | F57: 7 | G57: Python (statsmodels), valor copiado
A58: ARIMA(0,1,1) | B58: 3 | C58: 0.12247113 | D58: 130.002 | E58: 101.1059 | F58: 7 | G58: Python (statsmodels), valor copiado
A60: Pronóstico de la oferta total de respaldo (modelo ingenuo, intervalos empíricos)
A61: Periodo | B61: h | C61: Pronóstico | D61: Lím. inf. 80 % | E61: Lím. sup. 80 % | F61: Lím. inf. 95 % | G61: Lím. sup. 95 %
A62: 2026-S2 | B62: 1 | C62: =$C$25 -> 838 | D62: =$C$25+PERCENTILE($G$5:$G$24,0.1) -> 676.8 | E62: =$C$25+PERCENTILE($G$5:$G$24,0.9) -> 847.1 | F62: =$C$25+PERCENTILE($G$5:$G$24,0.025) -> 654.975 | G62: =$C$25+PERCENTILE($G$5:$G$24,0.975) -> 855.875
A63: 2027-S1 | B63: 2 | C63: =$C$25 -> 838 | D63: =$C$25+PERCENTILE($H$5:$H$23,0.1) -> 654 | E63: =$C$25+PERCENTILE($H$5:$H$23,0.9) -> 847.2 | F63: =$C$25+PERCENTILE($H$5:$H$23,0.025) -> 555.65 | G63: =$C$25+PERCENTILE($H$5:$H$23,0.975) -> 856.25
A64: 2027-S2 | B64: 3 | C64: =$C$25 -> 838 | D64: =$C$25+PERCENTILE($I$5:$I$22,0.1) -> 595.5 | E64: =$C$25+PERCENTILE($I$5:$I$22,0.9) -> 847.3 | F64: =$C$25+PERCENTILE($I$5:$I$22,0.025) -> 484.125 | G64: =$C$25+PERCENTILE($I$5:$I$22,0.975) -> 851.45

Sheet Modelo ENUT
A1: Modelo de horas de cuidado no remunerado por mujer de 15 a 59 (regresión lineal ponderada, ENUT 2024)
A2: Coeficientes estimados en el notebook 03 (valores). La calculadora aplica el modelo a los promedios de un AGEB.
A4: Variable | B4: Descripción | C4: Coeficiente (h/semana) | D4: Construcción con el Censo 2020 | E4: Valor de ejemplo (totales CDMX) | F4: Aporte (h/semana)
A5: constante | B5: Constante | C5: 9.6878593 | D5: — | E5: 1 | F5: =C5*E5 -> 9.6878593
A6: n_0a5 | B6: Niñas y niños de 0 a 5 en el hogar | C6: 14.389333 | D6: (P_0A2 + P_3A5) / TOTHOG | E6: 0.21481294 | F6: =C6*E6 -> 3.091015
A7: n_6a14 | B7: Niñas y niños de 6 a 14 en el hogar | C7: 3.8871978 | D7: (P_6A11 + P_12A14) / TOTHOG | E7: 0.38481758 | F7: =C7*E7 -> 1.495862
A8: n_60mas | B8: Personas de 60 años o más en el hogar | C8: 1.0793328 | D8: P_60YMAS / TOTHOG | E8: 0.54116341 | F8: =C8*E8 -> 0.58409542
A9: n_disc | B9: Personas con discapacidad para bañarse, vestirse o comer en el hogar | C9: 8.0872327 | D9: PCDISC_MOT2 / TOTHOG | E9: 0.030227271 | F9: =C9*E9 -> 0.24445497
A10: tam | B10: Integrantes del hogar | C10: -1.6229281 | D10: PROM_OCUP | E10: 3.32 | F10: =C10*E10 -> -5.3881214
A11: edad_15a24 | B11: Tiene de 15 a 24 años (referencia: 25 a 49) | C11: -3.4432703 | D11: (P_15A17_F + P_18A24_F) / mujeres 15-59 | E11: 0.21543111 | F11: =C11*E11 -> -0.74178753
A12: edad_50a59 | B12: Tiene de 50 a 59 años (referencia: 25 a 49) | C12: -4.3251563 | D12: (mujeres 15-59 − P_15A49_F) / mujeres 15-59 | E12: 0.19916578 | F12: =C12*E12 -> -0.86142311
A13: ocupada | B13: Está ocupada | C13: -2.7658462 | D13: POCUPADA_F / P_12YMAS_F | E13: 0.5456323 | F13: =C13*E13 -> -1.5091351
A14: anios_esc | B14: Años de escolaridad | C14: 0.46127854 | D14: GRAPROES_F | E14: 11.32 | F14: =C14*E14 -> 5.2216731
A15: jefa_hog | B15: Vive en un hogar con jefatura femenina | C15: -2.2590595 | D15: PHOGJEF_F / POBHOG | E15: 0.37208267 | F15: =C15*E15 -> -0.84055689
A16: urbana | B16: Localidad de 100 mil habitantes o más | C16: 0.0096689921 | D16: 1 en todas las AGEB urbanas | E16: 1 | F16: =C16*E16 -> 0.0096689921
B17: Predicción del modelo (h/semana por mujer) | F17: =SUM(F5:F16) -> 10.993605
B18: Factor de calibración a la ENUT CDMX | F18: 0.85220486
B19: Predicción calibrada (h/semana por mujer) | F19: =MAX(0,F17*F18) -> 9.3688036
A21: Validación
A22: Modelo | B22: Tarea | C22: Conjunto | D22: Métrica | E22: Valor | F22: ¿Elegido?
A23: Regresión lineal | B23: Horas de cuidado por mujer (individual) | C23: Prueba (20 %) | D23: RMSE | E23: 12.559714 | F23: Sí
A24: Regresión lineal | B24: Horas de cuidado por mujer (individual) | C24: Prueba (20 %) | D24: MAE | E24: 8.2717229 | F24: Sí
A25: Regresión lineal | B25: Horas de cuidado por mujer (individual) | C25: Prueba (20 %) | D25: R2 | E25: 0.31057471 | F25: Sí
A26: Regresión lineal | B26: Horas de cuidado por mujer (individual) | C26: Validación cruzada (5 pliegues) | D26: RMSE | E26: 13.490997 | F26: Sí
A27: Regresión lineal | B27: Horas de cuidado por mujer (individual) | C27: Validación cruzada (5 pliegues) | D27: MAE | E27: 8.5881821 | F27: Sí
A28: Regresión lineal | B28: Horas de cuidado por mujer (individual) | C28: Validación cruzada (5 pliegues) | D28: R2 | E28: 0.31530786 | F28: Sí
A29: Regresión lineal | B29: Horas de cuidado por mujer (individual) | C29: Validación cruzada, desv. estándar del RMSE | D29: RMSE | E29: 0.49065114 | F29: Sí
A30: Random Forest | B30: Horas de cuidado por mujer (individual) | C30: Prueba (20 %) | D30: RMSE | E30: 12.141544 | F30: No
A31: Random Forest | B31: Horas de cuidado por mujer (individual) | C31: Prueba (20 %) | D31: MAE | E31: 7.6820177 | F31: No
A32: Random Forest | B32: Horas de cuidado por mujer (individual) | C32: Prueba (20 %) | D32: R2 | E32: 0.35571864 | F32: No
A33: Random Forest | B33: Horas de cuidado por mujer (individual) | C33: Validación cruzada (5 pliegues) | D33: RMSE | E33: 12.721425 | F33: No
A34: Random Forest | B34: Horas de cuidado por mujer (individual) | C34: Validación cruzada (5 pliegues) | D34: MAE | E34: 7.7668513 | F34: No
... A48: Random Forest (microdatos, referencia) | B48: Horas de cuidado promedio de una entidad (aplicación con el Censo) | C48: Dejando fuera una entidad (32) | D48: R2 | E48: 0.13947914 | F48: No

Sheet Riesgos
A1: Análisis de riesgos del programa
A3: Tipo | B3: Descripción | C3: Probabilidad | D3: Impacto | E3: Mitigación
A4: Mercado | B4: Menor adopción de la prevista: solo 3.2 % de las cuidadoras buscó un servicio formal y 32.2 % no contrataría ninguno (ENASIC 2022, nacional); la desconfianza en alguien ajeno es una razón citada. | C4: Media | D4: Alto | E4: Cuidadoras de las mismas colonias, verificación visible y piloto de 15 familias; revisión en el mes 12 con regla de cierre (≥ 50 % de las familias del punto de equilibrio).
A5: Mercado | B5: Los 300 Centros de Cuidado Infantil gratuitos anunciados por la CDMX (sep-2026) pueden reducir la demanda del segmento de 0 a 5 años. | C5: Media | D5: Medio | E5: Enfocar la red en personas mayores y con discapacidad y en horarios fuera de 6:30 a 18:00; presentarla como complemento del Sistema Público de Cuidados, no como competencia.
A6: Costos | B6: Aumentos del salario mínimo por encima de la tarifa (el general subió 13 % en 2026) comprimen el margen de $25.50 por hora. | C6: Alta | D6: Medio | E6: Indexar el copago y el subsidio al salario mínimo profesional del trabajo del hogar dentro del convenio.
A7: Ejecución | B7: Rotación de cuidadoras e incidentes de seguridad o maltrato en el domicilio. | C7: Media | D7: Alto | E7: Curso de 40 h, verificación de antecedentes, seguro de responsabilidad civil, protocolo de incidentes y una trabajadora social por cada 80 familias.
A8: Financiero | B8: Dependencia del subsidio: con menos de ~$38 por hora el VAN realista es negativo. | C8: Media | D8: Alto | E8: Firmar un convenio plurianual antes de la etapa 2 y buscar fuentes complementarias (donativos, responsabilidad social empresarial).
A9: Legal | B9: Tratamiento de datos sensibles (salud, discapacidad, ubicación) de familias y cuidadoras bajo la LFPDPPP vigente desde el 21 de marzo de 2025. | C9: Baja | D9: Alto | E9: Aviso de privacidad, minimización de datos, seudonimización en los indicadores y protocolo de gobernanza (entregables de la UCA de Leyes).
